Workbook
Name Slicer_Channel_Name: #N/A
Name Slicer_Channel_Name1: #N/A
Name Slicer_Delivered_Count: #N/A
Name Slicer_Delivered_Count1: #N/A
Name Slicer_Delivered_Revenue: #N/A
Name Slicer_Delivered_Revenue1: #N/A
Name Slicer_RTO_Count: #N/A
Name Slicer_RTO_Count1: #N/A
Name Slicer_RTO_Revenue: #N/A
Name Slicer_RTO_Revenue1: #N/A
Name Slicer_Total_order_count: #N/A
Name Slicer_Total_order_count1: #N/A
Name Slicer_Total_Order_Revenue: #N/A
Name Slicer_Total_Order_Revenue1: #N/A

Sheet Topsheet
G1: TCS!D2
B2: Sales summary for the month of Mid Apr-2026 | G2: Fashion_GOFPL_042026_Sales_01-15
B4: {="Common Name :- "&INDIRECT(G1)} -> Common Name :- Fashion_GOFPL_042026_Sales_01-15
B6: Order Status in Mid Apr-26 Including Prev. Month | C6: Mid Apr'26
C7: Order Count | D7: TCS Amount | E7: Sales
B8: Delivered | C8: =COUNTIFS(nykaa!F:F,Topsheet!$G$2,nykaa!AT:AT,Topsheet!B8) -> 56 | D8: =SUMIFS(nykaa!AS:AS,nykaa!F:F,Topsheet!$G$2,nykaa!AT:AT,Topsheet!B8) -> 416.05222 | E8: =D8/0.5% -> 83210.445
B9: Return | C9: =COUNTIFS(nykaa!F:F,Topsheet!$G$2,nykaa!AT:AT,Topsheet!B9) -> 10 | D9: =SUMIFS(nykaa!AS:AS,nykaa!F:F,Topsheet!$G$2,nykaa!AT:AT,Topsheet!B9) -> 0 | E9: =D9/0.5% -> 0
B10: Not Shipped | C10: =COUNTIFS(nykaa!F:F,Topsheet!$G$2,nykaa!AT:AT,Topsheet!B10) -> 9 | D10: =SUMIFS(nykaa!AS:AS,nykaa!F:F,Topsheet!$G$2,nykaa!AT:AT,Topsheet!B10) -> 0 | E10: =D10/0.5% -> 0
B11: Cancelled | C11: =COUNTIFS(nykaa!F:F,Topsheet!$G$2,nykaa!AT:AT,Topsheet!B11) -> 4 | D11: =SUMIFS(nykaa!AS:AS,nykaa!F:F,Topsheet!$G$2,nykaa!AT:AT,Topsheet!B11) -> 0 | E11: =D11/0.5% -> 0
B12: Lost | C12: =COUNTIFS(nykaa!F:F,Topsheet!$G$2,nykaa!AT:AT,Topsheet!B12) -> 0 | D12: =SUMIFS(nykaa!AS:AS,nykaa!F:F,Topsheet!$G$2,nykaa!AT:AT,Topsheet!B12) -> 0 | E12: =D12/0.5% -> 0
B13: RTO | C13: =COUNTIFS(nykaa!F:F,Topsheet!$G$2,nykaa!AT:AT,Topsheet!B13) -> 2 | D13: =SUMIFS(nykaa!AS:AS,nykaa!F:F,Topsheet!$G$2,nykaa!AT:AT,Topsheet!B13) -> 0 | E13: =D13/0.5% -> 0
B14: Shipped | C14: =COUNTIFS(nykaa!F:F,Topsheet!$G$2,nykaa!AT:AT,Topsheet!B14) -> 12 | D14: =SUMIFS(nykaa!AS:AS,nykaa!F:F,Topsheet!$G$2,nykaa!AT:AT,Topsheet!B14) -> 0 | E14: =D14/0.5% -> 0
B15: Total (Sheet ''Mid Apr_Orders") | C15: =SUM(C8:C14) -> 93 | D15: =SUM(D8:D14) -> 416.05222 | E15: =D15/0.5% -> 83210.445
B18: Final Status Deliverd & Lost - Prev. Final Status Delivered to returns = Sales | C18: Order Count | D18: Sales | E18: Diff
B20: Delivered | C20: =COUNTIFS(nykaa!F:F,Topsheet!$G$2,nykaa!AT:AT,Topsheet!B20) -> 56 | D20: =SUMIFS(nykaa!X:X,nykaa!F:F,Topsheet!$G$2,nykaa!AT:AT,Topsheet!B20) -> 83210.445 | E20: =D20-E8 -> 0
B21: Lost | C21: =COUNTIFS(nykaa!F:F,Topsheet!$G$2,nykaa!AT:AT,Topsheet!B21) -> 0 | D21: =SUMIFS(nykaa!X:X,nykaa!F:F,Topsheet!$G$2,nykaa!AT:AT,Topsheet!B21) -> 0 | E21: =D21-E12 -> 0
B22: Return | C22: =COUNTIFS(nykaa!F:F,Topsheet!$G$2,nykaa!AT:AT,Topsheet!B22) -> 10 | D22: =-SUMIFS(nykaa!X:X,nykaa!F:F,Topsheet!$G$2,nykaa!AU:AU,"Delivered") -> 0 | E22: =D22-E9 -> 0
B23: Total Net Sales | D23: =SUM(D20:D22) -> 83210.445 | E23: =D23-E15 -> 0

Sheet TCS
A1: brand | B1: parent_vendor_name | C1: Common Name | D1: Other Name | E1: Sum of TCS | F1: Sum of base_value
A2: Chelvet | B2: GOTCHA FASHIONS PVT LTD_DL | C2: GOTCHA FASHIONS PRIVATE LIMITED-NF Mid Apr-26 Sales | D2: Fashion_GOFPL_042026_Sales_01-15 | E2: 387.71324 | F2: 77542.648

Sheet nykaa
A1: Period | B1: Month | C1: parent_vendor_code | D1: parent_vendor_name | E1: Common Name | F1: Other Name | G1: nykaa_orderno | H1: externorderno | I1: eretail_orderno | J1: product_sku | K1: product_name | L1: brand | M1: hsn_code | N1: mrp_per_unit | O1: dp_per_unit | P1: sp_per_unit | Q1: dp_per_unit_brand | R1: DP Nykaa Funded | S1: DP Brand Funded | T1: SP Coupon Nykaa Funded | U1: SP Brand Funded | V1: NSV= Net Sale Value | W1: taxable_amount | X1: base_value | Y1: tax_amount | Z1: tax_percent | AA1: cgst | AB1: sgst | AC1: ugst | AD1: igst | AE1: order_shipping_city | AF1: order_shipping_state | AG1: order_type | AH1: Child Vendor GST | AI1: invoiceno | AJ1: tracking_no | AK1: return_awb | AL1: order_date | AM1: ship_date | AN1: delivery_date | AO1: Quantity | AP1: Rule Name | AQ1: Yes or No | AR1: CountIF | AS1: TCS | AT1: FinalStatus | AU1: Previous Final Status
A2: APRIL_1_to_15_Orders | B2: 4 | C2: GOFPL | D2: GOTCHA FASHIONS PVT LTD_DL | E2: GOTCHA FASHIONS PRIVATE LIMITED-NF Mid Apr-26 Sales | F2: Fashion_GOFPL_042026_Sales_01-15 | G2: NYK-38112834-8327464 | H2: NYK-38112834-8327464-2-1 | I2: NYKF42123624 | J2: CHELV00001661 | K2: Chelvet Purple Satin Shirt With Pyjama (M) | L2: Chelvet | M2: 62082200 | N2: 2999 | O2: 2999 | P2: 2922.58 | Q2: 2999 | R2: 0 | S2: 0 | T2: 76.419998 | U2: 0 | V2: 2999 | W2: 2999 | X2: 2541.525 | Y2: 457.475 | Z2: 18 | AA2: 0 | AB2: 0 | AC2: 0 | AD2: 457.475 | AE2: Raipur | AF2: Chhattisgarh | AG2: COD | AH2: 09AALCG0172B1ZW | AI2: GOFPL2709100150 | AJ2: 28449601682033 | AL2: 46117.474 | AM2: 46118.618 | AN2: 46122.614 | AO2: 1 | AP2: Dynamic RB Paltform wide:Extra 10% off upto 270 on 1700 : 3 PV | AQ2: Yes | AR2: 3 | AS2: 12.707625 | AT2: Delivered
A3: APRIL_1_to_15_Orders | B3: 4 | C3: GOFPL | D3: GOTCHA FASHIONS PVT LTD_DL | E3: GOTCHA FASHIONS PRIVATE LIMITED-NF Mid Apr-26 Sales | F3: Fashion_GOFPL_042026_Sales_01-15 | G3: NYK-37984287-4482735 | H3: NYK-37984287-4482735-1-1 | I3: NYKF41978771 | J3: CHELV00001011 | K3: Chelvet Non-Wired Seamless Finish Plunge Bra (32B) | L3: Chelvet | M3: 62121000 | N3: 1849 | O3: 1295 | P3: 1229.34 | Q3: 1295 | R3: 0 | S3: 554 | T3: 65.660004 | U3: 0 | V3: 1295 | W3: 1295 | X3: 1233.333 | Y3: 61.667 | Z3: 5 | AA3: 0 | AB3: 0 | AC3: 0 | AD3: 61.667 | AE3: Faridabad | AF3: Haryana | AG3: Prepaid | AH3: 07AALCG0172B1Z0 | AL3: 46113.494 | AO3: 1 | AP3: Dynamic IOC1 & 2: Extra 10% off upto Rs 250 on 2000 | AQ3: Yes | AR3: 1 | AS3: 0 | AT3: Not Shipped
A4: APRIL_1_to_15_Orders | B4: 4 | C4: GOFPL | D4: GOTCHA FASHIONS PVT LTD_DL | E4: GOTCHA FASHIONS PRIVATE LIMITED-NF Mid Apr-26 Sales | F4: Fashion_GOFPL_042026_Sales_01-15 | G4: NYK-38130788-0594892 | H4: NYK-38130788-0594892-1-1 | I4: NYKF42144141 | J4: CHELV00002258 | K4: Chelvet Satin Lace Midi Dress with Robe (M) | L4: Chelvet | M4: 61091000 | N4: 2750 | O4: 1760 | P4: 1760 | Q4: 1760 | R4: 0 | S4: 990 | T4: 0 | U4: 0 | V4: 1760 | W4: 1760 | X4: 1676.19 | Y4: 83.81 | Z4: 5 | AA4: 0 | AB4: 0 | AC4: 0 | AD4: 83.81 | AE4: Bangalore | AF4: Karnataka | AG4: COD | AH4: 09AALCG0172B1ZW | AL4: 46117.847 | AO4: 1 | AQ4: Yes | AR4: 3 | AS4: 0 | AT4: Cancelled
A5: APRIL_1_to_15_Orders | B5: 4 | C5: GOFPL | D5: GOTCHA FASHIONS PVT LTD_DL | E5: GOTCHA FASHIONS PRIVATE LIMITED-NF Mid Apr-26 Sales | F5: Fashion_GOFPL_042026_Sales_01-15 | G5: NYK-37999926-8439694 | H5: NYK-37999926-8439694-2-1 | I5: NYKF41996559 | J5: CHELV00001423 | K5: Chelvet Women Pink Velvet Solid Jacket with Pyjama (L) | L5: Chelvet | M5: 61083100 | N5: 5099 | O5: 3213 | P5: 3213 | Q5: 3213 | R5: 0 | S5: 1886 | T5: 0 | U5: 0 | V5: 3213 | W5: 3213 | X5: 2722.881 | Y5: 490.119 | Z5: 18 | AA5: 0 | AB5: 0 | AC5: 0 | AD5: 490.119 | AE5: Mumbai | AF5: Maharashtra | AG5: Prepaid | AH5: 09AALCG0172B1ZW | AI5: GOFPL2709100137 | AJ5: 28449609598716 | AL5: 46113.887 | AM5: 46114.606 | AN5: 46118.641 | AO5: 1 | AQ5: Yes | AR5: 1 | AS5: 13.614405 | AT5: Delivered
A6: APRIL_1_to_15_Orders | B6: 4 | C6: GOFPL | D6: GOTCHA FASHIONS PVT LTD_DL | E6: GOTCHA FASHIONS PRIVATE LIMITED-NF Mid Apr-26 Sales | F6: Fashion_GOFPL_042026_Sales_01-15 | G6: NYK-38430708-8077330 | H6: NYK-38430708-8077330-1-1 | I6: NYKF42488214 | J6: CHELV00002421 | K6: Chelvet Red Non-Padded Non-Wired Lace Bra (36D) | L6: Chelvet | M6: 62121000 | N6: 1499 | O6: 900 | P6: 900 | Q6: 900 | R6: 0 | S6: 599 | T6: 0 | U6: 0 | V6: 900 | W6: 900 | X6: 857.143 | Y6: 42.857 | Z6: 5 | AA6: 0 | AB6: 0 | AC6: 0 | AD6: 42.857 | AE6: Bhubaneswar | AF6: Orissa | AG6: Prepaid | AH6: 09AALCG0172B1ZW | AI6: GOFPL2709100167 | AJ6: 88364570486 | AL6: 46125.92 | AM6: 46127.661 | AO6: 1 | AQ6: Yes | AR6: 1 | AS6: 0 | AT6: Shipped
A7: APRIL_1_to_15_Orders | B7: 4 | C7: GOFPL | D7: GOTCHA FASHIONS PVT LTD_DL | E7: GOTCHA FASHIONS PRIVATE LIMITED-NF Mid Apr-26 Sales | F7: Fashion_GOFPL_042026_Sales_01-15 | G7: NYK-38166264-2307271 | H7: NYK-38166264-2307271-1-1 | I7: NYKF42184995 | J7: CHELV00000924 | K7: Chelvet Underwired Lightly Padded Demi Cup Bra (32C) | L7: Chelvet | M7: 62121000 | N7: 1699 | O7: 1394 | P7: 1394 | Q7: 1394 | R7: 0 | S7: 305 | T7: 0 | U7: 0 | V7: 1394 | W7: 1394 | X7: 1327.619 | Y7: 66.381 | Z7: 5 | AA7: 0 | AB7: 0 | AC7: 0 | AD7: 66.381 | AE7: Cochin | AF7: Kerala | AG7: COD | AH7: 07AALCG0172B1Z0 | AI7: GOFPL2707100604 | AJ7: 28449601872304 | AL7: 46118.909 | AM7: 46121.496 | AN7: 46125.605 | AO7: 1 | AQ7: Yes | AR7: 1 | AS7: 6.638095 | AT7: Delivered
A8: APRIL_1_to_15_Orders | B8: 4 | C8: GOFPL | D8: GOTCHA FASHIONS PVT LTD_DL | E8: GOTCHA FASHIONS PRIVATE LIMITED-NF Mid Apr-26 Sales | F8: Fashion_GOFPL_042026_Sales_01-15 | G8: NYK-38149484-7129408 | H8: NYK-38149484-7129408-1-1 | I8: NYKF42165824 | J8: CHELV00000478 | K8: Chelvet Women Black Medium Coverage Non-Wired Lightly Padded Everyday Bra (36C) | L8: Chelvet | M8: 62121000 | N8: 1749 | O8: 1400 | P8: 1352.42 | Q8: 1400 | R8: 0 | S8: 349 | T8: 47.580002 | U8: 0 | V8: 1400 | W8: 1400 | X8: 1333.333 | Y8: 66.667 | Z8: 5 | AA8: 0 | AB8: 0 | AC8: 0 | AD8: 66.667 | AE8: Hyderabad | AF8: Telangana | AG8: Prepaid | AH8: 07AALCG0172B1Z0 | AL8: 46118.501 | AO8: 1 | AQ8: Yes | AR8: 2 | AS8: 0 | AT8: Not Shipped
A9: APRIL_1_to_15_Orders | B9: 4 | C9: GOFPL | D9: GOTCHA FASHIONS PVT LTD_DL | E9: GOTCHA FASHIONS PRIVATE LIMITED-NF Mid Apr-26 Sales | F9: Fashion_GOFPL_042026_Sales_01-15 | G9: NYK-38465841-6352996 | H9: NYK-38465841-6352996-1-1 | I9: NYKF42528705 | J9: CHELV00001573 | K9: Chelvet Women Light Pink Seamless Padded Pull On Bra (L) | L9: Chelvet | M9: 62121000 | N9: 2540 | O9: 1499 | P9: 1499 | Q9: 1499 | R9: 0 | S9: 1041 | T9: 0 | U9: 0 | V9: 1499 | W9: 1499 | X9: 1427.619 | Y9: 71.381 | Z9: 5 | AA9: 35.691 | AB9: 35.691 | AC9: 0 | AD9: 0 | AE9: Agra | AF9: Uttar Pradesh | AG9: Prepaid | AH9: 09AALCG0172B1ZW | AI9: GOFPL2709100169 | AJ9: SF2188751540NYK | AL9: 46126.826 | AM9: 46127.558 | AO9: 1 | AQ9: Yes | AR9: 1 | AS9: 0 | AT9: Shipped
A10: APRIL_1_to_15_Orders | B10: 4 | C10: GOFPL | D10: GOTCHA FASHIONS PVT LTD_DL | E10: GOTCHA FASHIONS PRIVATE LIMITED-NF Mid Apr-26 Sales | F10: Fashion_GOFPL_042026_Sales_01-15 | G10: NYK-38129696-8729519 | H10: NYK-38129696-8729519-3-1 | I10: NYKF42142936 | J10: CHELV00002403 | K10: Chelvet Nude Non-Padded Non-Wired Lace Bra (32D) | L10: Chelvet | M10: 62121000 | N10: 1499 | O10: 900 | P10: 852.13 | Q10: 900 | R10: 0 | S10: 599 | T10: 47.869999 | U10: 0 | V10: 900 | W10: 900 | X10: 857.143 | Y10: 42.857 | Z10: 5 | AA10: 0 | AB10: 0 | AC10: 0 | AD10: 42.857 | AE10: Bangalore | AF10: Karnataka | AG10: COD | AH10: 09AALCG0172B1ZW | AI10: GOFPL2709100145 | AJ10: 28449601680854 | AL10: 46117.826 | AM10: 46119.685 | AN10: 46125.888 | AO10: 1 | AQ10: Yes | AR10: 1 | AS10: 4.285715 | AT10: Delivered
A11: APRIL_1_to_15_Orders | B11: 4 | C11: GOFPL | D11: GOTCHA FASHIONS PVT LTD_DL | E11: GOTCHA FASHIONS PRIVATE LIMITED-NF Mid Apr-26 Sales | F11: Fashion_GOFPL_042026_Sales_01-15 | G11: NYK-38307031-8860236 | H11: NYK-38307031-8860236-1-1 | I11: NYKF42345044 | J11: CHELV00001355 | K11: Chelvet Women Pink Satin Solid Nightdress with Robe and Belt (M) | L11: Chelvet | M11: 62082200 | N11: 5699 | O11: 3819 | P11: 3539 | Q11: 3819 | R11: 0 | S11: 1880 | T11: 280 | U11: 0 | V11: 3819 | W11: 3819 | X11: 3236.441 | Y11: 582.559 | Z11: 18 | AA11: 0 | AB11: 0 | AC11: 0 | AD11: 582.559 | AE11: Chennai | AF11: Tamil Nadu | AG11: Prepaid | AH11: 09AALCG0172B1ZW | AI11: GOFPL2709100163 | AJ11: 88364307043 | AL11: 46122.92 | AM11: 46127.661 | AO11: 1 | AQ11: Yes | AR11: 1 | AS11: 0 | AT11: Shipped
A12: APRIL_1_to_15_Orders | B12: 4 | C12: GOFPL | D12: GOTCHA FASHIONS PVT LTD_DL | E12: GOTCHA FASHIONS PRIVATE LIMITED-NF Mid Apr-26 Sales | F12: Fashion_GOFPL_042026_Sales_01-15 | G12: NYK-38283607-0081774 | H12: NYK-38283607-0081774-1-1 | I12: NYKF42318257 | J12: CHELV00002248 | K12: Chelvet Floral Strappy Nightdress and Full Sleeve Robe (M) | L12: Chelvet | M12: 61091000 | N12: 4950 | O12: 3168 | P12: 2888 | Q12: 3168 | R12: 0 | S12: 1782 | T12: 280 | U12: 0 | V12: 3168 | W12: 3168 | X12: 2684.746 | Y12: 483.254 | Z12: 18 | AA12: 0 | AB12: 0 | AC12: 0 | AD12: 483.254 | AE12: Bangalore | AF12: Karnataka | AG12: COD | AH12: 09AALCG0172B1ZW | AI12: GOFPL2709100162 | AJ12: 59695181302 | AL12: 46122.471 | AM12: 46127.661 | AO12: 1 | AQ12: Yes | AR12: 1 | AS12: 0 | AT12: Shipped
A13: APRIL_1_to_15_Orders | B13: 4 | C13: GOFPL | D13: GOTCHA FASHIONS PVT LTD_DL | E13: GOTCHA FASHIONS PRIVATE LIMITED-NF Mid Apr-26 Sales | F13: Fashion_GOFPL_042026_Sales_01-15 | G13: NYK-38310048-3098293 | H13: NYK-38310048-3098293-1-1 | I13: NYKF42348508 | J13: CHELV00001169 | K13: Chelvet Non-Wired Medium Coverage T-Shirt Bra (34D) | L13: Chelvet | M13: 62121000 | N13: 1849 | O13: 1054 | P13: 1054 | Q13: 1054 | R13: 0 | S13: 795 | T13: 0 | U13: 0 | V13: 1054 | W13: 1054 | X13: 1003.81 | Y13: 50.19 | Z13: 5 | AA13: 0 | AB13: 0 | AC13: 0 | AD13: 50.19 | AE13: Kolkata | AF13: West Bengal | AG13: Prepaid | AH13: 07AALCG0172B1Z0 | AI13: GOFPL2707100608 | AJ13: 88364286872 | AL13: 46122.969 | AM13: 46123.685 | AN13: 46124.759 | AO13: 1 | AQ13: Yes | AR13: 1 | AS13: 5.01905 | AT13: Delivered
A14: APRIL_1_to_15_Orders | B14: 4 | C14: GOFPL | D14: GOTCHA FASHIONS PVT LTD_DL | E14: GOTCHA FASHIONS PRIVATE LIMITED-NF Mid Apr-26 Sales | F14: Fashion_GOFPL_042026_Sales_01-15 | G14: NYK-38112834-8327464 | H14: NYK-38112834-8327464-2-1 | I14: NYKF42123624 | J14: CHELV00001673 | K14: Chelvet White Satin Shirt With Pyjama (M) | L14: Chelvet | M14: 62082200 | N14: 2999 | O14: 2999 | P14: 2922.58 | Q14: 2999 | R14: 0 | S14: 0 | T14: 76.419998 | U14: 0 | V14: 2999 | W14: 2999 | X14: 2541.525 | Y14: 457.475 | Z14: 18 | AA14: 0 | AB14: 0 | AC14: 0 | AD14: 457.475 | AE14: Raipur | AF14: Chhattisgarh | AG14: COD | AH14: 09AALCG0172B1ZW | AI14: GOFPL2709100150 | AJ14: 28449601682033 | AL14: 46117.474 | AM14: 46118.618 | AN14: 46122.614 | AO14: 1 | AP14: Dynamic RB Paltform wide:Extra 10% off upto 270 on 1700 : 3 PV | AQ14: Yes | AR14: 3 | AS14: 12.707625 | AT14: Delivered
A15: APRIL_1_to_15_Orders | B15: 4 | C15: GOFPL | D15: GOTCHA FASHIONS PVT LTD_DL | E15: GOTCHA FASHIONS PRIVATE LIMITED-NF Mid Apr-26 Sales | F15: Fashion_GOFPL_042026_Sales_01-15 | G15: NYK-38274618-4377193 | H15: NYK-38274618-4377193-1-1 | I15: NYKF42308192 | J15: CHELV00001109 | K15: Chelvet Push-Up Non wired Medium Coverage Bra (38D) | L15: Chelvet | M15: 62121000 | N15: 1749 | O15: 1050 | P15: 1050 | Q15: 1050 | R15: 0 | S15: 699 | T15: 0 | U15: 0 | V15: 1050 | W15: 1050 | X15: 1000 | Y15: 50 | Z15: 5 | AA15: 0 | AB15: 0 | AC15: 0 | AD15: 50 | AE15: Aligarh | AF15: Uttar Pradesh | AG15: COD | AH15: 07AALCG0172B1Z0 | AI15: GOFPL2707100606 | AJ15: NKFC0000459950 | AL15: 46122.058 | AM15: 46122.548 | AN15: 46124.73 | AO15: 1 | AQ15: Yes | AR15: 3 | AS15: 5 | AT15: Delivered
A16: APRIL_1_to_15_Orders | B16: 4 | C16: GOFPL | D16: GOTCHA FASHIONS PVT LTD_DL | E16: GOTCHA FASHIONS PRIVATE LIMITED-NF Mid Apr-26 Sales | F16: Fashion_GOFPL_042026_Sales_01-15 | G16: NYK-38416538-3363882 | H16: NYK-38416538-3363882-1-1 | I16: NYKF42472137 | J16: CHELV00000062 | K16: Chelvet Solid Lightly Padded Half Coverage Plunge Bra (36C) | L16: Chelvet | M16: 61089100 | N16: 1499 | O16: 1050 | P16: 892.5 | Q16: 1050 | R16: 0 | S16: 449 | T16: 157.5 | U16: 0 | V16: 1050 | W16: 1050 | X16: 1000 | Y16: 50 | Z16: 5 | AA16: 0 | AB16: 0 | AC16: 0 | AD16: 50 | AE16: Bangalore | AF16: Karnataka | AG16: Prepaid | AH16: 07AALCG0172B1Z0 | AI16: GOFPL2707100616 | AJ16: 88364558645 | AL16: 46125.634 | AM16: 46126.637 | AO16: 1 | AQ16: Yes | AR16: 1 | AS16: 0 | AT16: Shipped
A17: APRIL_1_to_15_Orders | B17: 4 | C17: GOFPL | D17: GOTCHA FASHIONS PVT LTD_DL | E17: GOTCHA FASHIONS PRIVATE LIMITED-NF Mid Apr-26 Sales | F17: Fashion_GOFPL_042026_Sales_01-15 | G17: NYK-38046081-9372889 | H17: NYK-38046081-9372889-2-1 | I17: NYKF42047886 | J17: CHELV00002055 | K17: Chelvet Women Padded Non-Wired Lace Black Bralette (36D) | L17: Chelvet | M17: 62121000 | N17: 2299 | O17: 1495 | P17: 1407.22 | Q17: 1495 | R17: 0 | S17: 804 | T17: 87.779999 | U17: 0 | V17: 1495 | W17: 1495 | X17: 1423.81 | Y17: 71.19 | Z17: 5 | AA17: 0 | AB17: 0 | AC17: 0 | AD17: 71.19 | AE17: Siliguri | AF17: West Bengal | AG17: COD | AH17: 09AALCG0172B1ZW | AI17: GOFPL2709100141 | AJ17: 28449601497760 | AL17: 46115.518 | AM17: 46116.633 | AN17: 46119.613 | AO17: 1 | AQ17: Yes | AR17: 1 | AS17: 7.11905 | AT17: Delivered
A18: APRIL_1_to_15_Orders | B18: 4 | C18: GOFPL | D18: GOTCHA FASHIONS PVT LTD_DL | E18: GOTCHA FASHIONS PRIVATE LIMITED-NF Mid Apr-26 Sales | F18: Fashion_GOFPL_042026_Sales_01-15 | G18: NYK-38106346-6283082 | H18: NYK-38106346-6283082-2-1 | I18: NYKF42116285 | J18: CHELV00001107 | K18: Chelvet Push-Up Non wired Medium Coverage Bra (38B) | L18: Chelvet | M18: 62121000 | N18: 1749 | O18: 1050 | P18: 1050 | Q18: 1050 | R18: 0 | S18: 699 | T18: 0 | U18: 0 | V18: 1050 | W18: 1050 | X18: 1000 | Y18: 50 | Z18: 5 | AA18: 0 | AB18: 0 | AC18: 0 | AD18: 50 | AE18: Faridabad | AF18: Haryana | AG18: Prepaid | AH18: 07AALCG0172B1Z0 | AI18: GOFPL2707100599 | AJ18: SF2188733487NYK | AL18: 46117.103 | AM18: 46119.621 | AN18: 46120.909 | AO18: 1 | AQ18: Yes | AR18: 1 | AS18: 5 | AT18: Delivered
A19: APRIL_1_to_15_Orders | B19: 4 | C19: GOFPL | D19: GOTCHA FASHIONS PVT LTD_DL | E19: GOTCHA FASHIONS PRIVATE LIMITED-NF Mid Apr-26 Sales | F19: Fashion_GOFPL_042026_Sales_01-15 | G19: NYK-38271552-8059338 | H19: NYK-38271552-8059338-1-1 | I19: NYKF42304631 | J19: CHELV00000267 | K19: Chelvet Peach Solid Workout Bra (34D) | L19: Chelvet | M19: 62121000 | N19: 1599 | O19: 1056 | P19: 1056 | Q19: 1056 | R19: 0 | S19: 543 | T19: 0 | U19: 0 | V19: 1056 | W19: 1056 | X19: 1005.714 | Y19: 50.286 | Z19: 5 | AA19: 0 | AB19: 0 | AC19: 0 | AD19: 50.286 | AE19: Godhra | AF19: Gujarat | AG19: COD | AH19: 07AALCG0172B1Z0 | AI19: GOFPL2707100605 | AJ19: 28449601942901 | AL19: 46121.984 | AM19: 46122.489 | AO19: 1 | AQ19: Yes | AR19: 1 | AS19: 0 | AT19: RTO
A20: APRIL_1_to_15_Orders | B20: 4 | C20: GOFPL | D20: GOTCHA FASHIONS PVT LTD_DL | E20: GOTCHA FASHIONS PRIVATE LIMITED-NF Mid Apr-26 Sales | F20: Fashion_GOFPL_042026_Sales_01-15 | G20: NYK-37978882-9341965 | H20: NYK-37978882-9341965-1-1 | I20: NYKF41973053 | J20: CHELV00000919 | K20: Chelvet Underwired Lightly Padded Demi Cup Bra (36D) | L20: Chelvet | M20: 62121000 | N20: 1699 | O20: 1394 | P20: 1394 | Q20: 1394 | R20: 0 | S20: 305 | T20: 0 | U20: 0 | V20: 1394 | W20: 1394 | X20: 1327.619 | Y20: 66.381 | Z20: 5 | AA20: 0 | AB20: 0 | AC20: 0 | AD20: 66.381 | AE20: Basna | AF20: Chhattisgarh | AG20: COD | AH20: 07AALCG0172B1Z0 | AI20: GOFPL2707100591 | AJ20: 28449601317134 | AL20: 46113.319 | AM20: 46113.481 | AN20: 46115.733 | AO20: 1 | AQ20: Yes | AR20: 2 | AS20: 6.638095 | AT20: Delivered
A21: APRIL_1_to_15_Orders | B21: 4 | C21: GOFPL | D21: GOTCHA FASHIONS PVT LTD_DL | E21: GOTCHA FASHIONS PRIVATE LIMITED-NF Mid Apr-26 Sales | F21: Fashion_GOFPL_042026_Sales_01-15 | G21: NYK-38385468-3479391 | H21: NYK-38385468-3479391-2-1 | I21: NYKF42435601 | J21: CHELV00000227 | K21: Chelvet Solid Lightly Padded Half Coverage Plunge Bra (36D) | L21: Chelvet | M21: 61089100 | N21: 1499 | O21: 1050 | P21: 1050 | Q21: 1050 | R21: 0 | S21: 449 | T21: 0 | U21: 0 | V21: 1050 | W21: 1050 | X21: 1000 | Y21: 50 | Z21: 5 | AA21: 0 | AB21: 0 | AC21: 0 | AD21: 50 | AE21: Jaipur | AF21: Rajasthan | AG21: Prepaid | AH21: 07AALCG0172B1Z0 | AI21: GOFPL2707100612 | AJ21: NKFP0000533379 | AK21: R2011711627NYK | AL21: 46124.825 | AM21: 46125.567 | AN21: 46127.494 | AO21: 1 | AQ21: Yes | AR21: 1 | AS21: 0 | AT21: Return
A22: APRIL_1_to_15_Orders | B22: 4 | C22: GOFPL | D22: GOTCHA FASHIONS PVT LTD_DL | E22: GOTCHA FASHIONS PRIVATE LIMITED-NF Mid Apr-26 Sales | F22: Fashion_GOFPL_042026_Sales_01-15 | G22: NYK-38130788-0594892 | H22: NYK-38130788-0594892-1-1 | I22: NYKF42144141 | J22: CHELV00002308 | K22: Chelvet Collared Full-Sleeve Shirt and Pyjama Burgundy (M) | L22: Chelvet | M22: 61091000 | N22: 4400 | O22: 2816 | P22: 2816 | Q22: 2816 | R22: 0 | S22: 1584 | T22: 0 | U22: 0 | V22: 2816 | W22: 2816 | X22: 2386.441 | Y22: 429.559 | Z22: 18 | AA22: 0 | AB22: 0 | AC22: 0 | AD22: 429.559 | AE22: Bangalore | AF22: Karnataka | AG22: COD | AH22: 09AALCG0172B1ZW | AL22: 46117.847 | AO22: 1 | AQ22: Yes | AR22: 3 | AS22: 0 | AT22: Cancelled
A23: APRIL_1_to_15_Orders | B23: 4 | C23: GOFPL | D23: GOTCHA FASHIONS PVT LTD_DL | E23: GOTCHA FASHIONS PRIVATE LIMITED-NF Mid Apr-26 Sales | F23: Fashion_GOFPL_042026_Sales_01-15 | G23: NYK-38142305-4246438 | H23: NYK-38142305-4246438-3-1 | I23: NYKF42157848 | J23: CHELV00001325 | K23: Chelvet Women Off White Satin Embroidered Nightdress (XL) | L23: Chelvet | M23: 62082200 | N23: 4299 | O23: 2881 | P23: 2881 | Q23: 2881 | R23: 0 | S23: 1418 | T23: 0 | U23: 0 | V23: 2881 | W23: 2881 | X23: 2441.525 | Y23: 439.475 | Z23: 18 | AA23: 0 | AB23: 0 | AC23: 0 | AD23: 439.475 | AE23: Chennai | AF23: Tamil Nadu | AG23: Prepaid | AH23: 09AALCG0172B1ZW | AI23: GOFPL2709100143 | AJ23: 28449602083785 | AL23: 46118.121 | AM23: 46118.618 | AN23: 46120.737 | AO23: 1 | AQ23: Yes | AR23: 1 | AS23: 12.207625 | AT23: Delivered
A24: APRIL_1_to_15_Orders | B24: 4 | C24: GOFPL | D24: GOTCHA FASHIONS PVT LTD_DL | E24: GOTCHA FASHIONS PRIVATE LIMITED-NF Mid Apr-26 Sales | F24: Fashion_GOFPL_042026_Sales_01-15 | G24: NYK-38323114-6441537 | H24: NYK-38323114-6441537-4-1 | I24: NYKF42363266 | J24: CHELV00001011 | K24: Chelvet Non-Wired Seamless Finish Plunge Bra (32B) | L24: Chelvet | M24: 62121000 | N24: 1849 | O24: 1295 | P24: 1202.95 | Q24: 1295 | R24: 0 | S24: 554 | T24: 92.050003 | U24: 0 | V24: 1295 | W24: 1295 | X24: 1233.333 | Y24: 61.667 | Z24: 5 | AA24: 0 | AB24: 0 | AC24: 0 | AD24: 61.667 | AE24: Nagaur | AF24: Rajasthan | AG24: Prepaid | AH24: 07AALCG0172B1Z0 | AL24: 46123.47 | AO24: 1 | AQ24: Yes | AR24: 1 | AS24: 0 | AT24: Not Shipped
A25: APRIL_1_to_15_Orders | B25: 4 | C25: GOFPL | D25: GOTCHA FASHIONS PVT LTD_DL | E25: GOTCHA FASHIONS PRIVATE LIMITED-NF Mid Apr-26 Sales | F25: Fashion_GOFPL_042026_Sales_01-15 | G25: NYK-38252658-2942706 | H25: NYK-38252658-2942706-1-1 | I25: NYKF42283181 | J25: CHELV00002389 | K25: Chelvet Black Non-Padded Non-Wired Lace Bra (32B) | L25: Chelvet | M25: 62121000 | N25: 1499 | O25: 900 | P25: 900 | Q25: 900 | R25: 0 | S25: 599 | T25: 0 | U25: 0 | V25: 900 | W25: 900 | X25: 857.143 | Y25: 42.857 | Z25: 5 | AA25: 0 | AB25: 0 | AC25: 0 | AD25: 42.857 | AE25: Himmatnagar | AF25: Gujarat | AG25: Prepaid | AH25: 09AALCG0172B1ZW | AI25: GOFPL2709100159 | AJ25: 28449602338736 | AL25: 46121.578 | AM25: 46122.65 | AN25: 46126.449 | AO25: 1 | AQ25: Yes | AR25: 1 | AS25: 4.285715 | AT25: Delivered
A26: APRIL_1_to_15_Orders | B26: 4 | C26: GOFPL | D26: GOTCHA FASHIONS PVT LTD_DL | E26: GOTCHA FASHIONS PRIVATE LIMITED-NF Mid Apr-26 Sales | F26: Fashion_GOFPL_042026_Sales_01-15 | G26: NYK-38055810-7290756 | H26: NYK-38055810-7290756-1-1 | I26: NYKF42145480 | J26: CHELV00002434 | K26: Chelvet Black Non-Padded Non-Wired Lace Bra (38B) | L26: Chelvet | M26: 62121000 | N26: 1499 | O26: 900 | P26: 900 | Q26: 900 | R26: 0 | S26: 599 | T26: 0 | U26: 0 | V26: 900 | W26: 900 | X26: 857.143 | Y26: 42.857 | Z26: 5 | AA26: 0 | AB26: 0 | AC26: 0 | AD26: 42.857 | AE26: Bangalore | AF26: Karnataka | AG26: Prepaid | AH26: 09AALCG0172B1ZW | AI26: GOFPL2709100152 | AJ26: 28449602082982 | AL26: 46115.726 | AM26: 46119.685 | AN26: 46121.664 | AO26: 1 | AQ26: Yes | AR26: 1 | AS26: 4.285715 | AT26: Delivered
A27: APRIL_1_to_15_Orders | B27: 4 | C27: GOFPL | D27: GOTCHA FASHIONS PVT LTD_DL | E27: GOTCHA FASHIONS PRIVATE LIMITED-NF Mid Apr-26 Sales | F27: Fashion_GOFPL_042026_Sales_01-15 | G27: NYK-38313689-9120998 | H27: NYK-38313689-9120998-5-1 | I27: NYKF42352757 | J27: CHELV00000212 | K27: Chelvet Lightly Padded Classic T-Shirt Bra (34B) | L27: Chelvet | M27: 61089100 | N27: 1899 | O27: 1406 | P27: 1406 | Q27: 1406 | R27: 0 | S27: 493 | T27: 0 | U27: 0 | V27: 1406 | W27: 1406 | X27: 1339.048 | Y27: 66.952 | Z27: 5 | AA27: 0 | AB27: 0 | AC27: 0 | AD27: 66.952 | AE27: Hyderabad | AF27: Telangana | AG27: COD | AH27: 07AALCG0172B1Z0 | AI27: GOFPL2707100609 | AJ27: 59695211752 | AL27: 46123.038 | AM27: 46123.685 | AN27: 46124.586 | AO27: 1 | AQ27: Yes | AR27: 1 | AS27: 6.69524 | AT27: Delivered
A28: APRIL_1_to_15_Orders | B28: 4 | C28: GOFPL | D28: GOTCHA FASHIONS PVT LTD_DL | E28: GOTCHA FASHIONS PRIVATE LIMITED-NF Mid Apr-26 Sales | F28: Fashion_GOFPL_042026_Sales_01-15 | G28: NYK-38485322-8493652 | H28: NYK-38485322-8493652-6-1 | I28: NYKF42551518 | J28: CHELV00000407 | K28: Chelvet Olive Ultra-Soft Lightly Padded Non-Wired Everyday Bra - Medium Coverage (32C) | L28: Chelvet | M28: 62121000 | N28: 1849 | O28: 1406 | P28: 1384.13 | Q28: 1406 | R28: 0 | S28: 443 | T28: 21.870001 | U28: 0 | V28: 1406 | W28: 1406 | X28: 1339.048 | Y28: 66.952 | Z28: 5 | AA28: 0 | AB28: 0 | AC28: 0 | AD28: 66.952 | AE28: Mumbai | AF28: Maharashtra | AG28: Prepaid | AH28: 07AALCG0172B1Z0 | AL28: 46127.429 | AO28: 1 | AQ28: Yes | AR28: 1 | AS28: 0 | AT28: Not Shipped
A29: APRIL_1_to_15_Orders | B29: 4 | C29: GOFPL | D29: GOTCHA FASHIONS PVT LTD_DL | E29: GOTCHA FASHIONS PRIVATE LIMITED-NF Mid Apr-26 Sales | F29: Fashion_GOFPL_042026_Sales_01-15 | G29: NYK-38025780-6136753 | H29: NYK-38025780-6136753-2-1 | I29: NYKF42025249 | J29: CHELV00002004 | K29: Chelvet Non-Padded Underwired Lace Bra and Brief (34B) | L29: Chelvet | M29: 62121000 | N29: 2999 | O29: 2400 | P29: 2400 | Q29: 2400 | R29: 0 | S29: 599 | T29: 0 | U29: 0 | V29: 2400 | W29: 2400 | X29: 2285.714 | Y29: 114.286 | Z29: 5 | AA29: 0 | AB29: 0 | AC29: 0 | AD29: 114.286 | AE29: Mumbai | AF29: Maharashtra | AG29: Prepaid | AH29: 09AALCG0172B1ZW | AI29: GOFPL2709100140 | AJ29: 28449609681854 | AL29: 46114.786 | AM29: 46115.622 | AN29: 46118.623 | AO29: 1 | AQ29: Yes | AR29: 1 | AS29: 11.42857 | AT29: Delivered
A30: APRIL_1_to_15_Orders | B30: 4 | C30: GOFPL | D30: GOTCHA FASHIONS PVT LTD_DL | E30: GOTCHA FASHIONS PRIVATE LIMITED-NF Mid Apr-26 Sales | F30: Fashion_GOFPL_042026_Sales_01-15 | G30: NYK-38325574-0275387 | H30: NYK-38325574-0275387-3-1 | I30: NYKF42366040 | J30: CHELV00002212 | K30: Chelvet Black Satin Cami, Pyjama and Robe (S) | L30: Chelvet | M30: 61091000 | N30: 5500 | O30: 5500 | P30: 5372.19 | Q30: 5500 | R30: 0 | S30: 0 | T30: 127.81 | U30: 0 | V30: 5500 | W30: 5500 | X30: 4661.017 | Y30: 838.983 | Z30: 18 | AA30: 0 | AB30: 0 | AC30: 0 | AD30: 838.983 | AE30: Vizianagaram | AF30: Andhra Pradesh | AG30: COD | AH30: 09AALCG0172B1ZW | AI30: GOFPL2709100166 | AJ30: 28449606073623 | AL30: 46123.515 | AM30: 46127.678 | AO30: 1 | AP30: Extra 15% off upto 280 on mov of 1800 - RB - Dynamic - 3 PV | AQ30: Yes | AR30: 1 | AS30: 0 | AT30: Shipped
A31: APRIL_1_to_15_Orders | B31: 4 | C31: GOFPL | D31: GOTCHA FASHIONS PVT LTD_DL | E31: GOTCHA FASHIONS PRIVATE LIMITED-NF Mid Apr-26 Sales | F31: Fashion_GOFPL_042026_Sales_01-15 | G31: NYK-38064984-4715797 | H31: NYK-38064984-4715797-1-1 | I31: NYKF42069133 | J31: CHELV00000011 | K31: Chelvet Women Full Coverage Lightly Padded Bra (38D) | L31: Chelvet | M31: 61089100 | N31: 2099 | O31: 1407 | P31: 1407 | Q31: 1407 | R31: 0 | S31: 692 | T31: 0 | U31: 0 | V31: 1407 | W31: 1407 | X31: 1340 | Y31: 67 | Z31: 5 | AA31: 0 | AB31: 0 | AC31: 0 | AD31: 67 | AE31: Kazhakkoottam | AF31: Kerala | AG31: Prepaid | AH31: 07AALCG0172B1Z0 | AI31: GOFPL2707100598 | AJ31: 28449609722255 | AK31: 28449612130163 | AL31: 46115.927 | AM31: 46116.498 | AN31: 46120.491 | AO31: 1 | AQ31: Yes | AR31: 1 | AS31: 0 | AT31: Return
A32: APRIL_1_to_15_Orders | B32: 4 | C32: GOFPL | D32: GOTCHA FASHIONS PVT LTD_DL | E32: GOTCHA FASHIONS PRIVATE LIMITED-NF Mid Apr-26 Sales | F32: Fashion_GOFPL_042026_Sales_01-15 | G32: NYK-38226464-3188365 | H32: NYK-38226464-3188365-2-1 | I32: NYKF42253368 | J32: CHELV00001655 | K32: Chelvet Pink Satin Shirt With Shorts (M) | L32: Chelvet | M32: 62082200 | N32: 2799 | O32: 2799 | P32: 2799 | Q32: 2799 | R32: 0 | S32: 0 | T32: 0 | U32: 0 | V32: 2799 | W32: 2799 | X32: 2372.034 | Y32: 426.966 | Z32: 18 | AA32: 0 | AB32: 0 | AC32: 0 | AD32: 426.966 | AE32: Gurugram | AF32: Haryana | AG32: COD | AH32: 09AALCG0172B1ZW | AI32: GOFPL2709100158 | AJ32: SF2188978318NYK | AL32: 46120.771 | AM32: 46121.657 | AN32: 46122.637 | AO32: 1 | AQ32: Yes | AR32: 1 | AS32: 11.86017 | AT32: Delivered
A33: APRIL_1_to_15_Orders | B33: 4 | C33: GOFPL | D33: GOTCHA FASHIONS PVT LTD_DL | E33: GOTCHA FASHIONS PRIVATE LIMITED-NF Mid Apr-26 Sales | F33: Fashion_GOFPL_042026_Sales_01-15 | G33: NYK-38151278-0783319 | H33: NYK-38151278-0783319-3-1 | I33: NYKF42167932 | J33: CHELV00000178 | K33: Chelvet Lightly Padded Classic T-Shirt Bra (32C) | L33: Chelvet | M33: 61089100 | N33: 1899 | O33: 1406 | P33: 1406 | Q33: 1406 | R33: 0 | S33: 493 | T33: 0 | U33: 0 | V33: 1406 | W33: 1406 | X33: 1339.048 | Y33: 66.952 | Z33: 5 | AA33: 0 | AB33: 0 | AC33: 0 | AD33: 66.952 | AE33: Jajpur | AF33: Orissa | AG33: Prepaid | AH33: 07AALCG0172B1Z0 | AI33: GOFPL2707100602 | AJ33: 28449602144663 | AL33: 46118.544 | AM33: 46119.513 | AN33: 46122.441 | AO33: 1 | AQ33: Yes | AR33: 2 | AS33: 6.69524 | AT33: Delivered
A34: APRIL_1_to_15_Orders | B34: 4 | C34: GOFPL | D34: GOTCHA FASHIONS PVT LTD_DL | E34: GOTCHA FASHIONS PRIVATE LIMITED-NF Mid Apr-26 Sales | F34: Fashion_GOFPL_042026_Sales_01-15 | G34: NYK-38316546-8288821 | H34: NYK-38316546-8288821-2-1 | I34: NYKF42355951 | J34: CHELV00002249 | K34: Chelvet Floral Strappy Nightdress and Full Sleeve Robe (L) | L34: Chelvet | M34: 61091000 | N34: 4950 | O34: 3168 | P34: 2949.09 | Q34: 3168 | R34: 0 | S34: 1782 | T34: 218.91 | U34: 0 | V34: 3168 | W34: 3168 | X34: 2684.746 | Y34: 483.254 | Z34: 18 | AA34: 241.627 | AB34: 241.627 | AC34: 0 | AD34: 0 | AE34: Noida | AF34: Uttar Pradesh | AG34: COD | AH34: 09AALCG0172B1ZW | AI34: GOFPL2709100165 | AJ34: SF2188981730NYK | AL34: 46123.26 | AM34: 46123.585 | AN34: 46125.603 | AO34: 1 | AQ34: Yes | AR34: 1 | AS34: 13.42373 | AT34: Delivered
A35: APRIL_1_to_15_Orders | B35: 4 | C35: GOFPL | D35: GOTCHA FASHIONS PVT LTD_DL | E35: GOTCHA FASHIONS PRIVATE LIMITED-NF Mid Apr-26 Sales | F35: Fashion_GOFPL_042026_Sales_01-15 | G35: NYK-38353054-2045424 | H35: NYK-38353054-2045424-1-1 | I35: NYKF42397848 | J35: CHELV00001143 | K35: Chelvet Non-Wired Medium Coverage T-Shirt Bra (32B) | L35: Chelvet | M35: 62121000 | N35: 1849 | O35: 1054 | P35: 1054 | Q35: 1054 | R35: 0 | S35: 795 | T35: 0 | U35: 0 | V35: 1054 | W35: 1054 | X35: 1003.81 | Y35: 50.19 | Z35: 5 | AA35: 0 | AB35: 0 | AC35: 0 | AD35: 50.19 | AE35: Indore | AF35: Madhya Pradesh | AG35: Prepaid | AH35: 07AALCG0172B1Z0 | AI35: GOFPL2707100611 | AJ35: 28449602582001 | AL35: 46123.998 | AM35: 46125.499 | AO35: 1 | AQ35: Yes | AR35: 1 | AS35: 0 | AT35: Shipped
A36: APRIL_1_to_15_Orders | B36: 4 | C36: GOFPL | D36: GOTCHA FASHIONS PVT LTD_DL | E36: GOTCHA FASHIONS PRIVATE LIMITED-NF Mid Apr-26 Sales | F36: Fashion_GOFPL_042026_Sales_01-15 | G36: NYK-38112834-8327464 | H36: NYK-38112834-8327464-2-1 | I36: NYKF42123624 | J36: CHELV00001692 | K36: Chelvet Pink Satin Shirt With Pyjama With Shorts (L) | L36: Chelvet | M36: 62082200 | N36: 3599 | O36: 3599 | P36: 3507.29 | Q36: 3599 | R36: 0 | S36: 0 | T36: 91.709999 | U36: 0 | V36: 3599 | W36: 3599 | X36: 3050 | Y36: 549 | Z36: 18 | AA36: 0 | AB36: 0 | AC36: 0 | AD36: 549 | AE36: Raipur | AF36: Chhattisgarh | AG36: COD | AH36: 09AALCG0172B1ZW | AI36: GOFPL2709100150 | AJ36: 28449601682033 | AL36: 46117.474 | AM36: 46118.618 | AN36: 46122.614 | AO36: 1 | AP36: Dynamic RB Paltform wide:Extra 10% off upto 270 on 1700 : 3 PV | AQ36: Yes | AR36: 3 | AS36: 15.25 | AT36: Delivered
A37: APRIL_1_to_15_Orders | B37: 4 | C37: GOFPL | D37: GOTCHA FASHIONS PVT LTD_DL | E37: GOTCHA FASHIONS PRIVATE LIMITED-NF Mid Apr-26 Sales | F37: Fashion_GOFPL_042026_Sales_01-15 | G37: NYK-38162061-4122460 | H37: NYK-38162061-4122460-2-1 | I37: NYKF42180205 | J37: CHELV00001898 | K37: Chelvet Seamless Hipster Panties Multi-Color (Pack of 2) (L) | L37: Chelvet | M37: 61082210 | N37: 1299 | O37: 689 | P37: 657.18 | Q37: 689 | R37: 0 | S37: 610 | T37: 31.82 | U37: 0 | V37: 689 | W37: 689 | X37: 656.19 | Y37: 32.81 | Z37: 5 | AA37: 0 | AB37: 0 | AC37: 0 | AD37: 32.81 | AE37: Ranchi | AF37: Jharkhand | AG37: Prepaid | AH37: 09AALCG0172B1ZW | AI37: GOFPL2709100157 | AJ37: 28449602168091 | AL37: 46118.814 | AM37: 46119.685 | AN37: 46124.405 | AO37: 1 | AQ37: Yes | AR37: 1 | AS37: 3.28095 | AT37: Delivered
A38: APRIL_1_to_15_Orders | B38: 4 | C38: GOFPL | D38: GOTCHA FASHIONS PVT LTD_DL | E38: GOTCHA FASHIONS PRIVATE LIMITED-NF Mid Apr-26 Sales | F38: Fashion_GOFPL_042026_Sales_01-15 | G38: NYK-38028258-2025293 | H38: NYK-38028258-2025293-3-1 | I38: NYKF42028172 | J38: CHELV00002218 | K38: Chelvet Pink Satin Cami, Pyjama and Robe (M) | L38: Chelvet | M38: 61091000 | N38: 5500 | O38: 3520 | P38: 3520 | Q38: 3520 | R38: 0 | S38: 1980 | T38: 0 | U38: 0 | V38: 3520 | W38: 3520 | X38: 2983.051 | Y38: 536.949 | Z38: 18 | AA38: 0 | AB38: 0 | AC38: 0 | AD38: 536.949 | AE38: Mumbai | AF38: Maharashtra | AG38: COD | AH38: 09AALCG0172B1ZW | AI38: GOFPL2709100139 | AJ38: 28449601465125 | AL38: 46114.854 | AM38: 46115.622 | AO38: 1 | AQ38: Yes | AR38: 1 | AS38: 0 | AT38: RTO
A39: APRIL_1_to_15_Orders | B39: 4 | C39: GOFPL | D39: GOTCHA FASHIONS PVT LTD_DL | E39: GOTCHA FASHIONS PRIVATE LIMITED-NF Mid Apr-26 Sales | F39: Fashion_GOFPL_042026_Sales_01-15 | G39: NYK-38098162-0351202 | H39: NYK-38098162-0351202-1-1 | I39: NYKF42106914 | J39: CHELV00001550 | K39: Chelvet Women Beige Seamless Padded Front-Closure Bra (XL) | L39: Chelvet | M39: 62121000 | N39: 2264 | O39: 1698 | P39: 1698 | Q39: 1698 | R39: 0 | S39: 566 | T39: 0 | U39: 0 | V39: 1698 | W39: 1698 | X39: 1617.143 | Y39: 80.857 | Z39: 5 | AA39: 0 | AB39: 0 | AC39: 0 | AD39: 80.857 | AE39: Vadodara | AF39: Gujarat | AG39: Prepaid | AH39: 09AALCG0172B1ZW | AI39: GOFPL2709100144 | AJ39: 28449602084054 | AL39: 46116.918 | AM39: 46119.685 | AN39: 46122.808 | AO39: 1 | AQ39: Yes | AR39: 1 | AS39: 8.085715 | AT39: Delivered
A40: APRIL_1_to_15_Orders | B40: 4 | C40: GOFPL | D40: GOTCHA FASHIONS PVT LTD_DL | E40: GOTCHA FASHIONS PRIVATE LIMITED-NF Mid Apr-26 Sales | F40: Fashion_GOFPL_042026_Sales_01-15 | G40: NYK-38030183-5823098 | H40: NYK-38030183-5823098-1-1 | I40: NYKF42030358 | J40: CHELV00001547 | K40: Chelvet Women Beige Seamless Padded Front-Closure Bra (S) | L40: Chelvet | M40: 62121000 | N40: 2264 | O40: 1698 | P40: 1698 | Q40: 1698 | R40: 0 | S40: 566 | T40: 0 | U40: 0 | V40: 1698 | W40: 1698 | X40: 1617.143 | Y40: 80.857 | Z40: 5 | AA40: 0 | AB40: 0 | AC40: 0 | AD40: 80.857 | AE40: Pune | AF40: Maharashtra | AG40: Prepaid | AH40: 09AALCG0172B1ZW | AL40: 46114.898 | AO40: 1 | AQ40: Yes | AR40: 1 | AS40: 0 | AT40: Cancelled
A41: APRIL_1_to_15_Orders | B41: 4 | C41: GOFPL | D41: GOTCHA FASHIONS PVT LTD_DL | E41: GOTCHA FASHIONS PRIVATE LIMITED-NF Mid Apr-26 Sales | F41: Fashion_GOFPL_042026_Sales_01-15 | G41: NYK-38282770-8783658 | H41: NYK-38282770-8783658-4-1 | I41: NYKF42317380 | J41: CHELV00001690 | K41: Chelvet Pink Satin Shirt With Pyjama With Shorts (S) | L41: Chelvet | M41: 62082200 | N41: 3599 | O41: 3599 | P41: 3599 | Q41: 3599 | R41: 0 | S41: 0 | T41: 0 | U41: 0 | V41: 3599 | W41: 3599 | X41: 3050 | Y41: 549 | Z41: 18 | AA41: 0 | AB41: 0 | AC41: 0 | AD41: 549 | AE41: Mysore | AF41: Karnataka | AG41: Prepaid | AH41: 09AALCG0172B1ZW | AI41: GOFPL2709100161 | AJ41: 28449602380272 | AK41: R1949013357NYK | AL41: 46122.456 | AM41: 46122.65 | AN41: 46126.639 | AO41: 1 | AQ41: Yes | AR41: 1 | AS41: 0 | AT41: Return
A42: APRIL_1_to_15_Orders | B42: 4 | C42: GOFPL | D42: GOTCHA FASHIONS PVT LTD_DL | E42: GOTCHA FASHIONS PRIVATE LIMITED-NF Mid Apr-26 Sales | F42: Fashion_GOFPL_042026_Sales_01-15 | G42: NYK-38004585-6935180 | H42: NYK-38004585-6935180-1-1 | I42: NYKF42001826 | J42: CHELV00001101 | K42: Chelvet Push-Up Non wired Medium Coverage Bra (34B) | L42: Chelvet | M42: 62121000 | N42: 1749 | O42: 1050 | P42: 1050 | Q42: 1050 | R42: 0 | S42: 699 | T42: 0 | U42: 0 | V42: 1050 | W42: 1050 | X42: 1000 | Y42: 50 | Z42: 5 | AA42: 0 | AB42: 0 | AC42: 0 | AD42: 50 | AE42: Lahunipara | AF42: Orissa | AG42: Prepaid | AH42: 07AALCG0172B1Z0 | AI42: GOFPL2707100595 | AJ42: 28449609586982 | AL42: 46113.985 | AM42: 46114.612 | AN42: 46118.808 | AO42: 1 | AQ42: Yes | AR42: 1 | AS42: 5 | AT42: Delivered
A43: APRIL_1_to_15_Orders | B43: 4 | C43: GOFPL | D43: GOTCHA FASHIONS PVT LTD_DL | E43: GOTCHA FASHIONS PRIVATE LIMITED-NF Mid Apr-26 Sales | F43: Fashion_GOFPL_042026_Sales_01-15 | G43: NYK-38151278-0783319 | H43: NYK-38151278-0783319-3-1 | I43: NYKF42167932 | J43: CHELV00000200 | K43: Chelvet Lightly Padded Classic T-Shirt Bra (32C) | L43: Chelvet | M43: 61089100 | N43: 1899 | O43: 1406 | P43: 1406 | Q43: 1406 | R43: 0 | S43: 493 | T43: 0 | U43: 0 | V43: 1406 | W43: 1406 | X43: 1339.048 | Y43: 66.952 | Z43: 5 | AA43: 0 | AB43: 0 | AC43: 0 | AD43: 66.952 | AE43: Jajpur | AF43: Orissa | AG43: Prepaid | AH43: 07AALCG0172B1Z0 | AI43: GOFPL2707100602 | AJ43: 28449602144663 | AL43: 46118.544 | AM43: 46119.513 | AN43: 46122.441 | AO43: 1 | AQ43: Yes | AR43: 2 | AS43: 6.69524 | AT43: Delivered
A44: APRIL_1_to_15_Orders | B44: 4 | C44: GOFPL | D44: GOTCHA FASHIONS PVT LTD_DL | E44: GOTCHA FASHIONS PRIVATE LIMITED-NF Mid Apr-26 Sales | F44: Fashion_GOFPL_042026_Sales_01-15 | G44: NYK-38315482-5666316 | H44: NYK-38315482-5666316-2-1 | I44: NYKF42354812 | J44: CHELV00001970 | K44: Chelvet Non-Padded Underwired Lace Bra and Panty - Olive (36B) | L44: Chelvet | M44: 62121000 | N44: 3500 | O44: 2800 | P44: 2725.53 | Q44: 2800 | R44: 0 | S44: 700 | T44: 74.470001 | U44: 0 | V44: 2800 | W44: 2800 | X44: 2372.881 | Y44: 427.119 | Z44: 18 | AA44: 0 | AB44: 0 | AC44: 0 | AD44: 427.119 | AE44: Gurugram | AF44: Haryana | AG44: Prepaid | AH44: 09AALCG0172B1ZW | AI44: GOFPL2709100164 | AJ44: SF2188742216NYK | AL44: 46123.114 | AM44: 46123.585 | AN44: 46125.53 | AO44: 1 | AQ44: Yes | AR44: 1 | AS44: 11.864405 | AT44: Delivered
A45: APRIL_1_to_15_Orders | B45: 4 | C45: GOFPL | D45: GOTCHA FASHIONS PVT LTD_DL | E45: GOTCHA FASHIONS PRIVATE LIMITED-NF Mid Apr-26 Sales | F45: Fashion_GOFPL_042026_Sales_01-15 | G45: NYK-38130788-0594892 | H45: NYK-38130788-0594892-1-1 | I45: NYKF42144141 | J45: CHELV00001643 | K45: Chelvet Pink Satin Shirt With Shorts (M) | L45: Chelvet | M45: 62082200 | N45: 2899 | O45: 2899 | P45: 2899 | Q45: 2899 | R45: 0 | S45: 0 | T45: 0 | U45: 0 | V45: 2899 | W45: 2899 | X45: 2456.78 | Y45: 442.22 | Z45: 18 | AA45: 0 | AB45: 0 | AC45: 0 | AD45: 442.22 | AE45: Bangalore | AF45: Karnataka | AG45: COD | AH45: 09AALCG0172B1ZW | AL45: 46117.847 | AO45: 1 | AQ45: Yes | AR45: 3 | AS45: 0 | AT45: Cancelled
A46: APRIL_1_to_15_Orders | B46: 4 | C46: GOFPL | D46: GOTCHA FASHIONS PVT LTD_DL | E46: GOTCHA FASHIONS PRIVATE LIMITED-NF Mid Apr-26 Sales | F46: Fashion_GOFPL_042026_Sales_01-15 | G46: NYK-38019467-1889932 | H46: NYK-38019467-1889932-2-1 | I46: NYKF42018065 | J46: CHELV00001436 | K46: Chelvet Women Burgundy Velvet Solid Sweatshirt with Pyjama (S) | L46: Chelvet | M46: 61083100 | N46: 4099 | O46: 2870 | P46: 2870 | Q46: 2870 | R46: 0 | S46: 1229 | T46: 0 | U46: 0 | V46: 2870 | W46: 2870 | X46: 2432.203 | Y46: 437.797 | Z46: 18 | AA46: 0 | AB46: 0 | AC46: 0 | AD46: 437.797 | AE46: Bangalore | AF46: Karnataka | AG46: Prepaid | AH46: 09AALCG0172B1ZW | AI46: GOFPL2709100138 | AJ46: 28449609632014 | AK46: 28449611868050 | AL46: 46114.621 | AM46: 46115.622 | AN46: 46118.603 | AO46: 1 | AQ46: Yes | AR46: 1 | AS46: 0 | AT46: Return
A47: APRIL_1_to_15_Orders | B47: 4 | C47: GOFPL | D47: GOTCHA FASHIONS PVT LTD_DL | E47: GOTCHA FASHIONS PRIVATE LIMITED-NF Mid Apr-26 Sales | F47: Fashion_GOFPL_042026_Sales_01-15 | G47: NYK-38155786-0691337 | H47: NYK-38155786-0691337-1-1 | I47: NYKF42173019 | J47: CHELV00002028 | K47: Chelvet Black Thermo Cot Ultra Warm Full Sleeves Thermal Top (L) | L47: Chelvet | M47: 62071990 | N47: 1499 | O47: 1499 | P47: 1499 | Q47: 1499 | R47: 0 | S47: 0 | T47: 0 | U47: 0 | V47: 1499 | W47: 1499 | X47: 1427.619 | Y47: 71.381 | Z47: 5 | AA47: 0 | AB47: 0 | AC47: 0 | AD47: 71.381 | AE47: Bargarh | AF47: Orissa | AG47: COD | AH47: 09AALCG0172B1ZW | AI47: GOFPL2709100153 | AJ47: 28449601721410 | AL47: 46118.658 | AM47: 46119.685 | AN47: 46123.807 | AO47: 1 | AQ47: Yes | AR47: 1 | AS47: 7.138095 | AT47: Delivered
A48: APRIL_1_to_15_Orders | B48: 4 | C48: GOFPL | D48: GOTCHA FASHIONS PVT LTD_DL | E48: GOTCHA FASHIONS PRIVATE LIMITED-NF Mid Apr-26 Sales | F48: Fashion_GOFPL_042026_Sales_01-15 | G48: NYK-38147233-2289513 | H48: NYK-38147233-2289513-2-1 | I48: NYKF42163237 | J48: CHELV00002220 | K48: Chelvet Pink Satin Cami, Pyjama and Robe (XL) | L48: Chelvet | M48: 61091000 | N48: 5500 | O48: 3520 | P48: 3424.76 | Q48: 3520 | R48: 0 | S48: 1980 | T48: 95.239998 | U48: 0 | V48: 3520 | W48: 3520 | X48: 2983.051 | Y48: 536.949 | Z48: 18 | AA48: 0 | AB48: 0 | AC48: 0 | AD48: 536.949 | AE48: Solan | AF48: Himachal Pradesh | AG48: COD | AH48: 09AALCG0172B1ZW | AI48: GOFPL2709100142 | AJ48: SF2188974608NYK | AL48: 46118.445 | AM48: 46120.637 | AO48: 1 | AQ48: Yes | AR48: 2 | AS48: 0 | AT48: Shipped
A49: APRIL_1_to_15_Orders | B49: 4 | C49: GOFPL | D49: GOTCHA FASHIONS PVT LTD_DL | E49: GOTCHA FASHIONS PRIVATE LIMITED-NF Mid Apr-26 Sales | F49: Fashion_GOFPL_042026_Sales_01-15 | G49: NYK-38325675-0428586 | H49: NYK-38325675-0428586-3-1 | I49: NYKF42366185 | J49: CHELV00002247 | K49: Chelvet Floral Strappy Nightdress and Full Sleeve Robe (S) | L49: Chelvet | M49: 61091000 | N49: 4950 | O49: 3168 | P49: 3168 | Q49: 3168 | R49: 0 | S49: 1782 | T49: 0 | U49: 0 | V49: 3168 | W49: 3168 | X49: 2684.746 | Y49: 483.254 | Z49: 18 | AA49: 0 | AB49: 0 | AC49: 0 | AD49: 483.254 | AE49: Vizianagaram | AF49: Andhra Pradesh | AG49: COD | AH49: 09AALCG0172B1ZW | AI49: GOFPL2709100168 | AJ49: 59695380570 | AL49: 46123.517 | AM49: 46127.661 | AO49: 1 | AQ49: Yes | AR49: 1 | AS49: 0 | AT49: Shipped
A50: APRIL_1_to_15_Orders | B50: 4 | C50: GOFPL | D50: GOTCHA FASHIONS PVT LTD_DL | E50: GOTCHA FASHIONS PRIVATE LIMITED-NF Mid Apr-26 Sales | F50: Fashion_GOFPL_042026_Sales_01-15 | G50: NYK-38274618-4377193 | H50: NYK-38274618-4377193-1-1 | I50: NYKF42308192 | J50: CHELV00001095 | K50: Chelvet Push-Up Non wired Medium Coverage Bra (36D) | L50: Chelvet | M50: 62121000 | N50: 1749 | O50: 1050 | P50: 1050 | Q50: 1050 | R50: 0 | S50: 699 | T50: 0 | U50: 0 | V50: 1050 | W50: 1050 | X50: 1000 | Y50: 50 | Z50: 5 | AA50: 0 | AB50: 0 | AC50: 0 | AD50: 50 | AE50: Aligarh | AF50: Uttar Pradesh | AG50: COD | AH50: 07AALCG0172B1Z0 | AI50: GOFPL2707100606 | AJ50: NKFC0000459950 | AL50: 46122.058 | AM50: 46122.548 | AN50: 46124.73 | AO50: 1 | AQ50: Yes | AR50: 3 | AS50: 5 | AT50: Delivered
A51: APRIL_1_to_15_Orders | B51: 4 | C51: GOFPL | D51: GOTCHA FASHIONS PVT LTD_DL | E51: GOTCHA FASHIONS PRIVATE LIMITED-NF Mid Apr-26 Sales | F51: Fashion_GOFPL_042026_Sales_01-15 | G51: NYK-38098863-1400316 | H51: NYK-38098863-1400316-2-1 | I51: NYKF42107660 | J51: CHELV00001437 | K51: Chelvet Women Burgundy Velvet Solid Sweatshirt with Pyjama (M) | L51: Chelvet | M51: 61083100 | N51: 4099 | O51: 2870 | P51: 2710.61 | Q51: 2870 | R51: 0 | S51: 1229 | T51: 159.39 | U51: 0 | V51: 2870 | W51: 2870 | X51: 2432.203 | Y51: 437.797 | Z51: 18 | AA51: 218.899 | AB51: 218.899 | AC51: 0 | AD51: 0 | AE51: Ghaziabad | AF51: Uttar Pradesh | AG51: Prepaid | AH51: 09AALCG0172B1ZW | AI51: GOFPL2709100148 | AJ51: SF2188731918NYK | AK51: 28449611973621 | AL51: 46116.931 | AM51: 46119.492 | AN51: 46120.53 | AO51: 1 | AQ51: Yes | AR51: 1 | AS51: 0 | AT51: Return
A52: APRIL_1_to_15_Orders | B52: 4 | C52: GOFPL | D52: GOTCHA FASHIONS PVT LTD_DL | E52: GOTCHA FASHIONS PRIVATE LIMITED-NF Mid Apr-26 Sales | F52: Fashion_GOFPL_042026_Sales_01-15 | G52: NYK-38178041-6625004 | H52: NYK-38178041-6625004-2-1 | I52: NYKF42198457 | J52: CHELV00001905 | K52: Chelvet Seamless Hipster Panties Lavender (Pack of 2) (M) | L52: Chelvet | M52: 61082210 | N52: 1299 | O52: 689 | P52: 689 | Q52: 689 | R52: 0 | S52: 610 | T52: 0 | U52: 0 | V52: 689 | W52: 689 | X52: 656.19 | Y52: 32.81 | Z52: 5 | AA52: 16.405 | AB52: 16.405 | AC52: 0 | AD52: 0 | AE52: Bareilly | AF52: Uttar Pradesh | AG52: Prepaid | AH52: 09AALCG0172B1ZW | AI52: GOFPL2709100156 | AJ52: SF2188734046NYK | AL52: 46119.422 | AM52: 46120.513 | AN52: 46122.484 | AO52: 1 | AQ52: Yes | AR52: 1 | AS52: 3.28095 | AT52: Delivered
A53: APRIL_1_to_15_Orders | B53: 4 | C53: GOFPL | D53: GOTCHA FASHIONS PVT LTD_DL | E53: GOTCHA FASHIONS PRIVATE LIMITED-NF Mid Apr-26 Sales | F53: Fashion_GOFPL_042026_Sales_01-15 | G53: NYK-37985303-6459307 | H53: NYK-37985303-6459307-2-1 | I53: NYKF41979871 | J53: CHELV00002096 | K53: Chelvet Women Padded Non-Wired Black T-Shirt Bra (36C) | L53: Chelvet | M53: 62121000 | N53: 1999 | O53: 1140 | P53: 1140 | Q53: 1140 | R53: 0 | S53: 859 | T53: 0 | U53: 0 | V53: 1140 | W53: 1140 | X53: 1085.714 | Y53: 54.286 | Z53: 5 | AA53: 0 | AB53: 0 | AC53: 0 | AD53: 54.286 | AE53: Chikkaballapura | AF53: Karnataka | AG53: COD | AH53: 09AALCG0172B1ZW | AL53: 46113.517 | AO53: 1 | AQ53: Yes | AR53: 1 | AS53: 0 | AT53: Not Shipped
A54: APRIL_1_to_15_Orders | B54: 4 | C54: GOFPL | D54: GOTCHA FASHIONS PVT LTD_DL | E54: GOTCHA FASHIONS PRIVATE LIMITED-NF Mid Apr-26 Sales | F54: Fashion_GOFPL_042026_Sales_01-15 | G54: NYK-38432666-0677860 | H54: NYK-38432666-0677860-2-1 | I54: NYKF42490501 | J54: CHELV00000796 | K54: Chelvet Women's Lightly Padded Wireless Medium Coverage Bra | Printed Everyday Support & Shape (36B) | L54: Chelvet | M54: 62121000 | N54: 1999 | O54: 1000 | P54: 1000 | Q54: 1000 | R54: 0 | S54: 999 | T54: 0 | U54: 0 | V54: 1000 | W54: 1000 | X54: 952.381 | Y54: 47.619 | Z54: 5 | AA54: 0 | AB54: 0 | AC54: 0 | AD54: 47.619 | AE54: Bangalore | AF54: Karnataka | AG54: Prepaid | AH54: 07AALCG0172B1Z0 | AI54: GOFPL2707100617 | AJ54: 88364559861 | AL54: 46125.95 | AM54: 46126.637 | AO54: 1 | AQ54: Yes | AR54: 1 | AS54: 0 | AT54: Shipped
A55: APRIL_1_to_15_Orders | B55: 4 | C55: GOFPL | D55: GOTCHA FASHIONS PVT LTD_DL | E55: GOTCHA FASHIONS PRIVATE LIMITED-NF Mid Apr-26 Sales | F55: Fashion_GOFPL_042026_Sales_01-15 | G55: NYK-38513618-7182109 | H55: NYK-38513618-7182109-2-1 | I55: NYKF42583896 | J55: CHELV00000919 | K55: Chelvet Underwired Lightly Padded Demi Cup Bra (36D) | L55: Chelvet | M55: 62121000 | N55: 1699 | O55: 1394 | P55: 1227.69 | Q55: 1394 | R55: 0 | S55: 305 | T55: 166.31 | U55: 0 | V55: 1394 | W55: 1394 | X55: 1327.619 | Y55: 66.381 | Z55: 5 | AA55: 0 | AB55: 0 | AC55: 0 | AD55: 66.381 | AE55: Noida | AF55: Uttar Pradesh | AG55: Prepaid | AH55: 07AALCG0172B1Z0 | AL55: 46127.993 | AO55: 1 | AP55: mov changed to 1000 - 11/9 max disc changed to 220 | AQ55: Yes | AR55: 1 | AS55: 0 | AT55: Not Shipped
A56: APRIL_1_to_15_Orders | B56: 4 | C56: GOFPL | D56: GOTCHA FASHIONS PVT LTD_DL | E56: GOTCHA FASHIONS PRIVATE LIMITED-NF Mid Apr-26 Sales | F56: Fashion_GOFPL_042026_Sales_01-15 | G56: NYK-38117864-6956737 | H56: NYK-38117864-6956737-1-1 | I56: NYKF42129366 | J56: CHELV00001541 | K56: Chelvet Women Seamless Nude Padded Bra (L) | L56: Chelvet | M56: 62121000 | N56: 2264 | O56: 1495 | P56: 1495 | Q56: 1495 | R56: 0 | S56: 769 | T56: 0 | U56: 0 | V56: 1495 | W56: 1495 | X56: 1423.81 | Y56: 71.19 | Z56: 5 | AA56: 0 | AB56: 0 | AC56: 0 | AD56: 71.19 | AE56: Chhindwara | AF56: Madhya Pradesh | AG56: Prepaid | AH56: 09AALCG0172B1ZW | AI56: GOFPL2709100146 | AJ56: 28449602083166 | AL56: 46117.574 | AM56: 46118.618 | AN56: 46122.511 | AO56: 1 | AQ56: Yes | AR56: 1 | AS56: 7.11905 | AT56: Delivered
A57: APRIL_1_to_15_Orders | B57: 4 | C57: GOFPL | D57: GOTCHA FASHIONS PVT LTD_DL | E57: GOTCHA FASHIONS PRIVATE LIMITED-NF Mid Apr-26 Sales | F57: Fashion_GOFPL_042026_Sales_01-15 | G57: NYK-38031550-8248146 | H57: NYK-38031550-8248146-1-1 | I57: NYKF42031904 | J57: CHELV00000678 | K57: Chelvet Medium Coverage Non-Padded Organic Cotton Bra (38B) | L57: Chelvet | M57: 62121000 | N57: 1499 | O57: 795 | P57: 795 | Q57: 795 | R57: 0 | S57: 704 | T57: 0 | U57: 0 | V57: 795 | W57: 795 | X57: 757.143 | Y57: 37.857 | Z57: 5 | AA57: 0 | AB57: 0 | AC57: 0 | AD57: 37.857 | AE57: Solapur | AF57: Maharashtra | AG57: Prepaid | AH57: 07AALCG0172B1Z0 | AI57: GOFPL2707100597 | AJ57: 28449609650995 | AL57: 46114.926 | AM57: 46115.61 | AN57: 46122.447 | AO57: 1 | AQ57: Yes | AR57: 2 | AS57: 3.785715 | AT57: Delivered
A58: APRIL_1_to_15_Orders | B58: 4 | C58: GOFPL | D58: GOTCHA FASHIONS PVT LTD_DL | E58: GOTCHA FASHIONS PRIVATE LIMITED-NF Mid Apr-26 Sales | F58: Fashion_GOFPL_042026_Sales_01-15 | G58: NYK-38330459-7686930 | H58: NYK-38330459-7686930-1-1 | I58: NYKF42371661 | J58: CHELV00001119 | K58: Chelvet Push-Up Non wired Medium Coverage Bra (38C) | L58: Chelvet | M58: 62121000 | N58: 1749 | O58: 1050 | P58: 1050 | Q58: 1050 | R58: 0 | S58: 699 | T58: 0 | U58: 0 | V58: 1050 | W58: 1050 | X58: 1000 | Y58: 50 | Z58: 5 | AA58: 0 | AB58: 0 | AC58: 0 | AD58: 50 | AE58: Valsad | AF58: Gujarat | AG58: COD | AH58: 07AALCG0172B1Z0 | AL58: 46123.601 | AO58: 1 | AQ58: Yes | AR58: 2 | AS58: 0 | AT58: Not Shipped
A59: APRIL_1_to_15_Orders | B59: 4 | C59: GOFPL | D59: GOTCHA FASHIONS PVT LTD_DL | E59: GOTCHA FASHIONS PRIVATE LIMITED-NF Mid Apr-26 Sales | F59: Fashion_GOFPL_042026_Sales_01-15 | G59: NYK-38085809-6817497 | H59: NYK-38085809-6817497-2-1 | I59: NYKF42092885 | J59: CHELV00000076 | K59: Chelvet Solid Lightly Padded Half Coverage Plunge Bra (38C) | L59: Chelvet | M59: 61089100 | N59: 1499 | O59: 1050 | P59: 963.93 | Q59: 1050 | R59: 0 | S59: 449 | T59: 86.07 | U59: 0 | V59: 1050 | W59: 1050 | X59: 1000 | Y59: 50 | Z59: 5 | AA59: 0 | AB59: 0 | AC59: 0 | AD59: 50 | AE59: Dhoom | AF59: Uttar Pradesh | AG59: COD | AH59: 07AALCG0172B1Z0 | AI59: GOFPL2707100600 | AJ59: SF2188975552NYK | AL59: 46116.646 | AM59: 46119.62 | AN59: 46120.436 | AO59: 1 | AQ59: Yes | AR59: 1 | AS59: 5 | AT59: Delivered
A60: APRIL_1_to_15_Orders | B60: 4 | C60: GOFPL | D60: GOTCHA FASHIONS PVT LTD_DL | E60: GOTCHA FASHIONS PRIVATE LIMITED-NF Mid Apr-26 Sales | F60: Fashion_GOFPL_042026_Sales_01-15 | G60: NYK-38362556-8415300 | H60: NYK-38362556-8415300-2-1 | I60: NYKF42408880 | J60: CHELV00000917 | K60: Chelvet Underwired Lightly Padded Demi Cup Bra (36B) | L60: Chelvet | M60: 62121000 | N60: 1699 | O60: 1394 | P60: 1261.19 | Q60: 1394 | R60: 0 | S60: 305 | T60: 132.81 | U60: 0 | V60: 1394 | W60: 1394 | X60: 1327.619 | Y60: 66.381 | Z60: 5 | AA60: 0 | AB60: 0 | AC60: 0 | AD60: 66.381 | AE60: Mumbai | AF60: Maharashtra | AG60: Prepaid | AH60: 07AALCG0172B1Z0 | AI60: GOFPL2707100615 | AJ60: 88364455583 | AK60: 28449612375196 | AL60: 46124.419 | AM60: 46125.68 | AN60: 46126.467 | AO60: 1 | AP60: Dynamic RB Paltform wide:Extra 10% off upto 270 on 1800 : 3 PV | AQ60: Yes | AR60: 1 | AS60: 0 | AT60: Return
A61: APRIL_1_to_15_Orders | B61: 4 | C61: GOFPL | D61: GOTCHA FASHIONS PVT LTD_DL | E61: GOTCHA FASHIONS PRIVATE LIMITED-NF Mid Apr-26 Sales | F61: Fashion_GOFPL_042026_Sales_01-15 | G61: NYK-38176752-3653327 | H61: NYK-38176752-3653327-4-1 | I61: NYKF42197094 | J61: CHELV00002249 | K61: Chelvet Floral Strappy Nightdress and Full Sleeve Robe (L) | L61: Chelvet | M61: 61091000 | N61: 4950 | O61: 3168 | P61: 3059.7 | Q61: 3168 | R61: 0 | S61: 1782 | T61: 108.3 | U61: 0 | V61: 3168 | W61: 3168 | X61: 2684.746 | Y61: 483.254 | Z61: 18 | AA61: 241.627 | AB61: 241.627 | AC61: 0 | AD61: 0 | AE61: Vrindavan | AF61: Uttar Pradesh | AG61: Prepaid | AH61: 09AALCG0172B1ZW | AI61: GOFPL2709100155 | AJ61: SF2188733661NYK | AL61: 46119.387 | AM61: 46120.512 | AN61: 46125.771 | AO61: 1 | AP61: Swiggy HDFC Bank Credit Card offer- Instant 5% discount | AQ61: Yes | AR61: 1 | AS61: 13.42373 | AT61: Delivered
A62: APRIL_1_to_15_Orders | B62: 4 | C62: GOFPL | D62: GOTCHA FASHIONS PVT LTD_DL | E62: GOTCHA FASHIONS PRIVATE LIMITED-NF Mid Apr-26 Sales | F62: Fashion_GOFPL_042026_Sales_01-15 | G62: NYK-38291604-2396922 | H62: NYK-38291604-2396922-3-1 | I62: NYKF42327366 | J62: CHELV00000509 | K62: Chelvet Women Beige Medium Coverage Non-Wired Lightly Padded Everyday Bra (34D) | L62: Chelvet | M62: 62121000 | N62: 1749 | O62: 1400 | P62: 1400 | Q62: 1400 | R62: 0 | S62: 349 | T62: 0 | U62: 0 | V62: 1400 | W62: 1400 | X62: 1333.333 | Y62: 66.667 | Z62: 5 | AA62: 0 | AB62: 0 | AC62: 0 | AD62: 66.667 | AE62: Ghaziabad | AF62: Uttar Pradesh | AG62: Prepaid | AH62: 07AALCG0172B1Z0 | AI62: GOFPL2707100607 | AJ62: SF2188741044NYK | AL62: 46122.613 | AM62: 46123.554 | AN62: 46124.421 | AO62: 1 | AQ62: Yes | AR62: 1 | AS62: 6.666665 | AT62: Delivered
A63: APRIL_1_to_15_Orders | B63: 4 | C63: GOFPL | D63: GOTCHA FASHIONS PVT LTD_DL | E63: GOTCHA FASHIONS PRIVATE LIMITED-NF Mid Apr-26 Sales | F63: Fashion_GOFPL_042026_Sales_01-15 | G63: NYK-38336655-7739725 | H63: NYK-38336655-7739725-1-1 | I63: NYKF42378797 | J63: CHELV00000941 | K63: Chelvet Underwired Lightly Padded Demi Cup Bra (36D) | L63: Chelvet | M63: 62121000 | N63: 1699 | O63: 1394 | P63: 1194 | Q63: 1394 | R63: 0 | S63: 305 | T63: 200 | U63: 0 | V63: 1394 | W63: 1394 | X63: 1327.619 | Y63: 66.381 | Z63: 5 | AA63: 0 | AB63: 0 | AC63: 0 | AD63: 66.381 | AE63: Pune | AF63: Maharashtra | AG63: Prepaid | AH63: 07AALCG0172B1Z0 | AI63: GOFPL2707100614 | AJ63: 88364455060 | AL63: 46123.717 | AM63: 46125.68 | AN63: 46127.626 | AO63: 1 | AQ63: Yes | AR63: 1 | AS63: 6.638095 | AT63: Delivered
A64: APRIL_1_to_15_Orders | B64: 4 | C64: GOFPL | D64: GOTCHA FASHIONS PVT LTD_DL | E64: GOTCHA FASHIONS PRIVATE LIMITED-NF Mid Apr-26 Sales | F64: Fashion_GOFPL_042026_Sales_01-15 | G64: NYK-38280083-4337947 | H64: NYK-38280083-4337947-1-1 | I64: NYKF42314475 | J64: CHELV00002249 | K64: Chelvet Floral Strappy Nightdress and Full Sleeve Robe (L) | L64: Chelvet | M64: 61091000 | N64: 4950 | O64: 3168 | P64: 3168 | Q64: 3168 | R64: 0 | S64: 1782 | T64: 0 | U64: 0 | V64: 3168 | W64: 3168 | X64: 2684.746 | Y64: 483.254 | Z64: 18 | AA64: 0 | AB64: 0 | AC64: 0 | AD64: 483.254 | AE64: Mumbai | AF64: Maharashtra | AG64: COD | AH64: 09AALCG0172B1ZW | AI64: GOFPL2709100160 | AJ64: 59695170706 | AL64: 46122.404 | AM64: 46127.661 | AO64: 1 | AQ64: Yes | AR64: 1 | AS64: 0 | AT64: Shipped
A65: APRIL_1_to_15_Orders | B65: 4 | C65: GOFPL | D65: GOTCHA FASHIONS PVT LTD_DL | E65: GOTCHA FASHIONS PRIVATE LIMITED-NF Mid Apr-26 Sales | F65: Fashion_GOFPL_042026_Sales_01-15 | G65: NYK-38284159-0847476 | H65: NYK-38284159-0847476-1-1 | I65: NYKF42318835 | J65: CHELV00000663 | K65: Chelvet Medium Coverage Non-Padded Organic Cotton Bra (34D) | L65: Chelvet | M65: 62121000 | N65: 1499 | O65: 795 | P65: 795 | Q65: 795 | R65: 0 | S65: 704 | T65: 0 | U65: 0 | V65: 795 | W65: 795 | X65: 757.143 | Y65: 37.857 | Z65: 5 | AA65: 0 | AB65: 0 | AC65: 0 | AD65: 37.857 | AE65: Siliguri | AF65: West Bengal | AG65: COD | AH65: 07AALCG0172B1Z0 | AI65: GOFPL2707100610 | AJ65: 28449606020924 | AK65: R1984974402NYK | AL65: 46122.48 | AM65: 46123.495 | AN65: 46126.663 | AO65: 1 | AQ65: Yes | AR65: 1 | AS65: 0 | AT65: Return
A66: APRIL_1_to_15_Orders | B66: 4 | C66: GOFPL | D66: GOTCHA FASHIONS PVT LTD_DL | E66: GOTCHA FASHIONS PRIVATE LIMITED-NF Mid Apr-26 Sales | F66: Fashion_GOFPL_042026_Sales_01-15 | G66: NYK-38031550-8248146 | H66: NYK-38031550-8248146-1-1 | I66: NYKF42031904 | J66: CHELV00000667 | K66: Chelvet Medium Coverage Non-Padded Organic Cotton Bra (38B) | L66: Chelvet | M66: 62121000 | N66: 1499 | O66: 795 | P66: 795 | Q66: 795 | R66: 0 | S66: 704 | T66: 0 | U66: 0 | V66: 795 | W66: 795 | X66: 757.143 | Y66: 37.857 | Z66: 5 | AA66: 0 | AB66: 0 | AC66: 0 | AD66: 37.857 | AE66: Solapur | AF66: Maharashtra | AG66: Prepaid | AH66: 07AALCG0172B1Z0 | AI66: GOFPL2707100597 | AJ66: 28449609650995 | AL66: 46114.926 | AM66: 46115.61 | AN66: 46122.447 | AO66: 1 | AQ66: Yes | AR66: 2 | AS66: 3.785715 | AT66: Delivered
A67: APRIL_1_to_15_Orders | B67: 4 | C67: GOFPL | D67: GOTCHA FASHIONS PVT LTD_DL | E67: GOTCHA FASHIONS PRIVATE LIMITED-NF Mid Apr-26 Sales | F67: Fashion_GOFPL_042026_Sales_01-15 | G67: NYK-38140186-5649979 | H67: NYK-38140186-5649979-1-1 | I67: NYKF42155317 | J67: CHELV00001672 | K67: Chelvet White Satin Shirt With Pyjama (S) | L67: Chelvet | M67: 62082200 | N67: 2999 | O67: 2999 | P67: 2999 | Q67: 2999 | R67: 0 | S67: 0 | T67: 0 | U67: 0 | V67: 2999 | W67: 2999 | X67: 2541.525 | Y67: 457.475 | Z67: 18 | AA67: 0 | AB67: 0 | AC67: 0 | AD67: 457.475 | AE67: Pune | AF67: Maharashtra | AG67: Prepaid | AH67: 09AALCG0172B1ZW | AI67: GOFPL2709100147 | AJ67: 28449602075352 | AL67: 46118.021 | AM67: 46119.685 | AN67: 46122.406 | AO67: 1 | AQ67: Yes | AR67: 1 | AS67: 12.707625 | AT67: Delivered
A68: APRIL_1_to_15_Orders | B68: 4 | C68: GOFPL | D68: GOTCHA FASHIONS PVT LTD_DL | E68: GOTCHA FASHIONS PRIVATE LIMITED-NF Mid Apr-26 Sales | F68: Fashion_GOFPL_042026_Sales_01-15 | G68: NYK-38330459-7686930 | H68: NYK-38330459-7686930-1-1 | I68: NYKF42371661 | J68: CHELV00001108 | K68: Chelvet Push-Up Non wired Medium Coverage Bra (38C) | L68: Chelvet | M68: 62121000 | N68: 1749 | O68: 1050 | P68: 1050 | Q68: 1050 | R68: 0 | S68: 699 | T68: 0 | U68: 0 | V68: 1050 | W68: 1050 | X68: 1000 | Y68: 50 | Z68: 5 | AA68: 0 | AB68: 0 | AC68: 0 | AD68: 50 | AE68: Valsad | AF68: Gujarat | AG68: COD | AH68: 07AALCG0172B1Z0 | AL68: 46123.601 | AO68: 1 | AQ68: Yes | AR68: 2 | AS68: 0 | AT68: Not Shipped
A69: APRIL_1_to_15_Orders | B69: 4 | C69: GOFPL | D69: GOTCHA FASHIONS PVT LTD_DL | E69: GOTCHA FASHIONS PRIVATE LIMITED-NF Mid Apr-26 Sales | F69: Fashion_GOFPL_042026_Sales_01-15 | G69: NYK-38149484-7129408 | H69: NYK-38149484-7129408-1-1 | I69: NYKF42165824 | J69: CHELV00000216 | K69: Chelvet Lightly Padded Classic T-Shirt Bra (36C) | L69: Chelvet | M69: 61089100 | N69: 1899 | O69: 1406 | P69: 1358.22 | Q69: 1406 | R69: 0 | S69: 493 | T69: 47.779999 | U69: 0 | V69: 1406 | W69: 1406 | X69: 1339.048 | Y69: 66.952 | Z69: 5 | AA69: 0 | AB69: 0 | AC69: 0 | AD69: 66.952 | AE69: Hyderabad | AF69: Telangana | AG69: Prepaid | AH69: 07AALCG0172B1Z0 | AL69: 46118.501 | AO69: 1 | AQ69: Yes | AR69: 2 | AS69: 0 | AT69: Not Shipped
A70: APRIL_1_to_15_Orders | B70: 4 | C70: GOFPL | D70: GOTCHA FASHIONS PVT LTD_DL | E70: GOTCHA FASHIONS PRIVATE LIMITED-NF Mid Apr-26 Sales | F70: Fashion_GOFPL_042026_Sales_01-15 | G70: NYK-38103202-7880364 | H70: NYK-38103202-7880364-1-1 | I70: NYKF42112696 | J70: CHELV00000085 | K70: Chelvet Solid Lightly Padded Half Coverage Plunge Bra (36D) | L70: Chelvet | M70: 61089100 | N70: 1499 | O70: 1050 | P70: 840 | Q70: 1050 | R70: 0 | S70: 449 | T70: 210 | U70: 0 | V70: 1050 | W70: 1050 | X70: 1000 | Y70: 50 | Z70: 5 | AA70: 25 | AB70: 25 | AC70: 0 | AD70: 0 | AE70: New Delhi | AF70: Delhi | AG70: COD | AH70: 07AALCG0172B1Z0 | AI70: GOFPL2707100601 | AJ70: SF2188975729NYK | AL70: 46117.006 | AM70: 46119.62 | AN70: 46120.508 | AO70: 1 | AP70: mov changed to 1000 - 11/9 max disc changed to 220 | AQ70: Yes | AR70: 1 | AS70: 5 | AT70: Delivered
A71: APRIL_1_to_15_Orders | B71: 4 | C71: GOFPL | D71: GOTCHA FASHIONS PVT LTD_DL | E71: GOTCHA FASHIONS PRIVATE LIMITED-NF Mid Apr-26 Sales | F71: Fashion_GOFPL_042026_Sales_01-15 | G71: NYK-38168649-6024229 | H71: NYK-38168649-6024229-2-1 | I71: NYKF42187712 | J71: CHELV00002217 | K71: Chelvet Pink Satin Cami, Pyjama and Robe (S) | L71: Chelvet | M71: 61091000 | N71: 5500 | O71: 3520 | P71: 3520 | Q71: 3520 | R71: 0 | S71: 1980 | T71: 0 | U71: 0 | V71: 3520 | W71: 3520 | X71: 2983.051 | Y71: 536.949 | Z71: 18 | AA71: 0 | AB71: 0 | AC71: 0 | AD71: 536.949 | AE71: Mumbai | AF71: Maharashtra | AG71: Prepaid | AH71: 09AALCG0172B1ZW | AI71: GOFPL2709100154 | AJ71: 28449602166573 | AL71: 46118.952 | AM71: 46119.685 | AN71: 46122.546 | AO71: 1 | AQ71: Yes | AR71: 1 | AS71: 14.915255 | AT71: Delivered
A72: APRIL_1_to_15_Orders | B72: 4 | C72: GOFPL | D72: GOTCHA FASHIONS PVT LTD_DL | E72: GOTCHA FASHIONS PRIVATE LIMITED-NF Mid Apr-26 Sales | F72: Fashion_GOFPL_042026_Sales_01-15 | G72: NYK-38274618-4377193 | H72: NYK-38274618-4377193-1-1 | I72: NYKF42308192 | J72: CHELV00000140 | K72: Chelvet Women Full Coverage Lightly Padded Bra (36D) | L72: Chelvet | M72: 61089100 | N72: 1749 | O72: 1505 | P72: 1505 | Q72: 1505 | R72: 0 | S72: 244 | T72: 0 | U72: 0 | V72: 1505 | W72: 1505 | X72: 1433.333 | Y72: 71.667 | Z72: 5 | AA72: 0 | AB72: 0 | AC72: 0 | AD72: 71.667 | AE72: Aligarh | AF72: Uttar Pradesh | AG72: COD | AH72: 07AALCG0172B1Z0 | AI72: GOFPL2707100606 | AJ72: NKFC0000459950 | AL72: 46122.058 | AM72: 46122.548 | AN72: 46124.73 | AO72: 1 | AQ72: Yes | AR72: 3 | AS72: 7.166665 | AT72: Delivered
A73: APRIL_1_to_15_Orders | B73: 4 | C73: GOFPL | D73: GOTCHA FASHIONS PVT LTD_DL | E73: GOTCHA FASHIONS PRIVATE LIMITED-NF Mid Apr-26 Sales | F73: Fashion_GOFPL_042026_Sales_01-15 | G73: NYK-37995464-8603174 | H73: NYK-37995464-8603174-2-1 | I73: NYKF41991266 | J73: CHELV00000993 | K73: Chelvet Non-Wired Seamless Finish Plunge Bra (34D) | L73: Chelvet | M73: 62121000 | N73: 1849 | O73: 1295 | P73: 1295 | Q73: 1295 | R73: 0 | S73: 554 | T73: 0 | U73: 0 | V73: 1295 | W73: 1295 | X73: 1233.333 | Y73: 61.667 | Z73: 5 | AA73: 0 | AB73: 0 | AC73: 0 | AD73: 61.667 | AE73: Mumbai | AF73: Maharashtra | AG73: Prepaid | AH73: 07AALCG0172B1Z0 | AI73: GOFPL2707100593 | AJ73: 88363725166 | AK73: 28449611825965 | AL73: 46113.773 | AM73: 46114.531 | AN73: 46116.617 | AO73: 1 | AQ73: Yes | AR73: 1 | AS73: 0 | AT73: Return
A74: APRIL_1_to_15_Orders | B74: 4 | C74: GOFPL | D74: GOTCHA FASHIONS PVT LTD_DL | E74: GOTCHA FASHIONS PRIVATE LIMITED-NF Mid Apr-26 Sales | F74: Fashion_GOFPL_042026_Sales_01-15 | G74: NYK-38353353-2454726 | H74: NYK-38353353-2454726-4-1 | I74: NYKF42398213 | J74: CHELV00000058 | K74: Chelvet Solid Lightly Padded Half Coverage Plunge Bra (34B) | L74: Chelvet | M74: 61089100 | N74: 1499 | O74: 1050 | P74: 1029.17 | Q74: 1050 | R74: 0 | S74: 449 | T74: 20.83 | U74: 0 | V74: 1050 | W74: 1050 | X74: 1000 | Y74: 50 | Z74: 5 | AA74: 0 | AB74: 0 | AC74: 0 | AD74: 50 | AE74: Thane | AF74: Maharashtra | AG74: Prepaid | AH74: 07AALCG0172B1Z0 | AI74: GOFPL2707100613 | AJ74: 88364454975 | AL74: 46124.003 | AM74: 46125.68 | AN74: 46126.498 | AO74: 1 | AQ74: Yes | AR74: 1 | AS74: 5 | AT74: Delivered
A75: APRIL_1_to_15_Orders | B75: 4 | C75: GOFPL | D75: GOTCHA FASHIONS PVT LTD_DL | E75: GOTCHA FASHIONS PRIVATE LIMITED-NF Mid Apr-26 Sales | F75: Fashion_GOFPL_042026_Sales_01-15 | G75: NYK-38226770-3894103 | H75: NYK-38226770-3894103-1-1 | I75: NYKF42253730 | J75: CHELV00000088 | K75: Chelvet Solid Lightly Padded Half Coverage Plunge Bra (38D) | L75: Chelvet | M75: 61089100 | N75: 1499 | O75: 1050 | P75: 1050 | Q75: 1050 | R75: 0 | S75: 449 | T75: 0 | U75: 0 | V75: 1050 | W75: 1050 | X75: 1000 | Y75: 50 | Z75: 5 | AA75: 0 | AB75: 0 | AC75: 0 | AD75: 50 | AE75: Goa | AF75: Goa | AG75: Prepaid | AH75: 07AALCG0172B1Z0 | AI75: GOFPL2707100603 | AJ75: 28449602287231 | AK75: 28449612389664 | AL75: 46120.779 | AM75: 46121.496 | AN75: 46123.546 | AO75: 1 | AQ75: Yes | AR75: 1 | AS75: 0 | AT75: Return
A76: APRIL_1_to_15_Orders | B76: 4 | C76: GOFPL | D76: GOTCHA FASHIONS PVT LTD_DL | E76: GOTCHA FASHIONS PRIVATE LIMITED-NF Mid Apr-26 Sales | F76: Fashion_GOFPL_042026_Sales_01-15 | G76: NYK-38147233-2289513 | H76: NYK-38147233-2289513-2-1 | I76: NYKF42163237 | J76: CHELV00002230 | K76: Chelvet Black Satin Full-Sleeve Shirts with Pyjama (XL) | L76: Chelvet | M76: 61091000 | N76: 4950 | O76: 3168 | P76: 3082.29 | Q76: 3168 | R76: 0 | S76: 1782 | T76: 85.709999 | U76: 0 | V76: 3168 | W76: 3168 | X76: 2684.746 | Y76: 483.254 | Z76: 18 | AA76: 0 | AB76: 0 | AC76: 0 | AD76: 483.254 | AE76: Solan | AF76: Himachal Pradesh | AG76: COD | AH76: 09AALCG0172B1ZW | AI76: GOFPL2709100142 | AJ76: SF2188974608NYK | AL76: 46118.445 | AM76: 46120.637 | AO76: 1 | AQ76: Yes | AR76: 2 | AS76: 0 | AT76: Shipped
A77: APRIL_1_to_15_Orders | B77: 4 | C77: GOFPL | D77: GOTCHA FASHIONS PVT LTD_DL | E77: GOTCHA FASHIONS PRIVATE LIMITED-NF Mid Apr-26 Sales | F77: Fashion_GOFPL_042026_Sales_01-15 | G77: NYK-37997706-3786192 | H77: NYK-37997706-3786192-2-1 | I77: NYKF41993967 | J77: CHELV00001350 | K77: Chelvet Women Red Satin Solid Nightdress with Robe and Belt (S) | L77: Chelvet | M77: 62082200 | N77: 5699 | O77: 3477 | P77: 3361.04 | Q77: 3477 | R77: 0 | S77: 2222 | T77: 115.96 | U77: 0 | V77: 3477 | W77: 3477 | X77: 2946.61 | Y77: 530.39 | Z77: 18 | AA77: 0 | AB77: 0 | AC77: 0 | AD77: 530.39 | AE77: Pune | AF77: Maharashtra | AG77: Prepaid | AH77: 09AALCG0172B1ZW | AI77: GOFPL2709100136 | AJ77: 28449609594306 | AL77: 46113.833 | AM77: 46114.606 | AN77: 46117.562 | AO77: 1 | AQ77: Yes | AR77: 1 | AS77: 14.73305 | AT77: Delivered
A78: APRIL_1_to_15_Orders | B78: 4 | C78: GOFPL | D78: GOTCHA FASHIONS PVT LTD_DL | E78: GOTCHA FASHIONS PRIVATE LIMITED-NF Mid Apr-26 Sales | F78: Fashion_GOFPL_042026_Sales_01-15 | G78: NYK-38101831-5709355 | H78: NYK-38101831-5709355-2-1 | I78: NYKF42111030 | J78: CHELV00001538 | K78: Chelvet Women Nude Seamless Padded Bra (XL) | L78: Chelvet | M78: 62121000 | N78: 2264 | O78: 1495 | P78: 1387.33 | Q78: 1495 | R78: 0 | S78: 769 | T78: 107.67 | U78: 0 | V78: 1495 | W78: 1495 | X78: 1423.81 | Y78: 71.19 | Z78: 5 | AA78: 35.595 | AB78: 35.595 | AC78: 0 | AD78: 0 | AE78: Noida | AF78: Uttar Pradesh | AG78: COD | AH78: 09AALCG0172B1ZW | AI78: GOFPL2709100149 | AJ78: SF2188974685NYK | AL78: 46116.98 | AM78: 46119.492 | AN78: 46120.734 | AO78: 1 | AQ78: Yes | AR78: 1 | AS78: 7.11905 | AT78: Delivered
A79: APRIL_1_to_15_Orders | B79: 4 | C79: GOFPL | D79: GOTCHA FASHIONS PVT LTD_DL | E79: GOTCHA FASHIONS PRIVATE LIMITED-NF Mid Apr-26 Sales | F79: Fashion_GOFPL_042026_Sales_01-15 | G79: NYK-38114282-0809470 | H79: NYK-38114282-0809470-1-1 | I79: NYKF42125205 | J79: CHELV00001353 | K79: Chelvet Women Red Satin Solid Nightdress with Robe and Belt (XL) | L79: Chelvet | M79: 62082200 | N79: 5699 | O79: 3477 | P79: 3177 | Q79: 3477 | R79: 0 | S79: 2222 | T79: 300 | U79: 0 | V79: 3477 | W79: 3477 | X79: 2946.61 | Y79: 530.39 | Z79: 18 | AA79: 0 | AB79: 0 | AC79: 0 | AD79: 530.39 | AE79: Mumbai | AF79: Maharashtra | AG79: Prepaid | AH79: 09AALCG0172B1ZW | AI79: GOFPL2709100151 | AJ79: 28449602081954 | AK79: R1998765868NYK | AL79: 46117.502 | AM79: 46118.618 | AN79: 46121.542 | AO79: 1 | AQ79: Yes | AR79: 1 | AS79: 0 | AT79: Return
A80: APRIL_1_to_15_Orders | B80: 4 | C80: GOFPL | D80: GOTCHA FASHIONS PVT LTD_DL | E80: GOTCHA FASHIONS PRIVATE LIMITED-NF Mid Apr-26 Sales | F80: Fashion_GOFPL_042026_Sales_01-15 | G80: NYK-37978882-9341965 | H80: NYK-37978882-9341965-1-1 | I80: NYKF41973053 | J80: CHELV00000930 | K80: Chelvet Underwired Lightly Padded Demi Cup Bra (36D) | L80: Chelvet | M80: 62121000 | N80: 1699 | O80: 1394 | P80: 1394 | Q80: 1394 | R80: 0 | S80: 305 | T80: 0 | U80: 0 | V80: 1394 | W80: 1394 | X80: 1327.619 | Y80: 66.381 | Z80: 5 | AA80: 0 | AB80: 0 | AC80: 0 | AD80: 66.381 | AE80: Basna | AF80: Chhattisgarh | AG80: COD | AH80: 07AALCG0172B1Z0 | AI80: GOFPL2707100591 | AJ80: 28449601317134 | AL80: 46113.319 | AM80: 46113.481 | AN80: 46115.733 | AO80: 1 | AQ80: Yes | AR80: 2 | AS80: 6.638095 | AT80: Delivered
A81: MARCH_Orders | B81: 3 | C81: GOFPL | D81: GOTCHA FASHIONS PVT LTD_DL | E81: GOTCHA FASHIONS PRIVATE LIMITED-NF Mid Apr-26 Sales | F81: Fashion_GOFPL_042026_Sales_01-15 | G81: NYK-37933328-5885594 | H81: NYK-37933328-5885594-3-1 | I81: NYKF41921589 | J81: CHELV00002426 | K81: Chelvet Black Non-Padded Non-Wired Lace Bra (32C) | L81: Chelvet | M81: 62121000 | N81: 1499 | O81: 900 | P81: 900 | Q81: 900 | R81: 0 | S81: 599 | T81: 0 | U81: 0 | V81: 900 | W81: 900 | X81: 857.143 | Y81: 42.857 | Z81: 5 | AA81: 0 | AB81: 0 | AC81: 0 | AD81: 42.857 | AE81: Mumbai | AF81: Maharashtra | AG81: Prepaid | AH81: 09AALCG0172B1ZW | AI81: GOFPL2609100130 | AJ81: 28449593942166 | AL81: 46111.774 | AM81: 46112.626 | AN81: 46114.763 | AO81: 1 | AQ81: Yes | AR81: 1 | AS81: 4.285715 | AT81: Delivered | AU81: Shipped
A82: MARCH_Orders | B82: 3 | C82: GOFPL | D82: GOTCHA FASHIONS PVT LTD_DL | E82: GOTCHA FASHIONS PRIVATE LIMITED-NF Mid Apr-26 Sales | F82: Fashion_GOFPL_042026_Sales_01-15 | G82: NYK-37937276-4598834 | H82: NYK-37937276-4598834-1-1 | I82: NYKF41926100 | J82: CHELV00001068 | K82: Chelvet Medium Coverage Non-Wired Everyday Comfort Bra (34B) | L82: Chelvet | M82: 62121000 | N82: 1749 | O82: 1050 | P82: 1050 | Q82: 1050 | R82: 0 | S82: 699 | T82: 0 | U82: 0 | V82: 1050 | W82: 1050 | X82: 1000 | Y82: 50 | Z82: 5 | AA82: 0 | AB82: 0 | AC82: 0 | AD82: 50 | AE82: Noida | AF82: Uttar Pradesh | AG82: Prepaid | AH82: 07AALCG0172B1Z0 | AI82: GOFPL2607100589 | AJ82: SF2188719351NYK | AL82: 46111.875 | AM82: 46114.694 | AN82: 46118.453 | AO82: 1 | AQ82: Yes | AR82: 1 | AS82: 5 | AT82: Delivered | AU82: Not Shipped
A83: MARCH_Orders | B83: 3 | C83: GOFPL | D83: GOTCHA FASHIONS PVT LTD_DL | E83: GOTCHA FASHIONS PRIVATE LIMITED-NF Mid Apr-26 Sales | F83: Fashion_GOFPL_042026_Sales_01-15 | G83: NYK-37959008-0464981 | H83: NYK-37959008-0464981-2-1 | I83: NYKF41950261 | J83: CHELV00001054 | K83: Chelvet Medium Coverage Non-Wired Everyday Comfort Bra (38D) | L83: Chelvet | M83: 62121000 | N83: 1749 | O83: 1050 | P83: 970.95 | Q83: 1050 | R83: 0 | S83: 699 | T83: 79.050003 | U83: 0 | V83: 1050 | W83: 1050 | X83: 1000 | Y83: 50 | Z83: 5 | AA83: 0 | AB83: 0 | AC83: 0 | AD83: 50 | AE83: Pune | AF83: Maharashtra | AG83: COD | AH83: 07AALCG0172B1Z0 | AI83: GOFPL2707100592 | AJ83: 59694830930 | AL83: 46112.637 | AM83: 46113.653 | AN83: 46114.875 | AO83: 1 | AQ83: Yes | AR83: 2 | AS83: 5 | AT83: Delivered | AU83: Not Shipped
A84: MARCH_Orders | B84: 3 | C84: GOFPL | D84: GOTCHA FASHIONS PVT LTD_DL | E84: GOTCHA FASHIONS PRIVATE LIMITED-NF Mid Apr-26 Sales | F84: Fashion_GOFPL_042026_Sales_01-15 | G84: NYK-37883016-1384678 | H84: NYK-37883016-1384678-2-1 | I84: NYKF41864599 | J84: CHELV00001006 | K84: Chelvet Non-Wired Seamless Finish Plunge Bra (36C) | L84: Chelvet | M84: 62121000 | N84: 1849 | O84: 1295 | P84: 1201.73 | Q84: 1295 | R84: 0 | S84: 554 | T84: 93.269997 | U84: 0 | V84: 1295 | W84: 1295 | X84: 1233.333 | Y84: 61.667 | Z84: 5 | AA84: 0 | AB84: 0 | AC84: 0 | AD84: 61.667 | AE84: Jaipur | AF84: Rajasthan | AG84: Prepaid | AH84: 07AALCG0172B1Z0 | AI84: GOFPL2607100587 | AJ84: NKFP0000495235 | AL84: 46110.333 | AM84: 46111.548 | AN84: 46113.713 | AO84: 1 | AP84: Platform wide: Extra 10% off upto 270 on 1800 | AQ84: Yes | AR84: 1 | AS84: 6.166665 | AT84: Delivered | AU84: Shipped
A85: MARCH_Orders | B85: 3 | C85: GOFPL | D85: GOTCHA FASHIONS PVT LTD_DL | E85: GOTCHA FASHIONS PRIVATE LIMITED-NF Mid Apr-26 Sales | F85: Fashion_GOFPL_042026_Sales_01-15 | G85: NYK-37907332-9705408 | H85: NYK-37907332-9705408-1-2 | I85: NYKF41892073 | J85: CHELV00002431 | K85: Chelvet Black Non-Padded Non-Wired Lace Bra (36B) | L85: Chelvet | M85: 62121000 | N85: 1499 | O85: 900 | P85: 900 | Q85: 900 | R85: 0 | S85: 599 | T85: 0 | U85: 0 | V85: 900 | W85: 900 | X85: 857.143 | Y85: 42.857 | Z85: 5 | AA85: 0 | AB85: 0 | AC85: 0 | AD85: 42.857 | AE85: Udaipur | AF85: Rajasthan | AG85: Prepaid | AH85: 09AALCG0172B1ZW | AI85: GOFPL2609100126 | AJ85: SF2188718363NYK | AL85: 46110.892 | AM85: 46112.508 | AN85: 46114.545 | AO85: 1 | AQ85: Yes | AR85: 3 | AS85: 4.285715 | AT85: Delivered | AU85: Shipped
A86: MARCH_Orders | B86: 3 | C86: GOFPL | D86: GOTCHA FASHIONS PVT LTD_DL | E86: GOTCHA FASHIONS PRIVATE LIMITED-NF Mid Apr-26 Sales | F86: Fashion_GOFPL_042026_Sales_01-15 | G86: NYK-37907332-9705408 | H86: NYK-37907332-9705408-1-1 | I86: NYKF41892072 | J86: CHELV00000653 | K86: Chelvet Medium Coverage Non-Padded Organic Cotton Bra (36B) | L86: Chelvet | M86: 62121000 | N86: 1499 | O86: 795 | P86: 795 | Q86: 795 | R86: 0 | S86: 704 | T86: 0 | U86: 0 | V86: 795 | W86: 795 | X86: 757.143 | Y86: 37.857 | Z86: 5 | AA86: 0 | AB86: 0 | AC86: 0 | AD86: 37.857 | AE86: Udaipur | AF86: Rajasthan | AG86: Prepaid | AH86: 07AALCG0172B1Z0 | AI86: GOFPL2607100585 | AJ86: NKFP0000495651 | AL86: 46110.892 | AM86: 46111.548 | AN86: 46114.517 | AO86: 1 | AQ86: Yes | AR86: 3 | AS86: 3.785715 | AT86: Delivered | AU86: Shipped
A87: MARCH_Orders | B87: 3 | C87: GOFPL | D87: GOTCHA FASHIONS PVT LTD_DL | E87: GOTCHA FASHIONS PRIVATE LIMITED-NF Mid Apr-26 Sales | F87: Fashion_GOFPL_042026_Sales_01-15 | G87: NYK-37934667-8958134 | H87: NYK-37934667-8958134-5-1 | I87: NYKF41923158 | J87: CHELV00002360 | K87: Chelvet Purple Non-Padded Underwired Lace Bralette (38C) | L87: Chelvet | M87: 62121000 | N87: 2999 | O87: 1800 | P87: 1800 | Q87: 1800 | R87: 0 | S87: 1199 | T87: 0 | U87: 0 | V87: 1800 | W87: 1800 | X87: 1714.286 | Y87: 85.714 | Z87: 5 | AA87: 0 | AB87: 0 | AC87: 0 | AD87: 85.714 | AE87: Bangalore | AF87: Karnataka | AG87: Prepaid | AH87: 09AALCG0172B1ZW | AI87: GOFPL2609100131 | AJ87: 28449593945154 | AL87: 46111.81 | AM87: 46112.626 | AN87: 46114.715 | AO87: 1 | AQ87: Yes | AR87: 1 | AS87: 8.57143 | AT87: Delivered | AU87: Shipped
A88: MARCH_Orders | B88: 3 | C88: GOFPL | D88: GOTCHA FASHIONS PVT LTD_DL | E88: GOTCHA FASHIONS PRIVATE LIMITED-NF Mid Apr-26 Sales | F88: Fashion_GOFPL_042026_Sales_01-15 | G88: NYK-37854986-5144655 | H88: NYK-37854986-5144655-3-1 | I88: NYKF41832917 | J88: CHELV00000003 | K88: Chelvet Women Full Coverage Lightly Padded Bra (34B) | L88: Chelvet | M88: 61089100 | N88: 2099 | O88: 1407 | P88: 1337.37 | Q88: 1407 | R88: 0 | S88: 692 | T88: 69.629997 | U88: 0 | V88: 1407 | W88: 1407 | X88: 1340 | Y88: 67 | Z88: 5 | AA88: 0 | AB88: 0 | AC88: 0 | AD88: 67 | AE88: Cochin | AF88: Kerala | AG88: Prepaid | AH88: 07AALCG0172B1Z0 | AI88: GOFPL2607100586 | AJ88: 28449593844446 | AL88: 46109.451 | AM88: 46111.566 | AN88: 46115.511 | AO88: 1 | AQ88: Yes | AR88: 1 | AS88: 6.7 | AT88: Delivered | AU88: Shipped
A89: MARCH_Orders | B89: 3 | C89: GOFPL | D89: GOTCHA FASHIONS PVT LTD_DL | E89: GOTCHA FASHIONS PRIVATE LIMITED-NF Mid Apr-26 Sales | F89: Fashion_GOFPL_042026_Sales_01-15 | G89: NYK-37907332-9705408 | H89: NYK-37907332-9705408-1-2 | I89: NYKF41892073 | J89: CHELV00002407 | K89: Chelvet Nude Non-Padded Non-Wired Lace Bra (36B) | L89: Chelvet | M89: 62121000 | N89: 1499 | O89: 900 | P89: 900 | Q89: 900 | R89: 0 | S89: 599 | T89: 0 | U89: 0 | V89: 900 | W89: 900 | X89: 857.143 | Y89: 42.857 | Z89: 5 | AA89: 0 | AB89: 0 | AC89: 0 | AD89: 42.857 | AE89: Udaipur | AF89: Rajasthan | AG89: Prepaid | AH89: 09AALCG0172B1ZW | AI89: GOFPL2609100126 | AJ89: SF2188718363NYK | AL89: 46110.892 | AM89: 46112.508 | AN89: 46114.545 | AO89: 1 | AQ89: Yes | AR89: 3 | AS89: 4.285715 | AT89: Delivered | AU89: Shipped
A90: MARCH_Orders | B90: 3 | C90: GOFPL | D90: GOTCHA FASHIONS PVT LTD_DL | E90: GOTCHA FASHIONS PRIVATE LIMITED-NF Mid Apr-26 Sales | F90: Fashion_GOFPL_042026_Sales_01-15 | G90: NYK-37930342-9053107 | H90: NYK-37930342-9053107-2-1 | I90: NYKF41918271 | J90: CHELV00002444 | K90: Chelvet Red Padded Non-Wired Lace Bralette (36C) | L90: Chelvet | M90: 62121000 | N90: 2099 | O90: 1344 | P90: 1344 | Q90: 1344 | R90: 0 | S90: 755 | T90: 0 | U90: 0 | V90: 1344 | W90: 1344 | X90: 1280 | Y90: 64 | Z90: 5 | AA90: 0 | AB90: 0 | AC90: 0 | AD90: 64 | AE90: Calicut | AF90: Kerala | AG90: COD | AH90: 09AALCG0172B1ZW | AI90: GOFPL2609100129 | AJ90: 28449601228621 | AL90: 46111.695 | AM90: 46112.626 | AN90: 46116.769 | AO90: 1 | AQ90: Yes | AR90: 1 | AS90: 6.4 | AT90: Delivered | AU90: Shipped
A91: MARCH_Orders | B91: 3 | C91: GOFPL | D91: GOTCHA FASHIONS PVT LTD_DL | E91: GOTCHA FASHIONS PRIVATE LIMITED-NF Mid Apr-26 Sales | F91: Fashion_GOFPL_042026_Sales_01-15 | G91: NYK-37959008-0464981 | H91: NYK-37959008-0464981-2-2 | I91: NYKF41950262 | J91: CHELV00002100 | K91: Chelvet Women Padded Non-Wired Black T-Shirt Bra (40B) | L91: Chelvet | M91: 62121000 | N91: 1999 | O91: 1140 | P91: 1054.17 | Q91: 1140 | R91: 0 | S91: 859 | T91: 85.830002 | U91: 0 | V91: 1140 | W91: 1140 | X91: 1085.714 | Y91: 54.286 | Z91: 5 | AA91: 0 | AB91: 0 | AC91: 0 | AD91: 54.286 | AE91: Pune | AF91: Maharashtra | AG91: COD | AH91: 09AALCG0172B1ZW | AI91: GOFPL2609100132 | AJ91: 28449601291396 | AL91: 46112.637 | AM91: 46113.65 | AN91: 46116.485 | AO91: 1 | AQ91: Yes | AR91: 2 | AS91: 5.42857 | AT91: Delivered | AU91: Not Shipped
A92: MARCH_Orders | B92: 3 | C92: GOFPL | D92: GOTCHA FASHIONS PVT LTD_DL | E92: GOTCHA FASHIONS PRIVATE LIMITED-NF Mid Apr-26 Sales | F92: Fashion_GOFPL_042026_Sales_01-15 | G92: NYK-37875807-8074483 | H92: NYK-37875807-8074483-2-1 | I92: NYKF41856378 | J92: CHELV00002408 | K92: Chelvet Nude Non-Padded Non-Wired Lace Bra (36C) | L92: Chelvet | M92: 62121000 | N92: 1499 | O92: 900 | P92: 900 | Q92: 900 | R92: 0 | S92: 599 | T92: 0 | U92: 0 | V92: 900 | W92: 900 | X92: 857.143 | Y92: 42.857 | Z92: 5 | AA92: 0 | AB92: 0 | AC92: 0 | AD92: 42.857 | AE92: Dombivali | AF92: Maharashtra | AG92: Prepaid | AH92: 09AALCG0172B1ZW | AI92: GOFPL2609100127 | AJ92: 28449593866570 | AL92: 46109.948 | AM92: 46111.633 | AN92: 46117.701 | AO92: 1 | AQ92: Yes | AR92: 1 | AS92: 4.285715 | AT92: Delivered | AU92: Shipped
A93: MARCH_Orders | B93: 3 | C93: GOFPL | D93: GOTCHA FASHIONS PVT LTD_DL | E93: GOTCHA FASHIONS PRIVATE LIMITED-NF Mid Apr-26 Sales | F93: Fashion_GOFPL_042026_Sales_01-15 | G93: NYK-37916084-5488987 | H93: NYK-37916084-5488987-1-1 | I93: NYKF41902435 | J93: CHELV00002308 | K93: Chelvet Collared Full-Sleeve Shirt and Pyjama Burgundy (M) | L93: Chelvet | M93: 61091000 | N93: 4400 | O93: 2816 | P93: 2516 | Q93: 2816 | R93: 0 | S93: 1584 | T93: 300 | U93: 0 | V93: 2816 | W93: 2816 | X93: 2386.441 | Y93: 429.559 | Z93: 18 | AA93: 214.78 | AB93: 214.78 | AC93: 0 | AD93: 0 | AE93: Noida | AF93: Uttar Pradesh | AG93: Prepaid | AH93: 09AALCG0172B1ZW | AI93: GOFPL2609100128 | AJ93: SF2188718432NYK | AL93: 46111.075 | AM93: 46112.508 | AN93: 46113.704 | AO93: 1 | AP93: Platform wide: Extra 15% off upto 300 on 1800 | AQ93: Yes | AR93: 1 | AS93: 11.932205 | AT93: Delivered | AU93: Shipped
A94: MARCH_Orders | B94: 3 | C94: GOFPL | D94: GOTCHA FASHIONS PVT LTD_DL | E94: GOTCHA FASHIONS PRIVATE LIMITED-NF Mid Apr-26 Sales | F94: Fashion_GOFPL_042026_Sales_01-15 | G94: NYK-37959422-1403281 | H94: NYK-37959422-1403281-4-1 | I94: NYKF41950791 | J94: CHELV00001174 | K94: Chelvet Non-Wired Medium Coverage T-Shirt Bra (38C) | L94: Chelvet | M94: 62121000 | N94: 1849 | O94: 1054 | P94: 1054 | Q94: 1054 | R94: 0 | S94: 795 | T94: 0 | U94: 0 | V94: 1054 | W94: 1054 | X94: 1003.81 | Y94: 50.19 | Z94: 5 | AA94: 0 | AB94: 0 | AC94: 0 | AD94: 50.19 | AE94: Kolkata | AF94: West Bengal | AG94: Prepaid | AH94: 07AALCG0172B1Z0 | AI94: GOFPL2707100590 | AJ94: 88363669365 | AL94: 46112.648 | AM94: 46113.653 | AN94: 46114.659 | AO94: 1 | AQ94: Yes | AR94: 1 | AS94: 5.01905 | AT94: Delivered | AU94: Not Shipped
A95: APRIL_16_to_31_Orders | B95: 4 | C95: GOFPL | D95: GOTCHA FASHIONS PVT LTD_DL | E95: GOTCHA FASHIONS PVT LTD_DL-NF Apr-26 Sales | F95: Fashion_GOFPL_042026_Sales_01-30 | G95: NYK-38953510-8044620 | H95: NYK-38953510-8044620-2-1 | I95: NYKF43094541 | J95: CHELV00001499 | K95: Chelvet Women Pink Satin Solid Cami with Pyjama (M) | L95: Chelvet | M95: 62082200 | N95: 4199 | O95: 2646 | P95: 2592.85 | Q95: 2646 | R95: 0 | S95: 1553 | T95: 53.150002 | U95: 0 | V95: 2646 | W95: 2646 | X95: 2242.373 | Y95: 403.627 | Z95: 18 | AA95: 0 | AB95: 0 | AC95: 0 | AD95: 403.627 | AE95: Pune | AF95: Maharashtra | AG95: Prepaid | AH95: 09AALCG0172B1ZW | AI95: GOFPL2709100206 | AJ95: 28449598453600 | AL95: 46140.387 | AM95: 46140.599 | AO95: 1 | AP95: mov changed to 1000 - 11/9 max disc changed to 220 | AQ95: Yes | AR95: 4 | AS95: 0 | AT95: Shipped
A96: APRIL_16_to_31_Orders | B96: 4 | C96: GOFPL | D96: GOTCHA FASHIONS PVT LTD_DL | E96: GOTCHA FASHIONS PVT LTD_DL-NF Apr-26 Sales | F96: Fashion_GOFPL_042026_Sales_01-30 | G96: NYK-38748953-6064872 | H96: NYK-38748953-6064872-1-1 | I96: NYKF42858810 | J96: CHELV00001684 | K96: Chelvet Pink Satin Cami With Pyjama (S) | L96: Chelvet | M96: 62082200 | N96: 3299 | O96: 1980 | P96: 1825.54 | Q96: 1980 | R96: 0 | S96: 1319 | T96: 154.46001 | U96: 0 | V96: 1980 | W96: 1980 | X96: 1885.714 | Y96: 94.286 | Z96: 5 | AA96: 47.143 | AB96: 47.143 | AC96: 0 | AD96: 0 | AE96: Shikohabad | AF96: Uttar Pradesh | AG96: Prepaid | AH96: 09AALCG0172B1ZW | AI96: GOFPL2709100192 | AJ96: SF2188766945NYK | AL96: 46134.114 | AM96: 46136.988 | AO96: 1 | AP96: Extra 10% off upto 270 on mov of 1800 | AQ96: Yes | AR96: 1 | AS96: 0 | AT96: RTO
A97: APRIL_16_to_31_Orders | B97: 4 | C97: GOFPL | D97: GOTCHA FASHIONS PVT LTD_DL | E97: GOTCHA FASHIONS PVT LTD_DL-NF Apr-26 Sales | F97: Fashion_GOFPL_042026_Sales_01-30 | G97: NYK-38846116-4659429 | H97: NYK-38846116-4659429-3-1 | I97: NYKF42969838 | J97: CHELV00000058 | K97: Chelvet Solid Lightly Padded Half Coverage Plunge Bra (34B) | L97: Chelvet | M97: 61089100 | N97: 1499 | O97: 1050 | P97: 972.46 | Q97: 1050 | R97: 0 | S97: 449 | T97: 77.540001 | U97: 0 | V97: 1050 | W97: 1050 | X97: 1000 | Y97: 50 | Z97: 5 | AA97: 0 | AB97: 0 | AC97: 0 | AD97: 50 | AE97: Moradabad | AF97: Uttar Pradesh | AG97: Prepaid | AH97: 07AALCG0172B1Z0 | AI97: GOFPL2707100640 | AJ97: SF2188772450NYK | AL97: 46137.107 | AM97: 46137.604 | AN97: 46140.485 | AO97: 1 | AP97: mov changed to 1000 - 11/9 max disc changed to 220 | AQ97: Yes | AR97: 1 | AS97: 5 | AT97: Delivered
A98: APRIL_16_to_31_Orders | B98: 4 | C98: GOFPL | D98: GOTCHA FASHIONS PVT LTD_DL | E98: GOTCHA FASHIONS PVT LTD_DL-NF Apr-26 Sales | F98: Fashion_GOFPL_042026_Sales_01-30 | G98: NYK-38631087-6692600 | H98: NYK-38631087-6692600-12-1 | I98: NYKF42719816 | J98: CHELV00002090 | K98: Chelvet Women Padded Non-Wired Black T-Shirt Bra (32C) | L98: Chelvet | M98: 62121000 | N98: 1999 | O98: 1140 | P98: 1140 | Q98: 1140 | R98: 0 | S98: 859 | T98: 0 | U98: 0 | V98: 1140 | W98: 1140 | X98: 1085.714 | Y98: 54.286 | Z98: 5 | AA98: 0 | AB98: 0 | AC98: 0 | AD98: 54.286 | AE98: New Delhi | AF98: Delhi | AG98: Prepaid | AH98: 09AALCG0172B1ZW | AI98: GOFPL2709100185 | AJ98: SF2188762497NYK | AL98: 46131.112 | AM98: 46132.791 | AN98: 46133.829 | AO98: 1 | AQ98: Yes | AR98: 1 | AS98: 5.42857 | AT98: Delivered
A99: APRIL_16_to_31_Orders | B99: 4 | C99: GOFPL | D99: GOTCHA FASHIONS PVT LTD_DL | E99: GOTCHA FASHIONS PVT LTD_DL-NF Apr-26 Sales | F99: Fashion_GOFPL_042026_Sales_01-30 | G99: NYK-38691913-4903387 | H99: NYK-38691913-4903387-2-1 | I99: NYKF42790882 | J99: CHELV00001536 | K99: Chelvet Women Nude Seamless Padded Bra (M) | L99: Chelvet | M99: 62121000 | N99: 2264 | O99: 1495 | P99: 1495 | Q99: 1495 | R99: 0 | S99: 769 | T99: 0 | U99: 0 | V99: 1495 | W99: 1495 | X99: 1423.81 | Y99: 71.19 | Z99: 5 | AA99: 35.595 | AB99: 35.595 | AC99: 0 | AD99: 0 | AE99: Ghaziabad | AF99: Uttar Pradesh | AG99: COD | AH99: 09AALCG0172B1ZW | AI99: GOFPL2709100187 | AJ99: SF2188995250NYK | AL99: 46132.712 | AM99: 46133.52 | AN99: 46135.621 | AO99: 1 | AQ99: Yes | AR99: 1 | AS99: 7.11905 | AT99: Delivered
A100: APRIL_16_to_31_Orders | B100: 4 | C100: GOFPL | D100: GOTCHA FASHIONS PVT LTD_DL | E100: GOTCHA FASHIONS PVT LTD_DL-NF Apr-26 Sales | F100: Fashion_GOFPL_042026_Sales_01-30 | G100: NYK-38877047-9000110 | H100: NYK-38877047-9000110-4-1 | I100: NYKF43005239 | J100: CHELV00000793 | K100: Chelvet Women's Lightly Padded Wireless Medium Coverage Bra | Printed Everyday Support & Shape (34B) | L100: Chelvet | M100: 62121000 | N100: 1999 | O100: 1000 | P100: 928.21 | Q100: 1000 | R100: 0 | S100: 999 | T100: 71.790001 | U100: 0 | V100: 1000 | W100: 1000 | X100: 952.381 | Y100: 47.619 | Z100: 5 | AA100: 0 | AB100: 0 | AC100: 0 | AD100: 47.619 | AE100: Ahmedabad | AF100: Gujarat | AG100: COD | AH100: 07AALCG0172B1Z0 | AI100: GOFPL2707100647 | AJ100: 59696112674 | AL100: 46137.968 | AM100: 46140.537 | AN100: 46141.595 | AO100: 1 | AP100: NB: Flat 300 off on 2500 - Dynamic on 2 PVs - RB | AQ100: Yes | AR100: 1 | AS100: 4.761905 | AT100: Delivered
...

Sheet myntra
A1: sale_order_code | B1: order_number | C1: order_date | D1: packing_date | E1: invoice_number | F1: product_sku_code | G1: order_item_status | H1: promised_delivery_date | I1: actual_delivery_date | J1: return_date | K1: restocked_date | L1: return_type | M1: promised_settlement_date | N1: currency | O1: seller_paid_amount | P1: postpaid_amount | Q1: prepaid_amount | R1: mrp | S1: discount_amount | T1: shipping_case | U1: tax_rate | V1: igst_amount | W1: cgst_amount | X1: sgst_amount | Y1: tcs_igst_amt | Z1: tcs_sgst_amt | AA1: tcs_cgst_amt | AB1: minimum_commission | AC1: commission_pct | AD1: commission_total_amount | AE1: total_commission_plus_tcs_deduction_fw | AF1: logistics_deduction_fw | AG1: customer_paid_amt_fw | AH1: total_settlement_fw | AI1: amount_pending_settlement_fw | AJ1: prepaid_commission_deduction_fw | AK1: prepaid_logistics_deduction_fw | AL1: prepaid_payment_fw | AM1: postpaid_commission_deduction_fw | AN1: postpaid_logistics_deduction_fw | AO1: postpaid_payment_fw | AP1: settlement_date_prepaid_comm_deduction_fw | AQ1: settlement_date_prepaid_logistics_deduction_fw | AR1: settlement_date_prepaid_payment_fw | AS1: settlement_date_postpaid_comm_deduction_fw | AT1: settlement_date_postpaid_logistics_deduction_fw | AU1: settlement_date_postpaid_payment_fw | AV1: bank_utr_no_prepaid_comm_deduction_fw | AW1: bank_utr_no_prepaid_logistics_deduction_fw | AX1: bank_utr_no_prepaid_payment_fw | AY1: bank_utr_no_postpaid_comm_deduction_fw | AZ1: bank_utr_no_postpaid_logistics_deduction_fw | BA1: bank_utr_no_postpaid_payment_fw | BB1: total_commission_plus_tcs_deduction_rv | BC1: logistics_deduction_rv | BD1: customer_paid_amt_rv | BE1: total_settlement_rv | BF1: amount_pending_settlement_rv | BG1: prepaid_commission_deduction_rv | BH1: prepaid_logistics_deduction_rv | BI1: prepaid_payment_rv | BJ1: postpaid_commission_deduction_rv | BK1: postpaid_logistics_deduction_rv | BL1: postpaid_payment_rv | BM1: settlement_date_prepaid_comm_deduction_rv | BN1: settlement_date_prepaid_logistics_deduction_rv | BO1: settlement_date_prepaid_payment_rv | BP1: settlement_date_postpaid_comm_deduction_rv | BQ1: settlement_date_postpaid_logistics_deduction_rv | BR1: settlement_date_postpaid_payment_rv | BS1: bank_utr_no_prepaid_comm_deduction_rv | BT1: bank_utr_no_prepaid_logistics_deduction_rv | BU1: bank_utr_no_prepaid_payment_rv | BV1: bank_utr_no_postpaid_comm_deduction_rv | BW1: bank_utr_no_postpaid_logistics_deduction_rv | BX1: bank_utr_no_postpaid_payment_rv | BY1: courier_name | BZ1: e_commerce_portal_name | CA1: hsn | CB1: product_tax_category | CC1: payment_method | CD1: brand | CE1: gender | CF1: article_type | CG1: supply_type | CH1: is_try_and_buy | CI1: tracking_no | CJ1: customer_name | CK1: customer_pincode | CL1: customer_state | CM1: igst_rate | CN1: cgst_rate | CO1: sgst_rate | CP1: taxable_amount | CQ1: tcs_igst_rate | CR1: tcs_sgst_rate | CS1: tcs_cgst_rate | CT1: shipping_amount | CU1: gift_amount | CV1: cart_discount | CW1: coupon_discount | CX1: seller_gstn | CY1: seller_name | CZ1: seller_state_code | DA1: additional_amount | DB1: postpaid_amount_other | DC1: prepaid_amount_other | DD1: myntra_gstn | DE1: party_id_to | DF1: Item_Code | DG1: Item_Created_On | DH1: Item_Updated_On | DI1: Item_Status | DJ1: GRN_Number | DK1: GRN_Created | DL1: Vendor_Code | DM1: Facility | DN1: Item_Type_Name | DO1: _MRP | DP1: Item_Type_skuCode | DQ1: Vendor_skuCode | DR1: Unit_price_without_tax | DS1: Unit_price_with_tax | DT1: Rejection_Reason | DU1: Gate_Pass_No | DV1: Gate_Pass_Type | DW1: Gate_Pass_Status | DX1: Gate_Pass_Created | DY1: HSN_Code | DZ1: _Invoice_Number | EA1: _Invoice_Date | EB1: FOCI_PO_TYPE | EC1: PO_Code | ED1: PO_Created | EE1: Sale_Order_status | EF1: Myntra_Status_OGP | EG1: Vendor_Style_Code | EH1: ASN_code | EI1: ASN_created | EJ1: ASN_packed | EK1: ASN_picked | EL1: FOCI_supply_type | EM1: Total_Customer_Paid | EN1: commission_base_amount | EO1: commission_tax_amount | EP1: packed_id | EQ1: seller_order_id | ER1: return_id | ES1: item_id | ET1: return_status
A2: 100062098942 | B2: 1.3291408e+20 | C2: 2026-04-27T09:30:17.000+05:30 | D2: 46139.558 | E2: I0727GE000004876 | F2: CVETBRAA103717725 | G2: delivered | H2: 46144.479 | I2: 46143.775 | N2: INR | O2: 883 | P2: 0 | Q2: 882.99 | R2: 1849 | S2: 872 | T2: Inter-State | U2: 5 | V2: 42.05 | W2: 0 | X2: 0 | Y2: 4.20475 | Z2: 0 | AA2: 0 | AB2: 0 | AC2: 13.35 | AD2: 117.88 | BZ2: Myntra Designs Pvt Ltd | CA2: 62121000 | CB2: Apparel | CD2: Chelvet | CE2: Women | CF2: Bra | CG2: ON_HAND | CH2: FALSE | CI2: MYSP1394390734 | CJ2: 90c07133.382b.45ea.96e8.63a1892de4810HpFM8CVmf | CK2: 560034 | CL2: KA | CM2: 5 | CN2: 0 | CO2: 0 | CP2: 840.95 | CQ2: 0.5 | CR2: 0 | CS2: 0 | CT2: 0 | CU2: 0 | CW2: 0 | CX2: 07AALCG0172B1Z0 | CZ2: DL | DA2: 0 | DB2: 0 | DC2: 0 | DD2: 29AAECM9636P1ZJ | DE2: 27477 | EB2: PPMP | EL2: ON_HAND | EM2: 977.01 | EP2: 1000018121905 | EQ2: 3626c190-f207-4614-a06b-e62ed12ca6c5 | ES2: 11116828070
A3: 100046237953 | B3: 1.3282998e+20 | C3: 2026-04-17T15:53:52.000+05:30 | D3: 46129.667 | E3: I0927GE000000139 | F3: CVETBRAA127094138 | G3: reverse_in_transit | H3: 46134.479 | I3: 46135.069 | J3: 46135.086 | L3: return_refund | N3: INR | O3: 742 | P3: 0 | Q3: 742 | R3: 2199 | S3: 1363 | T3: Inter-State | U3: 5 | V3: 35.33 | W3: 0 | X3: 0 | Y3: 3.53335 | Z3: 0 | AA3: 0 | AB3: 0 | AC3: 14.29 | AD3: 106.032 | BZ3: Myntra Designs Pvt Ltd | CA3: 62121000 | CB3: Apparel | CD3: Chelvet | CE3: Women | CF3: Bra | CG3: ON_HAND | CH3: FALSE | CI3: MYSP1390016902 | CJ3: d67c8db3.7b7e.4e47.b779.d3dd19d0948d4YpKMinOEy | CK3: 400097 | CL3: MH | CM3: 5 | CN3: 0 | CO3: 0 | CP3: 706.67 | CQ3: 0.5 | CR3: 0 | CS3: 0 | CT3: 0 | CU3: 0 | CW3: 0 | CX3: 09AALCG0172B1ZW | CZ3: UP | DA3: 0 | DB3: 0 | DC3: 0 | DD3: 29AAECM9636P1ZJ | DE3: 27477 | EB3: PPMP | EL3: ON_HAND | EM3: 836 | EP3: 100046237953 | EQ3: 61edc745-b1dc-4b52-86d0-0fcca2aac121 | ES3: 11100966920 | ET3: DLS
A4: 100050606696 | B4: 1.3284962e+20 | C4: 2026-04-19T22:26:23.000+05:30 | D4: 46133.47 | E4: I0727GE000003975 | F4: CVETBRAA103682614 | G4: delivered | H4: 46139.354 | I4: 46139.684 | N4: INR | O4: 589 | P4: 0 | Q4: 589 | R4: 1499 | S4: 816 | T4: Inter-State | U4: 5 | V4: 28.05 | W4: 0 | X4: 0 | Y4: 2.80475 | Z4: 0 | AA4: 0 | AB4: 0 | AC4: 20.06 | AD4: 118.153 | BZ4: Myntra Designs Pvt Ltd | CA4: 62121000 | CB4: Apparel | CD4: Chelvet | CE4: Women | CF4: Bra | CG4: ON_HAND | CH4: FALSE | CI4: MYSP1391692628 | CJ4: 80e92566.58ba.4ee8.98c6.7581db0ff471N54UljOCg1 | CK4: 515004 | CL4: AP | CM4: 5 | CN4: 0 | CO4: 0 | CP4: 560.95 | CQ4: 0.5 | CR4: 0 | CS4: 0 | CT4: 0 | CU4: 0 | CW4: 0 | CX4: 07AALCG0172B1Z0 | CZ4: DL | DA4: 0 | DB4: 0 | DC4: 0 | DD4: 29AAECM9636P1ZJ | DE4: 27477 | EB4: PPMP | EL4: ON_HAND | EM4: 683 | EP4: 100050606696 | EQ4: e7d979c2-1e44-4002-a9d8-1bcc551fea9a | ES4: 11105335711
A5: 100045641471 | B5: 1.3282772e+20 | C5: 2026-04-17T09:37:33.000+05:30 | D5: 46129.432 | E5: I0927GE000000127 | F5: CVETNTST127223919 | G5: delivered | H5: 46133.479 | I5: 46133.776 | N5: INR | O5: 3294.01 | P5: 0 | Q5: 3294 | R5: 5500 | S5: 2000 | T5: Inter-State | U5: 18 | V5: 502.48 | W5: 0 | X5: 0 | Y5: 13.95765 | Z5: 0 | AA5: 0 | AB5: 0 | AC5: 17.7 | AD5: 583.038 | BZ5: Myntra Designs Pvt Ltd | CA5: 62082200 | CB5: Apparel | CD5: Chelvet | CE5: Women | CF5: Night suits | CG5: ON_HAND | CH5: FALSE | CI5: MYSP1389820286 | CJ5: 9bcec229.faed.4749.98fb.f858b5b65a3d5hb3fn65Wv | CK5: 248198 | CL5: UT | CM5: 18 | CN5: 0 | CO5: 0 | CP5: 2791.53 | CQ5: 0.5 | CR5: 0 | CS5: 0 | CT5: 0 | CU5: 0 | CW5: 0 | CX5: 09AALCG0172B1ZW | CZ5: UP | DA5: 0 | DB5: 0 | DC5: 0 | DD5: 29AAECM9636P1ZJ | DE5: 27477 | EB5: PPMP | EL5: ON_HAND | EM5: 3500.01 | EP5: 100045641471 | EQ5: 7860f2a7-4a08-4821-8923-9ef54a266cf4 | ES5: 11100370438
A6: 100057688280 | B6: 1.328908e+20 | C6: 2026-04-24T16:51:14.000+05:30 | D6: 46137.443 | E6: I0727GE000004556 | F6: CVETBRAA103646617 | G6: delivered | H6: 46141.479 | I6: 46141.714 | N6: INR | O6: 625 | P6: 0 | Q6: 625 | R6: 1499 | S6: 780 | T6: Inter-State | U6: 5 | V6: 29.76 | W6: 0 | X6: 0 | Y6: 2.9762 | Z6: 0 | AA6: 0 | AB6: 0 | AC6: 12.05 | AD6: 75.312 | BZ6: Myntra Designs Pvt Ltd | CA6: 62121000 | CB6: Apparel | CD6: Chelvet | CE6: Women | CF6: Bra | CG6: ON_HAND | CH6: FALSE | CI6: MYSP1393344595 | CJ6: e7438daf.b8f6.43f2.9c60.32ea9b29dd0917J2mkJM0N | CK6: 411008 | CL6: MH | CM6: 5 | CN6: 0 | CO6: 0 | CP6: 595.24 | CQ6: 0.5 | CR6: 0 | CS6: 0 | CT6: 0 | CU6: 0 | CW6: 0 | CX6: 07AALCG0172B1Z0 | CZ6: DL | DA6: 0 | DB6: 0 | DC6: 0 | DD6: 29AAECM9636P1ZJ | DE6: 27477 | EB6: PPMP | EL6: ON_HAND | EM6: 719 | EP6: 100057688280 | EQ6: 629d2633-0881-413e-a22b-2337640a6ec9 | ES6: 11112417349
A7: 100027429716 | B7: 1.3274546e+20 | C7: 2026-04-07T21:07:14.000+05:30 | D7: 46120.417 | E7: I0727GE000001551 | F7: CVETBRAA103705077 | G7: delivered | H7: 46124.479 | I7: 46123.753 | N7: INR | O7: 608 | P7: 0 | Q7: 608 | R7: 1849 | S7: 1147 | T7: Inter-State | U7: 5 | V7: 28.95 | W7: 0 | X7: 0 | Y7: 2.89525 | Z7: 0 | AA7: 0 | AB7: 0 | AC7: 10.3 | AD7: 62.624 | BZ7: Myntra Designs Pvt Ltd | CA7: 62121000 | CB7: Apparel | CD7: Chelvet | CE7: Women | CF7: Bra | CG7: ON_HAND | CH7: FALSE | CI7: MYSP1385237800 | CJ7: af012cee.7b87.4aa9.abb4.8b9e6c368838wTVmSLiGej | CK7: 411011 | CL7: MH | CM7: 5 | CN7: 0 | CO7: 0 | CP7: 579.05 | CQ7: 0.5 | CR7: 0 | CS7: 0 | CT7: 0 | CU7: 0 | CW7: 0 | CX7: 07AALCG0172B1Z0 | CZ7: DL | DA7: 0 | DB7: 0 | DC7: 0 | DD7: 29AAECM9636P1ZJ | DE7: 27477 | EB7: PPMP | EL7: ON_HAND | EM7: 702 | EP7: 100027429716 | EQ7: f7d5a0e8-d2a3-4405-9d18-03a2cdbbdf98 | ES7: 11082158650
A8: 100036528122 | B8: 1.3278629e+20 | C8: 2026-04-12T14:31:51.000+05:30 | D8: 46125.461 | E8: I0727GE000002474 | F8: CVETBRAA103722914 | G8: delivered | H8: 46129.479 | I8: 46130.025 | N8: INR | O8: 525 | P8: 0 | Q8: 525 | R8: 1999 | S8: 1380 | T8: Inter-State | U8: 5 | V8: 25 | W8: 0 | X8: 0 | Y8: 2.5 | Z8: 0 | AA8: 0 | AB8: 0 | AC8: 8.65 | AD8: 45.413 | BZ8: Myntra Designs Pvt Ltd | CA8: 62121000 | CB8: Apparel | CD8: Chelvet | CE8: Women | CF8: Bra | CG8: ON_HAND | CH8: FALSE | CI8: MYSP1387970834 | CJ8: 916d20ab.e348.4064.94ac.1b91b63cee68ovL07npyng | CK8: 560043 | CL8: KA | CM8: 5 | CN8: 0 | CO8: 0 | CP8: 500 | CQ8: 0.5 | CR8: 0 | CS8: 0 | CT8: 0 | CU8: 0 | CW8: 0 | CX8: 07AALCG0172B1Z0 | CZ8: DL | DA8: 0 | DB8: 0 | DC8: 0 | DD8: 29AAECM9636P1ZJ | DE8: 27477 | EB8: PPMP | EL8: ON_HAND | EM8: 619 | EP8: 100036528122 | EQ8: 7342fcb4-c5f2-4f53-bd2b-8c9eb19fd50b | ES8: 11091257077
A9: 100037450836 | B9: 1.3278906e+20 | C9: 2026-04-12T22:14:10.000+05:30 | D9: 46126.415 | E9: I0927GE000000103 | F9: CVETBRAA127094095 | G9: reverse_in_transit | H9: 46130.479 | L9: release_rto_refund | N9: INR | O9: 645 | P9: 0 | Q9: 645 | R9: 1999 | S9: 1260 | T9: Inter-State | U9: 5 | V9: 30.71 | W9: 0 | X9: 0 | Y9: 3.07145 | Z9: 0 | AA9: 0 | AB9: 0 | AC9: 14.04 | AD9: 90.558 | BZ9: Myntra Designs Pvt Ltd | CA9: 62121000 | CB9: Apparel | CD9: Chelvet | CE9: Women | CF9: Bra | CG9: ON_HAND | CH9: FALSE | CI9: MYSP1388414214 | CJ9: 9e0ed2fb.02e9.41ad.a516.3ad714ee62a1uctYnI4GUT | CK9: 411021 | CL9: MH | CM9: 5 | CN9: 0 | CO9: 0 | CP9: 614.29 | CQ9: 0.5 | CR9: 0 | CS9: 0 | CT9: 0 | CU9: 0 | CW9: 0 | CX9: 09AALCG0172B1ZW | CZ9: UP | DA9: 0 | DB9: 0 | DC9: 0 | DD9: 29AAECM9636P1ZJ | DE9: 27477 | EB9: PPMP | EL9: ON_HAND | EM9: 739 | EP9: 100037450836 | EQ9: 25ec7360-e465-419a-b8af-93ba7a568654 | ES9: 11092179791
A10: 100037219755 | B10: 1.327884e+20 | C10: 2026-04-12T20:24:37.000+05:30 | D10: 46125.464 | E10: I0727GE000002500 | F10: CVETBRAA103682605 | G10: delivered | H10: 46129.479 | I10: 46129.667 | N10: INR | O10: 535 | P10: 0 | Q10: 535 | R10: 1499 | S10: 870 | T10: Inter-State | U10: 5 | V10: 25.48 | W10: 0 | X10: 0 | Y10: 2.5476 | Z10: 0 | AA10: 0 | AB10: 0 | AC10: 11.88 | AD10: 63.558 | BZ10: Myntra Designs Pvt Ltd | CA10: 62121000 | CB10: Apparel | CD10: Chelvet | CE10: Women | CF10: Bra | CG10: ON_HAND | CH10: FALSE | CI10: MYEP1114324694 | CJ10: cab1b639.12d7.4a1b.9357.f13f0918cc74A7vLlAc5hi | CK10: 815301 | CL10: JH | CM10: 5 | CN10: 0 | CO10: 0 | CP10: 509.52 | CQ10: 0.5 | CR10: 0 | CS10: 0 | CT10: 0 | CU10: 0 | CW10: 0 | CX10: 07AALCG0172B1Z0 | CZ10: DL | DA10: 0 | DB10: 0 | DC10: 0 | DD10: 29AAECM9636P1ZJ | DE10: 27477 | EB10: PPMP | EL10: ON_HAND | EM10: 629 | EP10: 100037219755 | EQ10: d473029c-50c3-4c0b-ac95-c7cc01596278 | ES10: 11091948710
A11: 100031467610 | B11: 1.3276307e+20 | C11: 2026-04-09T22:01:59.000+05:30 | D11: 46122.44 | E11: I0927GE000000073 | F11: CVETBRAA127713179 | G11: delivered | H11: 46129.479 | I11: 46128.026 | N11: INR | O11: 998 | P11: 998 | Q11: 0 | R11: 2999 | S11: 1830 | T11: Inter-State | U11: 5 | V11: 47.52 | W11: 0 | X11: 0 | Y11: 4.7524 | Z11: 0 | AA11: 0 | AB11: 0 | AC11: 14.2 | AD11: 141.716 | BZ11: Myntra Designs Pvt Ltd | CA11: 62121000 | CB11: Apparel | CD11: Chelvet | CE11: Women | CF11: Bra | CG11: ON_HAND | CH11: FALSE | CI11: MYSC1282367654 | CJ11: a0a373c3.ea0f.495c.8a6a.d29ed96a3d576ftjMqPHHx | CK11: 190001 | CL11: JK | CM11: 5 | CN11: 0 | CO11: 0 | CP11: 950.48 | CQ11: 0.5 | CR11: 0 | CS11: 0 | CT11: 0 | CU11: 0 | CW11: 0 | CX11: 09AALCG0172B1ZW | CZ11: UP | DA11: 0 | DB11: 0 | DC11: 0 | DD11: 29AAECM9636P1ZJ | DE11: 27477 | EB11: PPMP | EL11: ON_HAND | EM11: 1169 | EP11: 1000009096790 | EQ11: 11fbd2da-3ef7-4682-b12b-8ff46799b138 | ES11: 11086196556
A12: 100014574204 | B12: 1.3269119e+20 | C12: 2026-04-01T14:21:54.000+05:30 | D12: 46114.429 | E12: I0727GE000000285 | F12: CVETBRAA103697034 | G12: reverse_in_transit | H12: 46120.958 | L12: release_rto_refund | N12: INR | O12: 622 | P12: 622 | Q12: 0 | R12: 1749 | S12: 1033 | T12: Inter-State | U12: 5 | V12: 29.62 | W12: 0 | X12: 0 | Y12: 2.9619 | Z12: 0 | AA12: 0 | AB12: 0 | AC12: 11.79 | AD12: 73.334 | BZ12: Myntra Designs Pvt Ltd | CA12: 62121000 | CB12: Apparel | CD12: Chelvet | CE12: Women | CF12: Bra | CG12: ON_HAND | CH12: FALSE | CI12: 5965570380431 | CJ12: e6c7ef34.85ea.4055.9bdc.0ef21197d8bbgO4fJOUarw | CK12: 272152 | CL12: UP | CM12: 5 | CN12: 0 | CO12: 0 | CP12: 592.38 | CQ12: 0.5 | CR12: 0 | CS12: 0 | CT12: 0 | CU12: 0 | CW12: 0 | CX12: 07AALCG0172B1Z0 | CZ12: DL | DA12: 0 | DB12: 0 | DC12: 0 | DD12: 29AAECM9636P1ZJ | DE12: 27477 | EB12: PPMP | EL12: ON_HAND | EM12: 716 | EP12: 100014574204 | EQ12: 32c8db63-01db-48d5-b5af-0dc5a40e2a3d | ES12: 11069303026
A13: 100047464456 | B13: 1.3283658e+20 | C13: 2026-04-18T10:13:13.000+05:30 | D13: 46130.483 | E13: I0727GE000003535 | F13: CVETBRAA103701214 | G13: delivered | H13: 46136.479 | I13: 46135.738 | N13: INR | O13: 873 | P13: 0 | Q13: 873 | R13: 1899 | S13: 932 | T13: Inter-State | U13: 5 | V13: 41.57 | W13: 0 | X13: 0 | Y13: 4.15715 | Z13: 0 | AA13: 0 | AB13: 0 | AC13: 12.64 | AD13: 110.347 | BZ13: Myntra Designs Pvt Ltd | CA13: 62121000 | CB13: Apparel | CD13: Chelvet | CE13: Women | CF13: Bra | CG13: ON_HAND | CH13: FALSE | CI13: MYEP1115037467 | CJ13: 7a82e088.cb9e.43aa.a102.ffd8667002beqLikx0ZIpk | CK13: 784010 | CL13: AS | CM13: 5 | CN13: 0 | CO13: 0 | CP13: 831.43 | CQ13: 0.5 | CR13: 0 | CS13: 0 | CT13: 0 | CU13: 0 | CW13: 0 | CX13: 07AALCG0172B1Z0 | CZ13: DL | DA13: 0 | DB13: 0 | DC13: 0 | DD13: 29AAECM9636P1ZJ | DE13: 27477 | EB13: PPMP | EL13: ON_HAND | EM13: 967 | EP13: 100047464456 | EQ13: 4998aa5a-bb7a-4bff-b72a-863a551aa12e | ES13: 11102193429
A14: 100059070276 | B14: 1.3289845e+20 | C14: 2026-04-25T14:05:21.000+05:30 | D14: 46137.765 | E14: I0927GE000000208 | F14: CVETNIDR118984921 | G14: delivered | H14: 46142.479 | I14: 46141.747 | N14: INR | O14: 1420 | P14: 1420 | Q14: 0 | R14: 4299 | S14: 2708 | T14: Intra-State | U14: 5 | V14: 0 | W14: 33.81 | X14: 33.81 | Y14: 0 | Z14: 3.38095 | AA14: 3.38095 | AB14: 0 | AC14: 11.82 | AD14: 167.844 | BZ14: Myntra Designs Pvt Ltd | CA14: 62082200 | CB14: Apparel | CD14: Chelvet | CE14: Women | CF14: Nightdress | CG14: ON_HAND | CH14: FALSE | CI14: MYSC1288017560 | CJ14: 1a9a081e.274c.492e.8e1e.2800df03eadaCp7oFDD0FV | CK14: 226001 | CL14: UP | CM14: 0 | CN14: 2.5 | CO14: 2.5 | CP14: 1352.38 | CQ14: 0 | CR14: 0.25 | CS14: 0.25 | CT14: 0 | CU14: 0 | CW14: 250 | CX14: 09AALCG0172B1ZW | CZ14: UP | DA14: 250 | DB14: 0 | DC14: 0 | DD14: 29AAECM9636P1ZJ | DE14: 27477 | EB14: PPMP | EL14: ON_HAND | EM14: 1591 | EP14: 100059070276 | EQ14: 61218dce-0a9c-4be8-b399-9f78e7909378 | ES14: 11113799369
A15: 100032479293 | B15: 1.3276849e+20 | C15: 2026-04-10T13:05:20.000+05:30 | D15: 46123.44 | E15: I0727GE000002324 | F15: CVETBRAA104595883 | G15: reverse_in_transit | H15: 46127.479 | L15: release_rto_refund | N15: INR | O15: 625 | P15: 625 | Q15: 0 | R15: 1499 | S15: 780 | T15: Inter-State | U15: 5 | V15: 29.76 | W15: 0 | X15: 0 | Y15: 2.9762 | Z15: 0 | AA15: 0 | AB15: 0 | AC15: 12.05 | AD15: 75.312 | BZ15: Myntra Designs Pvt Ltd | CA15: 62121000 | CB15: Apparel | CD15: Chelvet | CE15: Women | CF15: Bra | CG15: ON_HAND | CH15: FALSE | CI15: MYSC1282778426 | CJ15: 3942a201.875a.47ab.a621.81b709310f8eYOMlj6Ssga | CK15: 421204 | CL15: MH | CM15: 5 | CN15: 0 | CO15: 0 | CP15: 595.24 | CQ15: 0.5 | CR15: 0 | CS15: 0 | CT15: 0 | CU15: 0 | CW15: 0 | CX15: 07AALCG0172B1Z0 | CZ15: DL | DA15: 0 | DB15: 0 | DC15: 0 | DD15: 29AAECM9636P1ZJ | DE15: 27477 | EB15: PPMP | EL15: ON_HAND | EM15: 719 | EP15: 100032479293 | EQ15: 994550ad-22da-4084-b8f5-30386cfb1c8b | ES15: 11087208240
A16: 100054405440 | B16: 1.3287241e+20 | C16: 2026-04-22T13:44:45.000+05:30 | D16: 46135.449 | E16: I0727GE000004277 | F16: CVETBRAA104595888 | G16: reverse_in_transit | H16: 46136.75 | I16: 46136.78 | J16: 46138.807 | L16: return_refund | N16: INR | O16: 687 | P16: 687 | Q16: 0 | R16: 1499 | S16: 718 | T16: Inter-State | U16: 5 | V16: 32.71 | W16: 0 | X16: 0 | Y16: 3.27145 | Z16: 0 | AA16: 0 | AB16: 0 | AC16: 20.06 | AD16: 137.812 | BZ16: Myntra Designs Pvt Ltd | CA16: 62121000 | CB16: Apparel | CD16: Chelvet | CE16: Women | CF16: Bra | CG16: ON_HAND | CH16: FALSE | CI16: MYSC1287190087 | CJ16: b91b6040.d1bc.4249.821a.d5d934c52f8fcJYm4Apm1t | CK16: 122001 | CL16: HR | CM16: 5 | CN16: 0 | CO16: 0 | CP16: 654.29 | CQ16: 0.5 | CR16: 0 | CS16: 0 | CT16: 0 | CU16: 0 | CW16: 0 | CX16: 07AALCG0172B1Z0 | CZ16: DL | DA16: 0 | DB16: 0 | DC16: 0 | DD16: 29AAECM9636P1ZJ | DE16: 27477 | EB16: PPMP | EL16: ON_HAND | EM16: 781 | EP16: 100054405440 | EQ16: 4d78eb0b-760e-4038-b3f3-75edd6284c6b | ES16: 11109134474 | ET16: DLS
A17: 100030542238 | B17: 1.3275985e+20 | C17: 2026-04-09T13:06:07.000+05:30 | D17: 46121.731 | E17: I0927GE000000067 | F17: CVETBRAA120951084 | G17: reverse_in_transit | H17: 46126.479 | I17: 46126.683 | J17: 46126.779 | L17: return_refund | N17: INR | O17: 996 | P17: 0 | Q17: 996 | R17: 2540 | S17: 1373 | T17: Inter-State | U17: 5 | V17: 47.43 | W17: 0 | X17: 0 | Y17: 4.74285 | Z17: 0 | AA17: 0 | AB17: 0 | AC17: 14.21 | AD17: 141.532 | BZ17: Myntra Designs Pvt Ltd | CA17: 62121000 | CB17: Apparel | CD17: Chelvet | CE17: Women | CF17: Bra | CG17: ON_HAND | CH17: FALSE | CI17: MYSP1386074439 | CJ17: 78480c2c.0898.488c.98c0.e54e0d351cd64jRCKMhQkA | CK17: 560034 | CL17: KA | CM17: 5 | CN17: 0 | CO17: 0 | CP17: 948.57 | CQ17: 0.5 | CR17: 0 | CS17: 0 | CT17: 0 | CU17: 0 | CW17: 0 | CX17: 09AALCG0172B1ZW | CZ17: UP | DA17: 0 | DB17: 0 | DC17: 0 | DD17: 29AAECM9636P1ZJ | DE17: 27477 | EB17: PPMP | EL17: ON_HAND | EM17: 1167 | EP17: 1000008739819 | EQ17: 1ed20db0-ef6c-458a-b066-43bc3b3a5ade | ES17: 11085271182 | ET17: DLS
A18: 100066952585 | B18: 1.3294111e+20 | C18: 2026-04-30T12:35:06.000+05:30 | D18: 46142.533 | E18: I0727GE000005294 | F18: CVETBRAA103716925 | G18: delivered | H18: 46145.75 | I18: 46145.788 | N18: INR | O18: 883 | P18: 0 | Q18: 883 | R18: 1849 | S18: 872 | T18: Inter-State | U18: 5 | V18: 42.05 | W18: 0 | X18: 0 | Y18: 4.20475 | Z18: 0 | AA18: 0 | AB18: 0 | AC18: 13.35 | AD18: 117.88 | BZ18: Myntra Designs Pvt Ltd | CA18: 62121000 | CB18: Apparel | CD18: Chelvet | CE18: Women | CF18: Bra | CG18: ON_HAND | CH18: FALSE | CI18: MYSP1395621464 | CJ18: f954e58c.bb7a.43ab.9529.9a893b519df0AAMYFykzB2 | CK18: 500084 | CL18: TG | CM18: 5 | CN18: 0 | CO18: 0 | CP18: 840.95 | CQ18: 0.5 | CR18: 0 | CS18: 0 | CT18: 0 | CU18: 0 | CW18: 0 | CX18: 07AALCG0172B1Z0 | CZ18: DL | DA18: 0 | DB18: 0 | DC18: 0 | DD18: 29AAECM9636P1ZJ | DE18: 27477 | EB18: PPMP | EL18: ON_HAND | EM18: 977 | EP18: 1000019452711 | EQ18: 52e6effb-64ee-4480-a537-0ccad9c9d43d | ES18: 11121681773
A19: 100015723665 | B19: 1.3269461e+20 | C19: 2026-04-01T23:51:42.000+05:30 | D19: 46114.454 | E19: I0727GE000000349 | F19: CVETBRAA103723126 | G19: reverse_in_transit | H19: 46119.479 | L19: release_rto_refund | N19: INR | O19: 525 | P19: 0 | Q19: 525 | R19: 1999 | S19: 1380 | T19: Inter-State | U19: 5 | V19: 25 | W19: 0 | X19: 0 | Y19: 2.5 | Z19: 0 | AA19: 0 | AB19: 0 | AC19: 8.65 | AD19: 45.413 | BZ19: Myntra Designs Pvt Ltd | CA19: 62121000 | CB19: Apparel | CD19: Chelvet | CE19: Women | CF19: Bra | CG19: ON_HAND | CH19: FALSE | CI19: MYSP1382061742 | CJ19: 17aedc98.9888.42a4.a228.41e802aa7ac7BPCULLt03A | CK19: 751003 | CL19: OR | CM19: 5 | CN19: 0 | CO19: 0 | CP19: 500 | CQ19: 0.5 | CR19: 0 | CS19: 0 | CT19: 0 | CU19: 0 | CW19: 0 | CX19: 07AALCG0172B1Z0 | CZ19: DL | DA19: 0 | DB19: 0 | DC19: 0 | DD19: 29AAECM9636P1ZJ | DE19: 27477 | EB19: PPMP | EL19: ON_HAND | EM19: 619 | EP19: 100015723665 | EQ19: ec69582c-4b02-4079-838a-fb184c60a8c5 | ES19: 11070452493
A20: 100067391774 | B20: 1.3294307e+20 | C20: 2026-04-30T18:02:11.000+05:30 | D20: 46143.475 | E20: I0927GE000000261 | F20: CVETBRAA127713123 | G20: delivered | H20: 46147.479 | I20: 46146.733 | N20: INR | O20: 941 | P20: 0 | Q20: 941 | R20: 2099 | S20: 987 | T20: Inter-State | U20: 5 | V20: 44.81 | W20: 0 | X20: 0 | Y20: 4.48095 | Z20: 0 | AA20: 0 | AB20: 0 | AC20: 15.63 | AD20: 147.078 | BZ20: Myntra Designs Pvt Ltd | CA20: 62121000 | CB20: Apparel | CD20: Chelvet | CE20: Women | CF20: Bra | CG20: ON_HAND | CH20: FALSE | CI20: MYSP1395951530 | CJ20: 341dac55.52b9.4a4f.aa95.bb9aee5f29fdcacND8bemn | CK20: 313001 | CL20: RJ | CM20: 5 | CN20: 0 | CO20: 0 | CP20: 896.19 | CQ20: 0.5 | CR20: 0 | CS20: 0 | CT20: 0 | CU20: 0 | CW20: 0 | CX20: 09AALCG0172B1ZW | CZ20: UP | DA20: 0 | DB20: 0 | DC20: 0 | DD20: 29AAECM9636P1ZJ | DE20: 27477 | EB20: PPMP | EL20: ON_HAND | EM20: 1112 | EP20: 100067391774 | EQ20: 8d75e203-54ce-4856-be13-2742c07e52f3 | ES20: 11122120964
A21: 100053547722 | B21: 1.328667e+20 | C21: 2026-04-21T21:53:06.000+05:30 | D21: 46134.43 | E21: I0927GE000000174 | F21: CVETBRAA127713160 | G21: delivered | H21: 46135.75 | I21: 46136.006 | N21: INR | O21: 1148 | P21: 0 | Q21: 1148 | R21: 2999 | S21: 1680 | T21: Inter-State | U21: 5 | V21: 54.67 | W21: 0 | X21: 0 | Y21: 5.46665 | Z21: 0 | AA21: 0 | AB21: 0 | AC21: 23.6 | AD21: 270.928 | BZ21: Myntra Designs Pvt Ltd | CA21: 62121000 | CB21: Apparel | CD21: Chelvet | CE21: Women | CF21: Bra | CG21: ON_HAND | CH21: FALSE | CI21: MYSP1392070016 | CJ21: f89fba87.205e.4aed.949c.92f3fabe8ba9YZAmdB4TgL | CK21: 122003 | CL21: HR | CM21: 5 | CN21: 0 | CO21: 0 | CP21: 1093.33 | CQ21: 0.5 | CR21: 0 | CS21: 0 | CT21: 0 | CU21: 0 | CW21: 0 | CX21: 09AALCG0172B1ZW | CZ21: UP | DA21: 0 | DB21: 0 | DC21: 0 | DD21: 29AAECM9636P1ZJ | DE21: 27477 | EB21: PPMP | EL21: ON_HAND | EM21: 1319 | EP21: 100053547722 | EQ21: fe5468f5-d346-4c51-be40-eea156d65cad | ES21: 11108276749
A22: 100061903517 | B22: 1.3291128e+20 | C22: 2026-04-27T01:44:01.000+05:30 | D22: 46139.389 | E22: I0927GE000000209 | F22: CVETBRAA127431550 | G22: delivered | H22: 46140.75 | I22: 46140.941 | N22: INR | O22: 1569 | P22: 0 | Q22: 1569 | R22: 2599 | S22: 859 | T22: Inter-State | U22: 5 | V22: 74.71 | W22: 0 | X22: 0 | Y22: 7.47145 | Z22: 0 | AA22: 0 | AB22: 0 | AC22: 18.65 | AD22: 292.619 | BZ22: Myntra Designs Pvt Ltd | CA22: 62121000 | CB22: Apparel | CD22: Chelvet | CE22: Women | CF22: Bra | CG22: ON_HAND | CH22: FALSE | CI22: MYSP1394148095 | CJ22: dcced7ad.d01f.47d9.800f.c131b639cea1tTdzmUrMYM | CK22: 122012 | CL22: HR | CM22: 5 | CN22: 0 | CO22: 0 | CP22: 1494.29 | CQ22: 0.5 | CR22: 0 | CS22: 0 | CT22: 0 | CU22: 0 | CW22: 0 | CX22: 09AALCG0172B1ZW | CZ22: UP | DA22: 0 | DB22: 0 | DC22: 0 | DD22: 29AAECM9636P1ZJ | DE22: 27477 | EB22: PPMP | EL22: ON_HAND | EM22: 1740 | EP22: 100061903517 | EQ22: 5fe91dc5-b1ac-4d07-a3f3-08f715639609 | ES22: 11116632642
A23: 100021728663 | B23: 1.327205e+20 | C23: 2026-04-04T23:47:21.000+05:30 | D23: 46118.538 | E23: I0727GE000001135 | F23: CVETBRAA103722941 | G23: reverse_in_transit | H23: 46122.354 | I23: 46122.935 | J23: 46122.948 | L23: return_refund | N23: INR | O23: 525 | P23: 0 | Q23: 525 | R23: 1999 | S23: 1380 | T23: Inter-State | U23: 5 | V23: 25 | W23: 0 | X23: 0 | Y23: 2.5 | Z23: 0 | AA23: 0 | AB23: 0 | AC23: 8.65 | AD23: 45.413 | BZ23: Myntra Designs Pvt Ltd | CA23: 62121000 | CB23: Apparel | CD23: Chelvet | CE23: Women | CF23: Bra | CG23: ON_HAND | CH23: FALSE | CI23: MYSP1384302819 | CJ23: 0d4d3141.309e.4166.8216.981894de63c8p3suqcj0md | CK23: 462003 | CL23: MP | CM23: 5 | CN23: 0 | CO23: 0 | CP23: 500 | CQ23: 0.5 | CR23: 0 | CS23: 0 | CT23: 0 | CU23: 0 | CW23: 0 | CX23: 07AALCG0172B1Z0 | CZ23: DL | DA23: 0 | DB23: 0 | DC23: 0 | DD23: 29AAECM9636P1ZJ | DE23: 27477 | EB23: PPMP | EL23: ON_HAND | EM23: 619 | EP23: 1000006776020 | EQ23: df48687a-98ff-4747-a9d9-557be22bdd3e | ES23: 11076457532 | ET23: DLS
A24: 100058104184 | B24: 1.3289264e+20 | C24: 2026-04-24T21:56:35.000+05:30 | D24: 46137.444 | E24: I0727GE000004560 | F24: CVETBRAA103725193 | G24: reverse_in_transit | H24: 46139.479 | L24: release_rto_refund | N24: INR | O24: 811 | P24: 811 | Q24: 0 | R24: 1849 | S24: 944 | T24: Inter-State | U24: 5 | V24: 38.62 | W24: 0 | X24: 0 | Y24: 3.8619 | Z24: 0 | AA24: 0 | AB24: 0 | AC24: 12.86 | AD24: 104.295 | BZ24: Myntra Designs Pvt Ltd | CA24: 62121000 | CB24: Apparel | CD24: Chelvet | CE24: Women | CF24: Bra | CG24: ON_HAND | CH24: FALSE | CI24: MYSC1287850303 | CJ24: 67b7e943.4061.499b.9e26.86ec6ef484d0rYKRCUhkTQ | CK24: 302029 | CL24: RJ | CM24: 5 | CN24: 0 | CO24: 0 | CP24: 772.38 | CQ24: 0.5 | CR24: 0 | CS24: 0 | CT24: 0 | CU24: 0 | CW24: 0 | CX24: 07AALCG0172B1Z0 | CZ24: DL | DA24: 0 | DB24: 0 | DC24: 0 | DD24: 29AAECM9636P1ZJ | DE24: 27477 | EB24: PPMP | EL24: ON_HAND | EM24: 905 | EP24: 100058104184 | EQ24: 688d20a6-f520-4861-a4d7-0465dbeec7b8 | ES24: 11112833259
A25: 100042056510 | B25: 1.3281048e+20 | C25: 2026-04-15T09:43:54.000+05:30 | D25: 46127.529 | E25: I0727GE000003068 | F25: CVETBRAA104553130 | G25: delivered | H25: 46131.479 | I25: 46130.766 | N25: INR | O25: 805 | P25: 0 | Q25: 805 | R25: 1699 | S25: 800 | T25: Inter-State | U25: 5 | V25: 38.33 | W25: 0 | X25: 0 | Y25: 3.83335 | Z25: 0 | AA25: 0 | AB25: 0 | AC25: 15.87 | AD25: 127.754 | BZ25: Myntra Designs Pvt Ltd | CA25: 62121000 | CB25: Apparel | CD25: Chelvet | CE25: Women | CF25: Bra | CG25: ON_HAND | CH25: FALSE | CI25: MYSP1389030055 | CJ25: c99fdb42.d4aa.4fbd.9d7b.8ab1e83cb44dDAEis3hyml | CK25: 500091 | CL25: TG | CM25: 5 | CN25: 0 | CO25: 0 | CP25: 766.67 | CQ25: 0.5 | CR25: 0 | CS25: 0 | CT25: 0 | CU25: 0 | CW25: 0 | CX25: 07AALCG0172B1Z0 | CZ25: DL | DA25: 0 | DB25: 0 | DC25: 0 | DD25: 29AAECM9636P1ZJ | DE25: 27477 | EB25: PPMP | EL25: ON_HAND | EM25: 899 | EP25: 100042056510 | EQ25: 1b996cee-3d97-4521-9a0f-26e67ec6eeae | ES25: 11096785469
A26: 100038129961 | B26: 1.3279282e+20 | C26: 2026-04-13T08:40:34.000+05:30 | D26: 46126.45 | E26: I0727GE000002681 | F26: CVETBRAA103725191 | G26: reverse_in_transit | H26: 46131.479 | L26: release_rto_refund | N26: INR | O26: 811 | P26: 811 | Q26: 0 | R26: 1849 | S26: 944 | T26: Inter-State | U26: 5 | V26: 38.62 | W26: 0 | X26: 0 | Y26: 3.8619 | Z26: 0 | AA26: 0 | AB26: 0 | AC26: 12.86 | AD26: 104.295 | BZ26: Myntra Designs Pvt Ltd | CA26: 62121000 | CB26: Apparel | CD26: Chelvet | CE26: Women | CF26: Bra | CG26: ON_HAND | CH26: FALSE | CI26: MYSC1283973783 | CJ26: fdbc832b.93a4.4a71.a82f.e8369e50df8a4kIUC5uxoU | CK26: 403801 | CL26: GA | CM26: 5 | CN26: 0 | CO26: 0 | CP26: 772.38 | CQ26: 0.5 | CR26: 0 | CS26: 0 | CT26: 0 | CU26: 0 | CW26: 0 | CX26: 07AALCG0172B1Z0 | CZ26: DL | DA26: 0 | DB26: 0 | DC26: 0 | DD26: 29AAECM9636P1ZJ | DE26: 27477 | EB26: PPMP | EL26: ON_HAND | EM26: 905 | EP26: 100038129961 | EQ26: 48bc7c94-fd84-4721-8df2-0dcd3ef04c74 | ES26: 11092858916
A27: 100044964317 | B27: 1.3282341e+20 | C27: 2026-04-16T21:38:36.000+05:30 | D27: 46129.442 | E27: I0727GE000003264 | F27: CVETBRAA103682593 | G27: delivered | H27: 46134.479 | I27: 46134.937 | N27: INR | O27: 535 | P27: 0 | Q27: 535 | R27: 1499 | S27: 870 | T27: Inter-State | U27: 5 | V27: 25.48 | W27: 0 | X27: 0 | Y27: 2.5476 | Z27: 0 | AA27: 0 | AB27: 0 | AC27: 11.88 | AD27: 63.558 | BZ27: Myntra Designs Pvt Ltd | CA27: 62121000 | CB27: Apparel | CD27: Chelvet | CE27: Women | CF27: Bra | CG27: ON_HAND | CH27: FALSE | CI27: MYSP1389833799 | CJ27: d871f709.3e59.47ad.8a71.4332f22fb025QM5HXHO7aS | CK27: 600107 | CL27: TN | CM27: 5 | CN27: 0 | CO27: 0 | CP27: 509.52 | CQ27: 0.5 | CR27: 0 | CS27: 0 | CT27: 0 | CU27: 0 | CW27: 0 | CX27: 07AALCG0172B1Z0 | CZ27: DL | DA27: 0 | DB27: 0 | DC27: 0 | DD27: 29AAECM9636P1ZJ | DE27: 27477 | EB27: PPMP | EL27: ON_HAND | EM27: 629 | EP27: 1000013168360 | EQ27: 3fd091bd-5a6b-4723-8874-d86861b5b06e | ES27: 11099693284
A28: 100063367502 | B28: 1.3291937e+20 | C28: 2026-04-28T00:12:25.000+05:30 | D28: 46140.446 | E28: I0727GE000004966 | F28: CVETBRAA103718506 | G28: reverse_in_transit | H28: 46146.479 | I28: 46143.748 | J28: 46144.096 | L28: return_refund | N28: INR | O28: 622 | P28: 0 | Q28: 622 | R28: 1749 | S28: 1033 | T28: Inter-State | U28: 5 | V28: 29.62 | W28: 0 | X28: 0 | Y28: 2.9619 | Z28: 0 | AA28: 0 | AB28: 0 | AC28: 11.79 | AD28: 73.334 | BZ28: Myntra Designs Pvt Ltd | CA28: 62121000 | CB28: Apparel | CD28: Chelvet | CE28: Women | CF28: Bra | CG28: ON_HAND | CH28: FALSE | CI28: MYSP1394732053 | CJ28: d7dd2d09.e212.4f5f.b2af.e503ab98a2a0DOvxxGFJTu | CK28: 834003 | CL28: JH | CM28: 5 | CN28: 0 | CO28: 0 | CP28: 592.38 | CQ28: 0.5 | CR28: 0 | CS28: 0 | CT28: 0 | CU28: 0 | CW28: 0 | CX28: 07AALCG0172B1Z0 | CZ28: DL | DA28: 0 | DB28: 0 | DC28: 0 | DD28: 29AAECM9636P1ZJ | DE28: 27477 | EB28: PPMP | EL28: ON_HAND | EM28: 716 | EP28: 100063367502 | EQ28: 026bb454-84a3-44ea-87c6-1bd271071841 | ES28: 11118096639 | ET28: DLS
A29: 100033688388 | B29: 1.3277266e+20 | C29: 2026-04-11T00:39:45.000+05:30 | D29: 46123.43 | E29: I0727GE000002233 | F29: CVETBRAA103643236 | G29: delivered | H29: 46127.479 | I29: 46127.663 | N29: INR | O29: 705 | P29: 705 | Q29: 0 | R29: 1499 | S29: 700 | T29: Inter-State | U29: 5 | V29: 33.57 | W29: 0 | X29: 0 | Y29: 3.35715 | Z29: 0 | AA29: 0 | AB29: 0 | AC29: 20.06 | AD29: 141.423 | BZ29: Myntra Designs Pvt Ltd | CA29: 62121000 | CB29: Apparel | CD29: Chelvet | CE29: Women | CF29: Bra | CG29: ON_HAND | CH29: FALSE | CI29: MYEC1097738398 | CJ29: 361a87c7.212e.4801.8212.64f0dce02e29JaPCXDXjYC | CK29: 802314 | CL29: BR | CM29: 5 | CN29: 0 | CO29: 0 | CP29: 671.43 | CQ29: 0.5 | CR29: 0 | CS29: 0 | CT29: 0 | CU29: 0 | CW29: 0 | CX29: 07AALCG0172B1Z0 | CZ29: DL | DA29: 0 | DB29: 0 | DC29: 0 | DD29: 29AAECM9636P1ZJ | DE29: 27477 | EB29: PPMP | EL29: ON_HAND | EM29: 799 | EP29: 100033688388 | EQ29: 7095b17a-18f9-44b6-9ebf-4f5e8d2168f2 | ES29: 11088417334
A30: 100035584449 | B30: 1.3278106e+20 | C30: 2026-04-12T00:00:03.000+05:30 | D30: 46125.481 | E30: I0727GE000002613 | F30: CVETBRAA103722958 | G30: delivered | H30: 46134.479 | I30: 46133.729 | N30: INR | O30: 525 | P30: 0 | Q30: 525 | R30: 1999 | S30: 1380 | T30: Inter-State | U30: 5 | V30: 25 | W30: 0 | X30: 0 | Y30: 2.5 | Z30: 0 | AA30: 0 | AB30: 0 | AC30: 8.65 | AD30: 45.413 | BZ30: Myntra Designs Pvt Ltd | CA30: 62121000 | CB30: Apparel | CD30: Chelvet | CE30: Women | CF30: Bra | CG30: ON_HAND | CH30: FALSE | CI30: MYSP1388004043 | CJ30: bbe7a67e.86cc.4324.a36e.5d68d40fe046hGohIZ05Z5 | CK30: 799001 | CL30: TR | CM30: 5 | CN30: 0 | CO30: 0 | CP30: 500 | CQ30: 0.5 | CR30: 0 | CS30: 0 | CT30: 0 | CU30: 0 | CW30: 0 | CX30: 07AALCG0172B1Z0 | CZ30: DL | DA30: 0 | DB30: 0 | DC30: 0 | DD30: 29AAECM9636P1ZJ | DE30: 27477 | EB30: PPMP | EL30: ON_HAND | EM30: 619 | EP30: 1000010958925 | EQ30: 895e60ed-5043-4759-9992-02f221beae22 | ES30: 11090313398
A31: 100021518157 | B31: 1.327199e+20 | C31: 2026-04-04T22:07:03.000+05:30 | D31: 46118.45 | E31: I0927GE000000035 | F31: CVETBRAA127703238 | G31: reverse_in_transit | H31: 46119.75 | L31: release_rto_refund | N31: INR | O31: 656 | P31: 0 | Q31: 656 | R31: 1499 | S31: 749 | T31: Intra-State | U31: 5 | V31: 0 | W31: 15.62 | X31: 15.62 | Y31: 0 | Z31: 1.5619 | AA31: 1.5619 | AB31: 0 | AC31: 15.53 | AD31: 101.877 | BZ31: Myntra Designs Pvt Ltd | CA31: 62121000 | CB31: Apparel | CD31: Chelvet | CE31: Women | CF31: Bra | CG31: ON_HAND | CH31: FALSE | CI31: MYSP1384181935 | CJ31: ed62139b.83b4.42d6.b11b.cbcdd596ba2dFwdhPY9hRW | CK31: 201310 | CL31: UP | CM31: 0 | CN31: 2.5 | CO31: 2.5 | CP31: 624.76 | CQ31: 0 | CR31: 0.25 | CS31: 0.25 | CT31: 0 | CU31: 0 | CW31: 0 | CX31: 09AALCG0172B1ZW | CZ31: UP | DA31: 0 | DB31: 0 | DC31: 0 | DD31: 29AAECM9636P1ZJ | DE31: 27477 | EB31: PPMP | EL31: ON_HAND | EM31: 750 | EP31: 100021518157 | EQ31: 86787407-c0c2-4eaf-aed3-e9a867793b01 | ES31: 11076247025
A32: 100028968346 | B32: 1.3275264e+20 | C32: 2026-04-08T17:03:01.000+05:30 | D32: 46121.445 | E32: I0927GE000000060 | F32: CVETLNGR130699387 | G32: delivered | H32: 46124.479 | I32: 46124.649 | N32: INR | O32: 1364 | P32: 0 | Q32: 1364 | R32: 2999 | S32: 1441 | T32: Inter-State | U32: 5 | V32: 64.95 | W32: 0 | X32: 0 | Y32: 6.49525 | Z32: 0 | AA32: 0 | AB32: 0 | AC32: 10.36 | AD32: 141.31 | BZ32: Myntra Designs Pvt Ltd | CA32: 62121000 | CB32: Apparel | CD32: Chelvet | CE32: Women | CF32: Lingerie Set | CG32: ON_HAND | CH32: FALSE | CI32: MYSP1385829786 | CJ32: f76937a6.26a7.40af.b3c1.5f9b25b59b20morAXsfSLn | CK32: 134203 | CL32: HR | CM32: 5 | CN32: 0 | CO32: 0 | CP32: 1299.05 | CQ32: 0.5 | CR32: 0 | CS32: 0 | CT32: 0 | CU32: 0 | CW32: 0 | CX32: 09AALCG0172B1ZW | CZ32: UP | DA32: 0 | DB32: 0 | DC32: 0 | DD32: 29AAECM9636P1ZJ | DE32: 27477 | EB32: PPMP | EL32: ON_HAND | EM32: 1558 | EP32: 100028968346 | EQ32: 0568584c-ee53-4346-b29c-b7dafaeaa7fa | ES32: 11083697286
A33: 100058632117 | B33: 1.3289677e+20 | C33: 2026-04-25T09:25:48.000+05:30 | D33: 46137.422 | E33: I0927GE000000201 | F33: CVETBRAA127713157 | G33: delivered | H33: 46143.479 | I33: 46142.956 | N33: INR | O33: 998 | P33: 998 | Q33: 0 | R33: 2999 | S33: 1830 | T33: Inter-State | U33: 5 | V33: 47.52 | W33: 0 | X33: 0 | Y33: 4.7524 | Z33: 0 | AA33: 0 | AB33: 0 | AC33: 14.2 | AD33: 141.716 | BZ33: Myntra Designs Pvt Ltd | CA33: 62121000 | CB33: Apparel | CD33: Chelvet | CE33: Women | CF33: Bra | CG33: ON_HAND | CH33: FALSE | CI33: MYSC1287827431 | CJ33: 74a32b02.0f3e.4185.aec1.7dec75f8716bGuFpmLoDCS | CK33: 600089 | CL33: TN | CM33: 5 | CN33: 0 | CO33: 0 | CP33: 950.48 | CQ33: 0.5 | CR33: 0 | CS33: 0 | CT33: 0 | CU33: 0 | CW33: 0 | CX33: 09AALCG0172B1ZW | CZ33: UP | DA33: 0 | DB33: 0 | DC33: 0 | DD33: 29AAECM9636P1ZJ | DE33: 27477 | EB33: PPMP | EL33: ON_HAND | EM33: 1169 | EP33: 100058632117 | EQ33: 2dbcc55e-b486-434f-b94a-d4f47f0745cc | ES33: 11113361192
A34: 100058443833 | B34: 1.3289411e+20 | C34: 2026-04-25T02:02:45.000+05:30 | D34: 46137.443 | E34: I0727GE000004554 | F34: CVETBRAA103716994 | G34: reverse_in_transit | H34: 46139.479 | I34: 46138.882 | J34: 46139.216 | L34: return_refund | N34: INR | O34: 883 | P34: 0 | Q34: 883 | R34: 1849 | S34: 872 | T34: Inter-State | U34: 5 | V34: 42.05 | W34: 0 | X34: 0 | Y34: 4.20475 | Z34: 0 | AA34: 0 | AB34: 0 | AC34: 13.35 | AD34: 117.88 | BZ34: Myntra Designs Pvt Ltd | CA34: 62121000 | CB34: Apparel | CD34: Chelvet | CE34: Women | CF34: Bra | CG34: ON_HAND | CH34: FALSE | CI34: MYSP1393344849 | CJ34: fa227767.3697.4750.b8be.ca8d6d265e81PU0V2I5uuW | CK34: 122101 | CL34: HR | CM34: 5 | CN34: 0 | CO34: 0 | CP34: 840.95 | CQ34: 0.5 | CR34: 0 | CS34: 0 | CT34: 0 | CU34: 0 | CW34: 0 | CX34: 07AALCG0172B1Z0 | CZ34: DL | DA34: 0 | DB34: 0 | DC34: 0 | DD34: 29AAECM9636P1ZJ | DE34: 27477 | EB34: PPMP | EL34: ON_HAND | EM34: 977 | EP34: 100058443833 | EQ34: eb4f5a81-67d5-4f11-952d-9a02c0af0806 | ES34: 11113172908 | ET34: DLS
A35: 100015078168 | B35: 1.3269281e+20 | C35: 2026-04-01T18:51:49.000+05:30 | D35: 46114.473 | E35: I0727GE000000377 | F35: CVETBRAA103646614 | G35: delivered | H35: 46118.479 | I35: 46118.916 | N35: INR | O35: 625 | P35: 0 | Q35: 625 | R35: 1499 | S35: 780 | T35: Inter-State | U35: 5 | V35: 29.76 | W35: 0 | X35: 0 | Y35: 2.9762 | Z35: 0 | AA35: 0 | AB35: 0 | AC35: 12.05 | AD35: 75.312 | BZ35: Myntra Designs Pvt Ltd | CA35: 62121000 | CB35: Apparel | CD35: Chelvet | CE35: Women | CF35: Bra | CG35: ON_HAND | CH35: FALSE | CI35: MYSP1382086003 | CJ35: 9eda9948.aa24.4fa0.894a.f6663b88bd78zKiEWGxQku | CK35: 411048 | CL35: MH | CM35: 5 | CN35: 0 | CO35: 0 | CP35: 595.24 | CQ35: 0.5 | CR35: 0 | CS35: 0 | CT35: 0 | CU35: 0 | CW35: 0 | CX35: 07AALCG0172B1Z0 | CZ35: DL | DA35: 0 | DB35: 0 | DC35: 0 | DD35: 29AAECM9636P1ZJ | DE35: 27477 | EB35: PPMP | EL35: ON_HAND | EM35: 719 | EP35: 1000004181184 | EQ35: 98e69967-42f5-4604-81a2-2e24f271e0bd | ES35: 11069806995
A36: 100050550221 | B36: 1.3284945e+20 | C36: 2026-04-19T21:59:37.000+05:30 | D36: 46132.497 | E36: I0727GE000003772 | F36: CVETBRAA103722906 | G36: delivered | H36: 46140.479 | I36: 46139.703 | N36: INR | O36: 599 | P36: 564.46026 | Q36: 34.53974 | R36: 1999 | S36: 1306 | T36: Inter-State | U36: 5 | V36: 28.52 | W36: 0 | X36: 0 | Y36: 2.8524 | Z36: 0 | AA36: 0 | AB36: 0 | AC36: 20.06 | AD36: 120.16 | BZ36: Myntra Designs Pvt Ltd | CA36: 62121000 | CB36: Apparel | CD36: Chelvet | CE36: Women | CF36: Bra | CG36: ON_HAND | CH36: FALSE | CI36: MYSC1286253439 | CJ36: 2b8b225e.e5f4.4ea4.9089.a9bf0f666165ScCGH94iLx | CK36: 571201 | CL36: KA | CM36: 5 | CN36: 0 | CO36: 0 | CP36: 570.48 | CQ36: 0.5 | CR36: 0 | CS36: 0 | CT36: 0 | CU36: 0 | CW36: 0 | CX36: 07AALCG0172B1Z0 | CZ36: DL | DA36: 0 | DB36: 0 | DC36: 0 | DD36: 29AAECM9636P1ZJ | DE36: 27477 | EB36: PPMP | EL36: ON_HAND | EM36: 693 | EP36: 100050550221 | EQ36: c67f8f3a-ce66-463c-978b-58dbcc7ce844 | ES36: 11105279236
A37: 100058612864 | B37: 1.3289667e+20 | C37: 2026-04-25T09:08:11.000+05:30 | D37: 46137.423 | E37: I0927GE000000202 | F37: CVETBREF130041945 | G37: reverse_in_transit | H37: 46141.479 | L37: release_rto_refund | N37: INR | O37: 390 | P37: 390 | Q37: 0 | R37: 899 | S37: 450 | T37: Inter-State | U37: 5 | V37: 18.57 | W37: 0 | X37: 0 | Y37: 1.85715 | Z37: 0 | AA37: 0 | AB37: 0 | AC37: 0.27 | AD37: 1.053 | BZ37: Myntra Designs Pvt Ltd | CA37: 61082210 | CB37: Apparel | CD37: Chelvet | CE37: Women | CF37: Briefs | CG37: ON_HAND | CH37: FALSE | CI37: MYSC1287827969 | CJ37: 58bf7db3.76bd.4c05.a9d9.0210b9549cb4iB6EVy69k4 | CK37: 333028 | CL37: RJ | CM37: 5 | CN37: 0 | CO37: 0 | CP37: 371.43 | CQ37: 0.5 | CR37: 0 | CS37: 0 | CT37: 0 | CU37: 0 | CW37: 0 | CX37: 09AALCG0172B1ZW | CZ37: UP | DA37: 0 | DB37: 0 | DC37: 0 | DD37: 29AAECM9636P1ZJ | DE37: 27477 | EB37: PPMP | EL37: ON_HAND | EM37: 449 | EP37: 100058612864 | EQ37: a5ed27fb-c8a5-440e-980a-5b989ce96b8a | ES37: 11113341939
A38: 100050907453 | B38: 1.3285055e+20 | C38: 2026-04-20T01:02:44.000+05:30 | D38: 46133.498 | E38: I0727GE000004014 | F38: CVETBRAA103656279 | G38: delivered | H38: 46136.479 | I38: 46136.902 | N38: INR | O38: 956 | P38: 0 | Q38: 956 | R38: 2099 | S38: 972 | T38: Inter-State | U38: 5 | V38: 45.52 | W38: 0 | X38: 0 | Y38: 4.5524 | Z38: 0 | AA38: 0 | AB38: 0 | AC38: 20.06 | AD38: 191.774 | BZ38: Myntra Designs Pvt Ltd | CA38: 62121000 | CB38: Apparel | CD38: Chelvet | CE38: Women | CF38: Bra | CG38: ON_HAND | CH38: FALSE | CI38: MYSP1391720389 | CJ38: 1094a4e3.f77d.4611.9bee.dfb0c9597be49XvA9rd8oX | CK38: 390007 | CL38: GJ | CM38: 5 | CN38: 0 | CO38: 0 | CP38: 910.48 | CQ38: 0.5 | CR38: 0 | CS38: 0 | CT38: 0 | CU38: 0 | CW38: 0 | CX38: 07AALCG0172B1Z0 | CZ38: DL | DA38: 0 | DB38: 0 | DC38: 0 | DD38: 29AAECM9636P1ZJ | DE38: 27477 | EB38: PPMP | EL38: ON_HAND | EM38: 1127 | EP38: 1000015266268 | EQ38: 88c50d72-3224-4d7e-906f-d99ca6d52d5a | ES38: 11105636468
A39: 100031082422 | B39: 1.3276181e+20 | C39: 2026-04-09T18:32:52.000+05:30 | D39: 46122.434 | E39: I0927GE000000068 | F39: CVETBRAA127431485 | G39: reverse_in_transit | H39: 46126.479 | L39: release_rto_refund | N39: INR | O39: 1361 | P39: 1361 | Q39: 0 | R39: 2599 | S39: 1067 | T39: Inter-State | U39: 5 | V39: 64.81 | W39: 0 | X39: 0 | Y39: 6.48095 | Z39: 0 | AA39: 0 | AB39: 0 | AC39: 19.78 | AD39: 269.206 | BZ39: Myntra Designs Pvt Ltd | CA39: 62121000 | CB39: Apparel | CD39: Chelvet | CE39: Women | CF39: Bra | CG39: ON_HAND | CH39: FALSE | CI39: MYSC1282360776 | CJ39: f6809850.5ef1.4a67.8714.06573c561b1cNz6rbHRY6E | CK39: 560037 | CL39: KA | CM39: 5 | CN39: 0 | CO39: 0 | CP39: 1296.19 | CQ39: 0.5 | CR39: 0 | CS39: 0 | CT39: 0 | CU39: 0 | CW39: 0 | CX39: 09AALCG0172B1ZW | CZ39: UP | DA39: 0 | DB39: 0 | DC39: 0 | DD39: 29AAECM9636P1ZJ | DE39: 27477 | EB39: PPMP | EL39: ON_HAND | EM39: 1532 | EP39: 100031082422 | EQ39: adbbc003-973a-4d77-9d68-a3c5ae62ecf4 | ES39: 11085811368
A40: 100023616330 | B40: 1.3272841e+20 | C40: 2026-04-05T21:44:53.000+05:30 | D40: 46118.556 | E40: I0727GE000001294 | F40: CVETBRAA103722844 | G40: reverse_in_transit | H40: 46122.479 | I40: 46122.675 | J40: 46123.769 | L40: return_refund | N40: INR | O40: 525 | P40: 0 | Q40: 525 | R40: 1999 | S40: 1380 | T40: Inter-State | U40: 5 | V40: 25 | W40: 0 | X40: 0 | Y40: 2.5 | Z40: 0 | AA40: 0 | AB40: 0 | AC40: 8.65 | AD40: 45.413 | BZ40: Myntra Designs Pvt Ltd | CA40: 62121000 | CB40: Apparel | CD40: Chelvet | CE40: Women | CF40: Bra | CG40: ON_HAND | CH40: FALSE | CI40: MYSP1384320891 | CJ40: b7f63722.7ce5.4682.b3c6.07bd4fcc42cbXykJJ6kcTP | CK40: 344001 | CL40: RJ | CM40: 5 | CN40: 0 | CO40: 0 | CP40: 500 | CQ40: 0.5 | CR40: 0 | CS40: 0 | CT40: 0 | CU40: 0 | CW40: 0 | CX40: 07AALCG0172B1Z0 | CZ40: DL | DA40: 0 | DB40: 0 | DC40: 0 | DD40: 29AAECM9636P1ZJ | DE40: 27477 | EB40: PPMP | EL40: ON_HAND | EM40: 619 | EP40: 100023616330 | EQ40: 45e4ddd2-fce8-451f-afc5-8551f4b4fdaf | ES40: 11078345215 | ET40: DLS
A41: 100036274709 | B41: 1.3278555e+20 | C41: 2026-04-12T12:28:10.000+05:30 | D41: 46126.485 | E41: I0727GE000002813 | F41: CVETBRAA103697042 | G41: reverse_in_transit | H41: 46130.479 | I41: 46130.788 | J41: 46143.614 | L41: return_refund | N41: INR | O41: 622 | P41: 0 | Q41: 622 | R41: 1749 | S41: 1033 | T41: Inter-State | U41: 5 | V41: 29.62 | W41: 0 | X41: 0 | Y41: 2.9619 | Z41: 0 | AA41: 0 | AB41: 0 | AC41: 11.79 | AD41: 73.334 | BZ41: Myntra Designs Pvt Ltd | CA41: 62121000 | CB41: Apparel | CD41: Chelvet | CE41: Women | CF41: Bra | CG41: ON_HAND | CH41: FALSE | CI41: MYSP1388509957 | CJ41: 46148c51.acdf.4b83.9043.8552b289eeb4Sa8x0fQk2u | CK41: 411041 | CL41: MH | CM41: 5 | CN41: 0 | CO41: 0 | CP41: 592.38 | CQ41: 0.5 | CR41: 0 | CS41: 0 | CT41: 0 | CU41: 0 | CW41: 0 | CX41: 07AALCG0172B1Z0 | CZ41: DL | DA41: 0 | DB41: 0 | DC41: 0 | DD41: 29AAECM9636P1ZJ | DE41: 27477 | EB41: PPMP | EL41: ON_HAND | EM41: 716 | EP41: 100036274709 | EQ41: ac40f359-b25f-481c-a813-fcaf1c592d5d | ES41: 11091003662 | ET41: DLS
A42: 100062900997 | B42: 1.3291757e+20 | C42: 2026-04-27T19:11:34.000+05:30 | D42: 46140.471 | E42: I0727GE000004985 | F42: CVETBRAA103716986 | G42: delivered | H42: 46144.479 | I42: 46142.973 | N42: INR | O42: 883 | P42: 0 | Q42: 883 | R42: 1849 | S42: 872 | T42: Inter-State | U42: 5 | V42: 42.05 | W42: 0 | X42: 0 | Y42: 4.20475 | Z42: 0 | AA42: 0 | AB42: 0 | AC42: 13.35 | AD42: 117.88 | BZ42: Myntra Designs Pvt Ltd | CA42: 62121000 | CB42: Apparel | CD42: Chelvet | CE42: Women | CF42: Bra | CG42: ON_HAND | CH42: FALSE | CI42: MYSP1394759986 | CJ42: 31ca9fef.5284.40c1.bf33.a64577f6dd21ivN0iLbZq1 | CK42: 382415 | CL42: GJ | CM42: 5 | CN42: 0 | CO42: 0 | CP42: 840.95 | CQ42: 0.5 | CR42: 0 | CS42: 0 | CT42: 0 | CU42: 0 | CW42: 0 | CX42: 07AALCG0172B1Z0 | CZ42: DL | DA42: 0 | DB42: 0 | DC42: 0 | DD42: 29AAECM9636P1ZJ | DE42: 27477 | EB42: PPMP | EL42: ON_HAND | EM42: 977 | EP42: 1000018540433 | EQ42: bc26b222-3626-43db-87cc-4a77ff253b1b | ES42: 11117630133
A43: 100029683331 | B43: 1.327549e+20 | C43: 2026-04-08T23:21:18.000+05:30 | D43: 46121.449 | E43: I0727GE000001789 | F43: CVETBRAA103646615 | G43: reverse_in_transit | H43: 46127.958 | L43: release_rto_refund | N43: INR | O43: 625 | P43: 0 | Q43: 625 | R43: 1499 | S43: 780 | T43: Inter-State | U43: 5 | V43: 29.76 | W43: 0 | X43: 0 | Y43: 2.9762 | Z43: 0 | AA43: 0 | AB43: 0 | AC43: 12.05 | AD43: 75.312 | BZ43: Myntra Designs Pvt Ltd | CA43: 62121000 | CB43: Apparel | CD43: Chelvet | CE43: Women | CF43: Bra | CG43: ON_HAND | CH43: FALSE | CI43: 5965579488374 | CJ43: 10c9d1db.ddbe.40c7.919e.ba08e74384521Vz70CglcN | CK43: 855113 | CL43: BR | CM43: 5 | CN43: 0 | CO43: 0 | CP43: 595.24 | CQ43: 0.5 | CR43: 0 | CS43: 0 | CT43: 0 | CU43: 0 | CW43: 0 | CX43: 07AALCG0172B1Z0 | CZ43: DL | DA43: 0 | DB43: 0 | DC43: 0 | DD43: 29AAECM9636P1ZJ | DE43: 27477 | EB43: PPMP | EL43: ON_HAND | EM43: 719 | EP43: 100029683331 | EQ43: 5aa9a98c-b0e7-417e-a255-bcf8e29fad66 | ES43: 11084412274
A44: 100022750800 | B44: 1.3272581e+20 | C44: 2026-04-05T14:31:24.000+05:30 | D44: 46118.556 | E44: I0727GE000001292 | F44: CVETBRAA103725199 | G44: reverse_in_transit | H44: 46119.75 | I44: 46119.82 | J44: 46120.025 | L44: return_refund | N44: INR | O44: 811 | P44: 0 | Q44: 811 | R44: 1849 | S44: 944 | T44: Intra-State | U44: 5 | V44: 0 | W44: 19.31 | X44: 19.31 | Y44: 0 | Z44: 1.93095 | AA44: 1.93095 | AB44: 0 | AC44: 12.86 | AD44: 104.295 | BZ44: Myntra Designs Pvt Ltd | CA44: 62121000 | CB44: Apparel | CD44: Chelvet | CE44: Women | CF44: Bra | CG44: ON_HAND | CH44: FALSE | CI44: MYSP1384321150 | CJ44: c09460cb.4e70.4edc.934a.f1a078618d33DKCfrdZrIz | CK44: 110015 | CL44: DL | CM44: 0 | CN44: 2.5 | CO44: 2.5 | CP44: 772.38 | CQ44: 0 | CR44: 0.25 | CS44: 0.25 | CT44: 0 | CU44: 0 | CW44: 0 | CX44: 07AALCG0172B1Z0 | CZ44: DL | DA44: 0 | DB44: 0 | DC44: 0 | DD44: 29AAECM9636P1ZJ | DE44: 27477 | EB44: PPMP | EL44: ON_HAND | EM44: 905 | EP44: 100022750800 | EQ44: c21f9107-3bfe-4a8e-9943-8c642041fde3 | ES44: 11077479671 | ET44: DLS
A45: 100034591396 | B45: 1.3277781e+20 | C45: 2026-04-11T14:59:00.000+05:30 | D45: 46123.704 | E45: I0927GE000000089 | F45: CVETNIDR118984881 | G45: reverse_in_transit | H45: 46129.479 | I45: 46132.907 | J45: 46133.753 | L45: return_refund | N45: INR | O45: 3443 | P45: 0 | Q45: 3443 | R45: 7299 | S45: 3650 | T45: Inter-State | U45: 18 | V45: 525.2 | W45: 0 | X45: 0 | Y45: 14.589 | Z45: 0 | AA45: 0 | AB45: 0 | AC45: 17.7 | AD45: 609.411 | BZ45: Myntra Designs Pvt Ltd | CA45: 62082200 | CB45: Apparel | CD45: Chelvet | CE45: Women | CF45: Nightdress | CG45: ON_HAND | CH45: FALSE | CI45: MYSP1387097299 | CJ45: 2ac3079b.5d28.49a7.b164.23b38f9fdc95fepLiRrjHp | CK45: 411045 | CL45: MH | CM45: 18 | CN45: 0 | CO45: 0 | CP45: 2917.8 | CQ45: 0.5 | CR45: 0 | CS45: 0 | CT45: 0 | CU45: 0 | CW45: 0 | CX45: 09AALCG0172B1ZW | CZ45: UP | DA45: 0 | DB45: 0 | DC45: 0 | DD45: 29AAECM9636P1ZJ | DE45: 27477 | EB45: PPMP | EL45: ON_HAND | EM45: 3649 | EP45: 100034591396 | EQ45: cbae582b-bab6-4440-9f08-f93ba98095fa | ES45: 11089320344 | ET45: DLS
A46: 100027076920 | B46: 1.3274428e+20 | C46: 2026-04-07T17:49:52.000+05:30 | D46: 46120.45 | E46: I0727GE000001591 | F46: CVETBRAA103723135 | G46: delivered | H46: 46127.479 | I46: 46126.658 | N46: INR | O46: 525 | P46: 0 | Q46: 525 | R46: 1999 | S46: 1380 | T46: Inter-State | U46: 5 | V46: 25 | W46: 0 | X46: 0 | Y46: 2.5 | Z46: 0 | AA46: 0 | AB46: 0 | AC46: 8.65 | AD46: 45.413 | BZ46: Myntra Designs Pvt Ltd | CA46: 62121000 | CB46: Apparel | CD46: Chelvet | CE46: Women | CF46: Bra | CG46: ON_HAND | CH46: FALSE | CI46: MYSP1385295127 | CJ46: 5fb5952f.801a.45ce.ae63.e93dfa9f3e18ogMxcilGIU | CK46: 682038 | CL46: KL | CM46: 5 | CN46: 0 | CO46: 0 | CP46: 500 | CQ46: 0.5 | CR46: 0 | CS46: 0 | CT46: 0 | CU46: 0 | CW46: 0 | CX46: 07AALCG0172B1Z0 | CZ46: DL | DA46: 0 | DB46: 0 | DC46: 0 | DD46: 29AAECM9636P1ZJ | DE46: 27477 | EB46: PPMP | EL46: ON_HAND | EM46: 619 | EP46: 100027076920 | EQ46: a21a9288-92a8-4fec-967f-5085efa34f77 | ES46: 11081805849
A47: 100044419963 | B47: 1.3282148e+20 | C47: 2026-04-16T16:17:31.000+05:30 | D47: 46128.705 | E47: I0927GE000000126 | F47: CVETLNGR119189034 | G47: delivered | H47: 46133.354 | I47: 46133.868 | N47: INR | O47: 875 | P47: 0 | Q47: 875 | R47: 2310 | S47: 1317 | T47: Inter-State | U47: 5 | V47: 41.67 | W47: 0 | X47: 0 | Y47: 4.16665 | Z47: 0 | AA47: 0 | AB47: 0 | AC47: 16.57 | AD47: 144.988 | BZ47: Myntra Designs Pvt Ltd | CA47: 62121000 | CB47: Apparel | CD47: Chelvet | CE47: Women | CF47: Lingerie Set | CG47: ON_HAND | CH47: FALSE | CI47: MYSP1389588507 | CJ47: b87b48ab.aa41.4098.8c18.d41df67965ddRnJRnCTmZH | CK47: 462010 | CL47: MP | CM47: 5 | CN47: 0 | CO47: 0 | CP47: 833.33 | CQ47: 0.5 | CR47: 0 | CS47: 0 | CT47: 0 | CU47: 0 | CW47: 0 | CX47: 09AALCG0172B1ZW | CZ47: UP | DA47: 0 | DB47: 0 | DC47: 0 | DD47: 29AAECM9636P1ZJ | DE47: 27477 | EB47: PPMP | EL47: ON_HAND | EM47: 993 | EP47: 1000012837877 | EQ47: f24c696c-faba-42c5-923d-bb1b62bfa9b5 | ES47: 11099148929
A48: 100045836062 | B48: 1.328285e+20 | C48: 2026-04-17T11:46:53.000+05:30 | D48: 46129.555 | E48: I0727GE000003392 | F48: CVETBRAA112489904 | G48: reverse_in_transit | H48: 46130.75 | I48: 46130.854 | J48: 46131.178 | L48: return_refund | N48: INR | O48: 1305 | P48: 0 | Q48: 1305 | R48: 1555 | S48: 79 | T48: Intra-State | U48: 5 | V48: 0 | W48: 31.07 | X48: 31.07 | Y48: 0 | Z48: 3.10715 | AA48: 3.10715 | AB48: 0 | AC48: 19.64 | AD48: 256.302 | BZ48: Myntra Designs Pvt Ltd | CA48: 62121000 | CB48: Apparel | CD48: Chelvet | CE48: Women | CF48: Bra | CG48: ON_HAND | CH48: FALSE | CI48: MYSP1389947155 | CJ48: 9805e66c.40e3.4da4.a9f2.da981917a4e29Uddu7tNZM | CK48: 110092 | CL48: DL | CM48: 0 | CN48: 2.5 | CO48: 2.5 | CP48: 1242.86 | CQ48: 0 | CR48: 0.25 | CS48: 0.25 | CT48: 0 | CU48: 0 | CW48: 0 | CX48: 07AALCG0172B1Z0 | CZ48: DL | DA48: 0 | DB48: 0 | DC48: 0 | DD48: 29AAECM9636P1ZJ | DE48: 27477 | EB48: PPMP | EL48: ON_HAND | EM48: 1476 | EP48: 100045836062 | EQ48: ade4386a-f1da-4caf-8c9f-c65cbdd2fccd | ES48: 11100565029 | ET48: DLS
A49: 100042135253 | B49: 1.3281084e+20 | C49: 2026-04-15T10:43:26.000+05:30 | D49: 46127.462 | E49: I0927GE000000120 | F49: CVETBRAA127431573 | G49: reverse_in_transit | H49: 46135.479 | I49: 46130.786 | J49: 46131.878 | L49: return_refund | N49: INR | O49: 1596 | P49: 0 | Q49: 1596 | R49: 2599 | S49: 832 | T49: Inter-State | U49: 5 | V49: 76 | W49: 0 | X49: 0 | Y49: 7.6 | Z49: 0 | AA49: 0 | AB49: 0 | AC49: 18.22 | AD49: 290.791 | BZ49: Myntra Designs Pvt Ltd | CA49: 62121000 | CB49: Apparel | CD49: Chelvet | CE49: Women | CF49: Bra | CG49: ON_HAND | CH49: FALSE | CI49: MYSP1388959172 | CJ49: d0ab900f.1088.4e96.945a.48be745747c7STBcJVYRyE | CK49: 302017 | CL49: RJ | CM49: 5 | CN49: 0 | CO49: 0 | CP49: 1520 | CQ49: 0.5 | CR49: 0 | CS49: 0 | CT49: 0 | CU49: 0 | CW49: 0 | CX49: 09AALCG0172B1ZW | CZ49: UP | DA49: 0 | DB49: 0 | DC49: 0 | DD49: 29AAECM9636P1ZJ | DE49: 27477 | EB49: PPMP | EL49: ON_HAND | EM49: 1767 | EP49: 100042135253 | EQ49: 309e498c-bd7e-48ca-9700-5d8824c67fd3 | ES49: 11096864212 | ET49: DLS
A50: 100052233851 | B50: 1.3285866e+20 | C50: 2026-04-20T23:33:50.000+05:30 | D50: 46133.501 | E50: I0727GE000004015 | F50: CVETBRAA104553133 | G50: delivered | H50: 46136.75 | I50: 46137.934 | N50: INR | O50: 847 | P50: 0 | Q50: 847 | R50: 1699 | S50: 758 | T50: Inter-State | U50: 5 | V50: 40.33 | W50: 0 | X50: 0 | Y50: 4.03335 | Z50: 0 | AA50: 0 | AB50: 0 | AC50: 20.06 | AD50: 169.908 | BZ50: Myntra Designs Pvt Ltd | CA50: 62121000 | CB50: Apparel | CD50: Chelvet | CE50: Women | CF50: Bra | CG50: ON_HAND | CH50: FALSE | CI50: MYSP1391723635 | CJ50: f908b048.6e5f.4faa.a6e5.1fa94a469031iCE77B235M | CK50: 500032 | CL50: TG | CM50: 5 | CN50: 0 | CO50: 0 | CP50: 806.67 | CQ50: 0.5 | CR50: 0 | CS50: 0 | CT50: 0 | CU50: 0 | CW50: 0 | CX50: 07AALCG0172B1Z0 | CZ50: DL | DA50: 0 | DB50: 0 | DC50: 0 | DD50: 29AAECM9636P1ZJ | DE50: 27477 | EB50: PPMP | EL50: ON_HAND | EM50: 941 | EP50: 1000015267964 | EQ50: 8776d895-8c79-4599-a1b5-bac3f9730067 | ES50: 11106962871
A51: 100060030651 | B51: 1.3290217e+20 | C51: 2026-04-26T00:25:28.000+05:30 | D51: 46139.459 | E51: I0727GE000004699 | F51: CVETBRAA103717725 | G51: reverse_in_transit | H51: 46143.479 | I51: 46144.032 | J51: 46144.244 | L51: return_refund | N51: INR | O51: 883 | P51: 0 | Q51: 883 | R51: 1849 | S51: 872 | T51: Inter-State | U51: 5 | V51: 42.05 | W51: 0 | X51: 0 | Y51: 4.20475 | Z51: 0 | AA51: 0 | AB51: 0 | AC51: 13.35 | AD51: 117.88 | BZ51: Myntra Designs Pvt Ltd | CA51: 62121000 | CB51: Apparel | CD51: Chelvet | CE51: Women | CF51: Bra | CG51: ON_HAND | CH51: FALSE | CI51: MYSP1394276839 | CJ51: 1d838a9f.6ff3.4cdc.84c5.58bd663c457bgO3evlVeLG | CK51: 400053 | CL51: MH | CM51: 5 | CN51: 0 | CO51: 0 | CP51: 840.95 | CQ51: 0.5 | CR51: 0 | CS51: 0 | CT51: 0 | CU51: 0 | CW51: 0 | CX51: 07AALCG0172B1Z0 | CZ51: DL | DA51: 0 | DB51: 0 | DC51: 0 | DD51: 29AAECM9636P1ZJ | DE51: 27477 | EB51: PPMP | EL51: ON_HAND | EM51: 977 | EP51: 100060030651 | EQ51: 4f83eca7-25b1-4f96-897c-59917a75312c | ES51: 11114759754 | ET51: DLS
A52: 100046604275 | B52: 1.3283144e+20 | C52: 2026-04-17T19:57:35.000+05:30 | D52: 46130.447 | E52: I0727GE000003516 | F52: CVETBRAA103640790 | G52: delivered | H52: 46134.479 | I52: 46134.687 | N52: INR | O52: 879 | P52: 0 | Q52: 879 | R52: 2099 | S52: 1126 | T52: Inter-State | U52: 5 | V52: 41.86 | W52: 0 | X52: 0 | Y52: 4.1857 | Z52: 0 | AA52: 0 | AB52: 0 | AC52: 13.02 | AD52: 114.446 | BZ52: Myntra Designs Pvt Ltd | CA52: 62121000 | CB52: Apparel | CD52: Chelvet | CE52: Women | CF52: Bra | CG52: ON_HAND | CH52: FALSE | CI52: MYSP1390285082 | CJ52: 6d3443fb.d463.481b.8f76.4f0c195baa0duRM5kMQCUg | CK52: 560103 | CL52: KA | CM52: 5 | CN52: 0 | CO52: 0 | CP52: 837.14 | CQ52: 0.5 | CR52: 0 | CS52: 0 | CT52: 0 | CU52: 0 | CW52: 0 | CX52: 07AALCG0172B1Z0 | CZ52: DL | DA52: 0 | DB52: 0 | DC52: 0 | DD52: 29AAECM9636P1ZJ | DE52: 27477 | EB52: PPMP | EL52: ON_HAND | EM52: 973 | EP52: 1000013704958 | EQ52: 6fb6bee9-71d8-40c6-9d6a-06dd4a2e0f70 | ES52: 11101333248
A53: 100019986207 | B53: 1.3271338e+20 | C53: 2026-04-04T04:00:39.000+05:30 | D53: 46116.43 | E53: I0927GE000000023 | F53: CVETBRAA127703226 | G53: reverse_in_transit | H53: 46120.479 | I53: 46120.885 | J53: 46127.725 | L53: return_refund | N53: INR | O53: 714 | P53: 0 | Q53: 714 | R53: 1499 | S53: 691 | T53: Inter-State | U53: 5 | V53: 34 | W53: 0 | X53: 0 | Y53: 3.4 | Z53: 0 | AA53: 0 | AB53: 0 | AC53: 15.89 | AD53: 113.455 | BZ53: Myntra Designs Pvt Ltd | CA53: 62121000 | CB53: Apparel | CD53: Chelvet | CE53: Women | CF53: Bra | CG53: ON_HAND | CH53: FALSE | CI53: MYSP1383055243 | CJ53: 96b254da.3956.4882.ab27.e439050c0131tN5dObvcw6 | CK53: 411028 | CL53: MH | CM53: 5 | CN53: 0 | CO53: 0 | CP53: 680 | CQ53: 0.5 | CR53: 0 | CS53: 0 | CT53: 0 | CU53: 0 | CW53: 0 | CX53: 09AALCG0172B1ZW | CZ53: UP | DA53: 0 | DB53: 0 | DC53: 0 | DD53: 29AAECM9636P1ZJ | DE53: 27477 | EB53: PPMP | EL53: ON_HAND | EM53: 808 | EP53: 1000005413158 | EQ53: ca0e8fc3-e76f-43bc-911e-29a068c24466 | ES53: 11074715069 | ET53: DLS
A54: 100037629225 | B54: 1.3278948e+20 | C54: 2026-04-12T23:23:20.000+05:30 | D54: 46126.412 | E54: I0927GE000000101 | F54: CVETBRAA120951106 | G54: reverse_in_transit | H54: 46129.479 | I54: 46131.803 | J54: 46133.957 | L54: return_refund | N54: INR | O54: 996 | P54: 0 | Q54: 996 | R54: 2540 | S54: 1373 | T54: Inter-State | U54: 5 | V54: 47.43 | W54: 0 | X54: 0 | Y54: 4.74285 | Z54: 0 | AA54: 0 | AB54: 0 | AC54: 14.21 | AD54: 141.532 | BZ54: Myntra Designs Pvt Ltd | CA54: 62121000 | CB54: Apparel | CD54: Chelvet | CE54: Women | CF54: Bra | CG54: ON_HAND | CH54: FALSE | CI54: MYSP1388410525 | CJ54: f5d12476.2568.4172.b0b1.88393c3732c7QThGaPMMFK | CK54: 500089 | CL54: TG | CM54: 5 | CN54: 0 | CO54: 0 | CP54: 948.57 | CQ54: 0.5 | CR54: 0 | CS54: 0 | CT54: 0 | CU54: 0 | CW54: 0 | CX54: 09AALCG0172B1ZW | CZ54: UP | DA54: 0 | DB54: 0 | DC54: 0 | DD54: 29AAECM9636P1ZJ | DE54: 27477 | EB54: PPMP | EL54: ON_HAND | EM54: 1167 | EP54: 100037629225 | EQ54: 94c8c54a-9a15-45ac-8de8-5000cfb610a9 | ES54: 11092358180 | ET54: DLS
A55: 100028332076 | B55: 1.3275048e+20 | C55: 2026-04-08T11:03:35.000+05:30 | D55: 46120.556 | E55: I0727GE000001784 | F55: CVETBRAA103705081 | G55: delivered | H55: 46125.479 | I55: 46124.832 | N55: INR | O55: 608 | P55: 0 | Q55: 608 | R55: 1849 | S55: 1147 | T55: Inter-State | U55: 5 | V55: 28.95 | W55: 0 | X55: 0 | Y55: 2.89525 | Z55: 0 | AA55: 0 | AB55: 0 | AC55: 10.3 | AD55: 62.624 | BZ55: Myntra Designs Pvt Ltd | CA55: 62121000 | CB55: Apparel | CD55: Chelvet | CE55: Women | CF55: Bra | CG55: ON_HAND | CH55: FALSE | CI55: MYEP1113644345 | CJ55: 73c68aa5.4a21.4b37.b0c1.7a34cff75c8azINYzUNf7c | CK55: 394520 | CL55: GJ | CM55: 5 | CN55: 0 | CO55: 0 | CP55: 579.05 | CQ55: 0.5 | CR55: 0 | CS55: 0 | CT55: 0 | CU55: 0 | CW55: 0 | CX55: 07AALCG0172B1Z0 | CZ55: DL | DA55: 0 | DB55: 0 | DC55: 0 | DD55: 29AAECM9636P1ZJ | DE55: 27477 | EB55: PPMP | EL55: ON_HAND | EM55: 702 | EP55: 100028332076 | EQ55: 8c31d8f1-5db8-44dd-b047-a87703ab7dd2 | ES55: 11083061014
A56: 100045676874 | B56: 1.3282789e+20 | C56: 2026-04-17T10:06:07.000+05:30 | D56: 46129.507 | E56: I0727GE000003379 | F56: CVETBRAA103682603 | G56: delivered | H56: 46133.479 | I56: 46134.726 | N56: INR | O56: 535 | P56: 0 | Q56: 535 | R56: 1499 | S56: 870 | T56: Inter-State | U56: 5 | V56: 25.48 | W56: 0 | X56: 0 | Y56: 2.5476 | Z56: 0 | AA56: 0 | AB56: 0 | AC56: 11.88 | AD56: 63.558 | BZ56: Myntra Designs Pvt Ltd | CA56: 62121000 | CB56: Apparel | CD56: Chelvet | CE56: Women | CF56: Bra | CG56: ON_HAND | CH56: FALSE | CI56: MYSP1389911428 | CJ56: dc0d0054.52cd.4184.a626.db8f6488c98dUd11sv0Ac1 | CK56: 560016 | CL56: KA | CM56: 5 | CN56: 0 | CO56: 0 | CP56: 509.52 | CQ56: 0.5 | CR56: 0 | CS56: 0 | CT56: 0 | CU56: 0 | CW56: 0 | CX56: 07AALCG0172B1Z0 | CZ56: DL | DA56: 0 | DB56: 0 | DC56: 0 | DD56: 29AAECM9636P1ZJ | DE56: 27477 | EB56: PPMP | EL56: ON_HAND | EM56: 629 | EP56: 1000013223622 | EQ56: 007f9313-929b-4656-9907-0a64d813ca8f | ES56: 11100405841
A57: 100046417216 | B57: 1.328307e+20 | C57: 2026-04-17T17:53:39.000+05:30 | D57: 46130.447 | E57: I0727GE000003517 | F57: CVETBRAA103725596 | G57: reverse_in_transit | H57: 46134.479 | L57: release_rto_refund | N57: INR | O57: 843 | P57: 0 | Q57: 843 | R57: 1749 | S57: 812 | T57: Inter-State | U57: 5 | V57: 40.14 | W57: 0 | X57: 0 | Y57: 4.0143 | Z57: 0 | AA57: 0 | AB57: 0 | AC57: 13.3 | AD57: 112.119 | BZ57: Myntra Designs Pvt Ltd | CA57: 62121000 | CB57: Apparel | CD57: Chelvet | CE57: Women | CF57: Bra | CG57: ON_HAND | CH57: FALSE | CI57: MYSP1390285697 | CJ57: f6b6c169.bd92.4313.8dfb.ac0298b468d169CWBtURFY | CK57: 411027 | CL57: MH | CM57: 5 | CN57: 0 | CO57: 0 | CP57: 802.86 | CQ57: 0.5 | CR57: 0 | CS57: 0 | CT57: 0 | CU57: 0 | CW57: 0 | CX57: 07AALCG0172B1Z0 | CZ57: DL | DA57: 0 | DB57: 0 | DC57: 0 | DD57: 29AAECM9636P1ZJ | DE57: 27477 | EB57: PPMP | EL57: ON_HAND | EM57: 937 | EP57: 1000013705051 | EQ57: e9a9e0af-d358-46e7-8f3e-fbdfbee37990 | ES57: 11101146188
A58: 100014002563 | B58: 1.3268918e+20 | C58: 2026-04-01T08:47:40.000+05:30 | D58: 46113.438 | E58: I0727GE000000125 | F58: CVETBRAA103725644 | G58: reverse_in_transit | H58: 46115.479 | I58: 46115.747 | J58: 46116.05 | L58: return_refund | N58: INR | O58: 843 | P58: 0 | Q58: 842.98 | R58: 1749 | S58: 812 | T58: Inter-State | U58: 5 | V58: 40.14 | W58: 0 | X58: 0 | Y58: 4.0143 | Z58: 0 | AA58: 0 | AB58: 0 | AC58: 13.3 | AD58: 112.119 | BZ58: Myntra Designs Pvt Ltd | CA58: 62121000 | CB58: Apparel | CD58: Chelvet | CE58: Women | CF58: Bra | CG58: ON_HAND | CH58: FALSE | CI58: MYEP1112582162 | CJ58: 708bf79f.437d.4e03.9a58.55358c2eebc2u14NQgCHZq | CK58: 333001 | CL58: RJ | CM58: 5 | CN58: 0 | CO58: 0 | CP58: 802.86 | CQ58: 0.5 | CR58: 0 | CS58: 0 | CT58: 0 | CU58: 0 | CW58: 0 | CX58: 07AALCG0172B1Z0 | CZ58: DL | DA58: 0 | DB58: 0 | DC58: 0 | DD58: 29AAECM9636P1ZJ | DE58: 27477 | EB58: PPMP | EL58: ON_HAND | EM58: 937.02 | EP58: 100014002563 | EQ58: ec1115a4-fca6-4dc1-9a83-1a55680e0286 | ES58: 11068731374 | ET58: DLS
A59: 100035484934 | B59: 1.3278077e+20 | C59: 2026-04-11T23:12:09.000+05:30 | D59: 46125.461 | E59: I0727GE000002473 | F59: CVETBRAA103646625 | G59: reverse_in_transit | H59: 46130.479 | L59: release_rto_refund | N59: INR | O59: 625 | P59: 0 | Q59: 625 | R59: 1499 | S59: 780 | T59: Inter-State | U59: 5 | V59: 29.76 | W59: 0 | X59: 0 | Y59: 2.9762 | Z59: 0 | AA59: 0 | AB59: 0 | AC59: 12.05 | AD59: 75.312 | BZ59: Myntra Designs Pvt Ltd | CA59: 62121000 | CB59: Apparel | CD59: Chelvet | CE59: Women | CF59: Bra | CG59: ON_HAND | CH59: FALSE | CI59: MYSP1387971315 | CJ59: 0a2fd92c.bbc9.4f15.a077.127afc764c75MGedUHP4Wv | CK59: 700054 | CL59: WB | CM59: 5 | CN59: 0 | CO59: 0 | CP59: 595.24 | CQ59: 0.5 | CR59: 0 | CS59: 0 | CT59: 0 | CU59: 0 | CW59: 0 | CX59: 07AALCG0172B1Z0 | CZ59: DL | DA59: 0 | DB59: 0 | DC59: 0 | DD59: 29AAECM9636P1ZJ | DE59: 27477 | EB59: PPMP | EL59: ON_HAND | EM59: 719 | EP59: 100035484934 | EQ59: b6c55a54-34bb-482a-a554-2655fe379d74 | ES59: 11090213884
A60: 100026451916 | B60: 1.3274211e+20 | C60: 2026-04-07T11:48:53.000+05:30 | D60: 46119.538 | E60: I0727GE000001526 | F60: CVETBRAA103725590 | G60: delivered | H60: 46123.479 | I60: 46123.749 | N60: INR | O60: 843 | P60: 0 | Q60: 843 | R60: 1749 | S60: 812 | T60: Inter-State | U60: 5 | V60: 40.14 | W60: 0 | X60: 0 | Y60: 4.0143 | Z60: 0 | AA60: 0 | AB60: 0 | AC60: 13.3 | AD60: 112.119 | BZ60: Myntra Designs Pvt Ltd | CA60: 62121000 | CB60: Apparel | CD60: Chelvet | CE60: Women | CF60: Bra | CG60: ON_HAND | CH60: FALSE | CI60: MYSP1384864837 | CJ60: 9490ae75.8f7b.49eb.8b5a.6fda881e06e25CoItgObQV | CK60: 440014 | CL60: MH | CM60: 5 | CN60: 0 | CO60: 0 | CP60: 802.86 | CQ60: 0.5 | CR60: 0 | CS60: 0 | CT60: 0 | CU60: 0 | CW60: 0 | CX60: 07AALCG0172B1Z0 | CZ60: DL | DA60: 0 | DB60: 0 | DC60: 0 | DD60: 29AAECM9636P1ZJ | DE60: 27477 | EB60: PPMP | EL60: ON_HAND | EM60: 937 | EP60: 1000007374566 | EQ60: 179a5487-09ea-4eb3-9ab8-e0f9b70860a8 | ES60: 11081180824
A61: 100038732163 | B61: 1.3279503e+20 | C61: 2026-04-13T14:49:19.000+05:30 | D61: 46126.479 | E61: I0727GE000002758 | F61: CVETBRAA103643243 | G61: reverse_in_transit | H61: 46130.479 | I61: 46130.767 | J61: 46133.854 | L61: return_refund | N61: INR | O61: 705 | P61: 0 | Q61: 705 | R61: 1499 | S61: 700 | T61: Inter-State | U61: 5 | V61: 33.57 | W61: 0 | X61: 0 | Y61: 3.35715 | Z61: 0 | AA61: 0 | AB61: 0 | AC61: 20.06 | AD61: 141.423 | BZ61: Myntra Designs Pvt Ltd | CA61: 62121000 | CB61: Apparel | CD61: Chelvet | CE61: Women | CF61: Bra | CG61: ON_HAND | CH61: FALSE | CI61: MYSP1388503636 | CJ61: c4419461.d386.4fe0.bc6b.67a4d4628840ipLN7nXJYR | CK61: 560005 | CL61: KA | CM61: 5 | CN61: 0 | CO61: 0 | CP61: 671.43 | CQ61: 0.5 | CR61: 0 | CS61: 0 | CT61: 0 | CU61: 0 | CW61: 0 | CX61: 07AALCG0172B1Z0 | CZ61: DL | DA61: 0 | DB61: 0 | DC61: 0 | DD61: 29AAECM9636P1ZJ | DE61: 27477 | EB61: PPMP | EL61: ON_HAND | EM61: 799 | EP61: 100038732163 | EQ61: 7158f437-e85d-41ad-93ce-0d07e86e668e | ES61: 11093461119 | ET61: DLS
A62: 100045047307 | B62: 1.3282364e+20 | C62: 2026-04-16T22:16:27.000+05:30 | D62: 46129.438 | E62: I0927GE000000133 | F62: CVETBRAA129785752 | G62: delivered | H62: 46133.479 | I62: 46133.976 | N62: INR | O62: 805 | P62: 805 | Q62: 0 | R62: 2999 | S62: 2100 | T62: Inter-State | U62: 5 | V62: 38.33 | W62: 0 | X62: 0 | Y62: 3.83335 | Z62: 0 | AA62: 0 | AB62: 0 | AC62: 20.06 | AD62: 161.483 | BZ62: Myntra Designs Pvt Ltd | CA62: 62121000 | CB62: Apparel | CD62: Chelvet | CE62: Women | CF62: Bra | CG62: ON_HAND | CH62: FALSE | CI62: MYSC1285108318 | CJ62: f9638b25.81b0.4e5e.b14d.2df90de70e63vaE6wxiQF6 | CK62: 560076 | CL62: KA | CM62: 5 | CN62: 0 | CO62: 0 | CP62: 766.67 | CQ62: 0.5 | CR62: 0 | CS62: 0 | CT62: 0 | CU62: 0 | CW62: 0 | CX62: 09AALCG0172B1ZW | CZ62: UP | DA62: 0 | DB62: 0 | DC62: 0 | DD62: 29AAECM9636P1ZJ | DE62: 27477 | EB62: PPMP | EL62: ON_HAND | EM62: 899 | EP62: 100045047307 | EQ62: 5d4259b1-d7ed-40e6-8f8e-373c3e452336 | ES62: 11099776274
A63: 100058683386 | B63: 1.3289702e+20 | C63: 2026-04-25T10:07:42.000+05:30 | D63: 46137.491 | E63: I0727GE000004593 | F63: CVETBRAA103646618 | G63: reverse_in_transit | H63: 46139.479 | I63: 46138.679 | J63: 46139.164 | L63: return_refund | N63: INR | O63: 625 | P63: 548.67003 | Q63: 76.329972 | R63: 1499 | S63: 780 | T63: Intra-State | U63: 5 | V63: 0 | W63: 14.88 | X63: 14.88 | Y63: 0 | Z63: 1.4881 | AA63: 1.4881 | AB63: 0 | AC63: 12.05 | AD63: 75.313 | BZ63: Myntra Designs Pvt Ltd | CA63: 62121000 | CB63: Apparel | CD63: Chelvet | CE63: Women | CF63: Bra | CG63: ON_HAND | CH63: FALSE | CI63: MYSC1287893412 | CJ63: a333c8c4.a860.4962.abb0.b94060c0142eit5nQA4Z68 | CK63: 110018 | CL63: DL | CM63: 0 | CN63: 2.5 | CO63: 2.5 | CP63: 595.24 | CQ63: 0 | CR63: 0.25 | CS63: 0.25 | CT63: 0 | CU63: 0 | CW63: 0 | CX63: 07AALCG0172B1Z0 | CZ63: DL | DA63: 0 | DB63: 0 | DC63: 0 | DD63: 29AAECM9636P1ZJ | DE63: 27477 | EB63: PPMP | EL63: ON_HAND | EM63: 719 | EP63: 100058683386 | EQ63: c928a1a0-88b5-4d52-b9fd-4e574f6b3c29 | ES63: 11113412474 | ET63: DLS
A64: 100048155096 | B64: 1.3283892e+20 | C64: 2026-04-18T16:44:05.000+05:30 | D64: 46130.735 | E64: I0927GE000000145 | F64: CVETNIDR118984877 | G64: delivered | H64: 46133.75 | I64: 46133.962 | N64: INR | O64: 2993 | P64: 2993 | Q64: 0 | R64: 7799 | S64: 4600 | T64: Inter-State | U64: 18 | V64: 456.56 | W64: 0 | X64: 0 | Y64: 12.6822 | Z64: 0 | AA64: 0 | AB64: 0 | AC64: 17.7 | AD64: 529.761 | BZ64: Myntra Designs Pvt Ltd | CA64: 62082200 | CB64: Apparel | CD64: Chelvet | CE64: Women | CF64: Nightdress | CG64: ON_HAND | CH64: FALSE | CI64: MYSC1285655591 | CJ64: 9846a1f5.3227.4e7d.ad87.95967dd82a44vBD4v563ul | CK64: 110048 | CL64: DL | CM64: 18 | CN64: 0 | CO64: 0 | CP64: 2536.44 | CQ64: 0.5 | CR64: 0 | CS64: 0 | CT64: 0 | CU64: 0 | CW64: 0 | CX64: 09AALCG0172B1ZW | CZ64: UP | DA64: 0 | DB64: 0 | DC64: 0 | DD64: 29AAECM9636P1ZJ | DE64: 27477 | EB64: PPMP | EL64: ON_HAND | EM64: 3199 | EP64: 1000013914045 | EQ64: dd565cdb-8214-4838-986f-46f99cb8f03f | ES64: 11102884082
A65: 100032566729 | B65: 1.327688e+20 | C65: 2026-04-10T13:57:10.000+05:30 | D65: 46123.44 | E65: I0727GE000002320 | F65: CVETBRAA103725212 | G65: reverse_in_transit | H65: 46127.479 | I65: 46127.761 | J65: 46130.786 | L65: return_refund | N65: INR | O65: 811 | P65: 0 | Q65: 811 | R65: 1849 | S65: 944 | T65: Inter-State | U65: 5 | V65: 38.62 | W65: 0 | X65: 0 | Y65: 3.8619 | Z65: 0 | AA65: 0 | AB65: 0 | AC65: 12.86 | AD65: 104.295 | BZ65: Myntra Designs Pvt Ltd | CA65: 62121000 | CB65: Apparel | CD65: Chelvet | CE65: Women | CF65: Bra | CG65: ON_HAND | CH65: FALSE | CI65: MYSP1386873028 | CJ65: 3664ac3d.5b14.4ff2.ac79.cf1c2364b1e2lx2h1WOXMo | CK65: 560103 | CL65: KA | CM65: 5 | CN65: 0 | CO65: 0 | CP65: 772.38 | CQ65: 0.5 | CR65: 0 | CS65: 0 | CT65: 0 | CU65: 0 | CW65: 0 | CX65: 07AALCG0172B1Z0 | CZ65: DL | DA65: 0 | DB65: 0 | DC65: 0 | DD65: 29AAECM9636P1ZJ | DE65: 27477 | EB65: PPMP | EL65: ON_HAND | EM65: 905 | EP65: 100032566729 | EQ65: f8d7cede-3fd3-4037-a009-10f3ce4ce716 | ES65: 11087295676 | ET65: DLS
A66: 100038954123 | B66: 1.3279581e+20 | C66: 2026-04-13T16:58:57.000+05:30 | D66: 46126.479 | E66: I0727GE000002761 | F66: CVETBRAA103722906 | G66: delivered | H66: 46128.479 | I66: 46128.879 | N66: INR | O66: 525 | P66: 525 | Q66: 0 | R66: 1999 | S66: 1380 | T66: Inter-State | U66: 5 | V66: 25 | W66: 0 | X66: 0 | Y66: 2.5 | Z66: 0 | AA66: 0 | AB66: 0 | AC66: 8.65 | AD66: 45.413 | BZ66: Myntra Designs Pvt Ltd | CA66: 62121000 | CB66: Apparel | CD66: Chelvet | CE66: Women | CF66: Bra | CG66: ON_HAND | CH66: FALSE | CI66: MYSC1284000561 | CJ66: eab213ae.a133.42b5.8d0a.b0e7d17eb365v0cRrvB4pf | CK66: 313001 | CL66: RJ | CM66: 5 | CN66: 0 | CO66: 0 | CP66: 500 | CQ66: 0.5 | CR66: 0 | CS66: 0 | CT66: 0 | CU66: 0 | CW66: 0 | CX66: 07AALCG0172B1Z0 | CZ66: DL | DA66: 0 | DB66: 0 | DC66: 0 | DD66: 29AAECM9636P1ZJ | DE66: 27477 | EB66: PPMP | EL66: ON_HAND | EM66: 619 | EP66: 100038954123 | EQ66: 1834cfdb-2d5d-4171-89d5-d5a98e7da280 | ES66: 11093683079
A67: 100052413606 | B67: 1.3285983e+20 | C67: 2026-04-21T02:49:15.000+05:30 | D67: 46133.443 | E67: I0727GE000003878 | F67: CVETBRAA103722810 | G67: reverse_in_transit | H67: 46135.479 | I67: 46134.774 | J67: 46134.783 | L67: return_refund | N67: INR | O67: 599 | P67: 599 | Q67: 0 | R67: 1999 | S67: 1306 | T67: Inter-State | U67: 5 | V67: 28.52 | W67: 0 | X67: 0 | Y67: 2.8524 | Z67: 0 | AA67: 0 | AB67: 0 | AC67: 20.06 | AD67: 120.159 | BZ67: Myntra Designs Pvt Ltd | CA67: 62121000 | CB67: Apparel | CD67: Chelvet | CE67: Women | CF67: Bra | CG67: ON_HAND | CH67: FALSE | CI67: MYSC1286540936 | CJ67: 56e9b9d6.58d1.47ba.886c.fe34b45cadb88La3bbLSkh | CK67: 201301 | CL67: UP | CM67: 5 | CN67: 0 | CO67: 0 | CP67: 570.48 | CQ67: 0.5 | CR67: 0 | CS67: 0 | CT67: 0 | CU67: 0 | CW67: 0 | CX67: 07AALCG0172B1Z0 | CZ67: DL | DA67: 0 | DB67: 0 | DC67: 0 | DD67: 29AAECM9636P1ZJ | DE67: 27477 | EB67: PPMP | EL67: ON_HAND | EM67: 693 | EP67: 100052413606 | EQ67: 2f09bf83-7e89-4c97-bb6a-4a22143eb003 | ES67: 11107142626 | ET67: DLS
A68: 100028111509 | B68: 1.3274956e+20 | C68: 2026-04-08T08:29:44.000+05:30 | D68: 46120.517 | E68: I0727GE000001663 | F68: CVETBRAA103725589 | G68: delivered | H68: 46124.479 | I68: 46124.824 | N68: INR | O68: 843 | P68: 0 | Q68: 843 | R68: 1749 | S68: 812 | T68: Inter-State | U68: 5 | V68: 40.14 | W68: 0 | X68: 0 | Y68: 4.0143 | Z68: 0 | AA68: 0 | AB68: 0 | AC68: 13.3 | AD68: 112.119 | BZ68: Myntra Designs Pvt Ltd | CA68: 62121000 | CB68: Apparel | CD68: Chelvet | CE68: Women | CF68: Bra | CG68: ON_HAND | CH68: FALSE | CI68: MYSP1385378101 | CJ68: e3d2846d.a809.4c48.a324.894c506467fc9nihqSibOW | CK68: 440015 | CL68: MH | CM68: 5 | CN68: 0 | CO68: 0 | CP68: 802.86 | CQ68: 0.5 | CR68: 0 | CS68: 0 | CT68: 0 | CU68: 0 | CW68: 0 | CX68: 07AALCG0172B1Z0 | CZ68: DL | DA68: 0 | DB68: 0 | DC68: 0 | DD68: 29AAECM9636P1ZJ | DE68: 27477 | EB68: PPMP | EL68: ON_HAND | EM68: 937 | EP68: 1000007941870 | EQ68: c2234897-e7cb-40d8-a74d-63d4067b5216 | ES68: 11082840444
A69: 100028868775 | B69: 1.3275227e+20 | C69: 2026-04-08T16:02:20.000+05:30 | D69: 46120.687 | E69: I0927GE000000059 | F69: CVETBRAA127703221 | G69: delivered | H69: 46126.479 | I69: 46126.718 | N69: INR | O69: 656 | P69: 656 | Q69: 0 | R69: 1499 | S69: 749 | T69: Inter-State | U69: 5 | V69: 31.24 | W69: 0 | X69: 0 | Y69: 3.1238 | Z69: 0 | AA69: 0 | AB69: 0 | AC69: 15.53 | AD69: 101.877 | BZ69: Myntra Designs Pvt Ltd | CA69: 62121000 | CB69: Apparel | CD69: Chelvet | CE69: Women | CF69: Bra | CG69: ON_HAND | CH69: FALSE | CI69: MYSC1281708162 | CJ69: 593855e9.15e0.436a.8707.19a2d8437a676N1wNFW1tm | CK69: 766014 | CL69: OR | CM69: 5 | CN69: 0 | CO69: 0 | CP69: 624.76 | CQ69: 0.5 | CR69: 0 | CS69: 0 | CT69: 0 | CU69: 0 | CW69: 0 | CX69: 09AALCG0172B1ZW | CZ69: UP | DA69: 0 | DB69: 0 | DC69: 0 | DD69: 29AAECM9636P1ZJ | DE69: 27477 | EB69: PPMP | EL69: ON_HAND | EM69: 750 | EP69: 100028868775 | EQ69: 134550df-ab48-49b4-8f3f-1c63205989a6 | ES69: 11083597715
A70: 100019572360 | B70: 1.3271139e+20 | C70: 2026-04-03T22:28:31.000+05:30 | D70: 46116.427 | E70: I0927GE000000022 | F70: CVETNIDR118984932 | G70: reverse_in_transit | H70: 46121.479 | I70: 46120.785 | J70: 46120.944 | L70: return_refund | N70: INR | O70: 1077 | P70: 1077 | Q70: 0 | R70: 3899 | S70: 2651 | T70: Inter-State | U70: 5 | V70: 51.29 | W70: 0 | X70: 0 | Y70: 5.12855 | Z70: 0 | AA70: 0 | AB70: 0 | AC70: 10.75 | AD70: 115.778 | BZ70: Myntra Designs Pvt Ltd | CA70: 62082200 | CB70: Apparel | CD70: Chelvet | CE70: Women | CF70: Nightdress | CG70: ON_HAND | CH70: FALSE | CI70: MYSC1279853941 | CJ70: 13d4777c.6427.4d44.a92d.b80cba08322aZp2idkXtdn | CK70: 751019 | CL70: OR | CM70: 5 | CN70: 0 | CO70: 0 | CP70: 1025.71 | CQ70: 0.5 | CR70: 0 | CS70: 0 | CT70: 0 | CU70: 0 | CW70: 0 | CX70: 09AALCG0172B1ZW | CZ70: UP | DA70: 0 | DB70: 0 | DC70: 0 | DD70: 29AAECM9636P1ZJ | DE70: 27477 | EB70: PPMP | EL70: ON_HAND | EM70: 1248 | EP70: 100019572360 | EQ70: 1f26c2eb-b1f7-43ac-a8b4-ad44791ce5f8 | ES70: 11074301222 | ET70: DLS
A71: 100062957930 | B71: 1.3291783e+20 | C71: 2026-04-27T19:55:09.000+05:30 | D71: 46140.446 | E71: I0727GE000004965 | F71: CVETBRAA103701214 | G71: delivered | H71: 46148.354 | I71: 46145.757 | N71: INR | O71: 873 | P71: 0 | Q71: 873 | R71: 1899 | S71: 932 | T71: Inter-State | U71: 5 | V71: 41.57 | W71: 0 | X71: 0 | Y71: 4.15715 | Z71: 0 | AA71: 0 | AB71: 0 | AC71: 12.64 | AD71: 110.347 | BZ71: Myntra Designs Pvt Ltd | CA71: 62121000 | CB71: Apparel | CD71: Chelvet | CE71: Women | CF71: Bra | CG71: ON_HAND | CH71: FALSE | CI71: MYEP1116259078 | CJ71: 71455172.426e.4f8c.ac91.bdbb81764073ic5M7IhJCq | CK71: 190021 | CL71: JK | CM71: 5 | CN71: 0 | CO71: 0 | CP71: 831.43 | CQ71: 0.5 | CR71: 0 | CS71: 0 | CT71: 0 | CU71: 0 | CW71: 0 | CX71: 07AALCG0172B1Z0 | CZ71: DL | DA71: 0 | DB71: 0 | DC71: 0 | DD71: 29AAECM9636P1ZJ | DE71: 27477 | EB71: PPMP | EL71: ON_HAND | EM71: 967 | EP71: 100062957930 | EQ71: 36254f25-f5be-46a4-9765-64d5d501639e | ES71: 11117687065
A72: 100034397768 | B72: 1.3277718e+20 | C72: 2026-04-11T13:14:12.000+05:30 | D72: 46123.617 | E72: I0927GE000000087 | F72: CVETNIDR118984881 | G72: reverse_in_transit | H72: 46129.479 | L72: release_rto_refund | N72: INR | O72: 3443 | P72: 3443 | Q72: 0 | R72: 7299 | S72: 3650 | T72: Inter-State | U72: 18 | V72: 525.2 | W72: 0 | X72: 0 | Y72: 14.589 | Z72: 0 | AA72: 0 | AB72: 0 | AC72: 17.7 | AD72: 609.411 | BZ72: Myntra Designs Pvt Ltd | CA72: 62082200 | CB72: Apparel | CD72: Chelvet | CE72: Women | CF72: Nightdress | CG72: ON_HAND | CH72: FALSE | CI72: MYSC1282904093 | CJ72: 6cf2a39c.c4a4.4bf7.a54d.a0f0554ea159aJt0KG5m5x | CK72: 411045 | CL72: MH | CM72: 18 | CN72: 0 | CO72: 0 | CP72: 2917.8 | CQ72: 0.5 | CR72: 0 | CS72: 0 | CT72: 0 | CU72: 0 | CW72: 0 | CX72: 09AALCG0172B1ZW | CZ72: UP | DA72: 0 | DB72: 0 | DC72: 0 | DD72: 29AAECM9636P1ZJ | DE72: 27477 | EB72: PPMP | EL72: ON_HAND | EM72: 3649 | EP72: 100034397768 | EQ72: dc0f0e8d-1577-4a81-934d-23d4565056d7 | ES72: 11089126717
A73: 100061237042 | B73: 1.3290878e+20 | C73: 2026-04-26T18:47:16.000+05:30 | D73: 46139.551 | E73: I0727GE000004848 | F73: CVETBRAA103716972 | G73: delivered | H73: 46145.479 | I73: 46142.936 | N73: INR | O73: 883 | P73: 883 | Q73: 0 | R73: 1849 | S73: 872 | T73: Inter-State | U73: 5 | V73: 42.05 | W73: 0 | X73: 0 | Y73: 4.20475 | Z73: 0 | AA73: 0 | AB73: 0 | AC73: 13.35 | AD73: 117.88 | BZ73: Myntra Designs Pvt Ltd | CA73: 62121000 | CB73: Apparel | CD73: Chelvet | CE73: Women | CF73: Bra | CG73: ON_HAND | CH73: FALSE | CI73: MYEC1099922984 | CJ73: 83a0f97c.cacd.4fc7.a20f.91c37d75fbaaIzwIW6gobY | CK73: 712601 | CL73: WB | CM73: 5 | CN73: 0 | CO73: 0 | CP73: 840.95 | CQ73: 0.5 | CR73: 0 | CS73: 0 | CT73: 0 | CU73: 0 | CW73: 31 | CX73: 07AALCG0172B1Z0 | CZ73: DL | DA73: 31 | DB73: 0 | DC73: 0 | DD73: 29AAECM9636P1ZJ | DE73: 27477 | EB73: PPMP | EL73: ON_HAND | EM73: 977 | EP73: 1000018117453 | EQ73: caf7002b-2df4-41c6-bbf2-83cb87c44870 | ES73: 11115966167
A74: 100038384567 | B74: 1.3279383e+20 | C74: 2026-04-13T11:28:37.000+05:30 | D74: 46125.496 | E74: I0727GE000002617 | F74: CVETBRAA103725208 | G74: delivered | H74: 46126.75 | I74: 46126.965 | N74: INR | O74: 811 | P74: 0 | Q74: 811 | R74: 1849 | S74: 944 | T74: Inter-State | U74: 5 | V74: 38.62 | W74: 0 | X74: 0 | Y74: 3.8619 | Z74: 0 | AA74: 0 | AB74: 0 | AC74: 12.86 | AD74: 104.295 | BZ74: Myntra Designs Pvt Ltd | CA74: 62121000 | CB74: Apparel | CD74: Chelvet | CE74: Women | CF74: Bra | CG74: ON_HAND | CH74: FALSE | CI74: MYSP1388029309 | CJ74: 1e3e59bf.1e96.4cc1.aa5a.c2a0c2fd490bQ2Ya8d0YD3 | CK74: 122022 | CL74: HR | CM74: 5 | CN74: 0 | CO74: 0 | CP74: 772.38 | CQ74: 0.5 | CR74: 0 | CS74: 0 | CT74: 0 | CU74: 0 | CW74: 0 | CX74: 07AALCG0172B1Z0 | CZ74: DL | DA74: 0 | DB74: 0 | DC74: 0 | DD74: 29AAECM9636P1ZJ | DE74: 27477 | EB74: PPMP | EL74: ON_HAND | EM74: 905 | EP74: 100038384567 | EQ74: 282cf006-dca3-4041-92a4-49d399fc2ed3 | ES74: 11093113523
A75: 100024654839 | B75: 1.3273387e+20 | C75: 2026-04-06T12:54:47.000+05:30 | D75: 46118.554 | E75: I0727GE000001268 | F75: CVETBRAA104595866 | G75: delivered | H75: 46122.479 | I75: 46121.924 | N75: INR | O75: 625 | P75: 0 | Q75: 625 | R75: 1499 | S75: 780 | T75: Inter-State | U75: 5 | V75: 29.76 | W75: 0 | X75: 0 | Y75: 2.9762 | Z75: 0 | AA75: 0 | AB75: 0 | AC75: 12.05 | AD75: 75.312 | BZ75: Myntra Designs Pvt Ltd | CA75: 62121000 | CB75: Apparel | CD75: Chelvet | CE75: Women | CF75: Bra | CG75: ON_HAND | CH75: FALSE | CI75: MYSP1384318385 | CJ75: 1bf1f751.2a92.4bf2.bf68.70ef0a1ab12aQW7SxbYoAb | CK75: 411014 | CL75: MH | CM75: 5 | CN75: 0 | CO75: 0 | CP75: 595.24 | CQ75: 0.5 | CR75: 0 | CS75: 0 | CT75: 0 | CU75: 0 | CW75: 0 | CX75: 07AALCG0172B1Z0 | CZ75: DL | DA75: 0 | DB75: 0 | DC75: 0 | DD75: 29AAECM9636P1ZJ | DE75: 27477 | EB75: PPMP | EL75: ON_HAND | EM75: 719 | EP75: 100024654839 | EQ75: 510e51cd-b7e1-4dec-8279-b266855b3fde | ES75: 11079383741
A76: 100066952474 | B76: 1.3294111e+20 | C76: 2026-04-30T12:35:00.000+05:30 | D76: 46142.534 | E76: I0727GE000005295 | F76: CVETBRAA103725209 | G76: delivered | H76: 46146.479 | I76: 46146.901 | N76: INR | O76: 811 | P76: 0 | Q76: 811 | R76: 1849 | S76: 944 | T76: Inter-State | U76: 5 | V76: 38.62 | W76: 0 | X76: 0 | Y76: 3.8619 | Z76: 0 | AA76: 0 | AB76: 0 | AC76: 12.86 | AD76: 104.295 | BZ76: Myntra Designs Pvt Ltd | CA76: 62121000 | CB76: Apparel | CD76: Chelvet | CE76: Women | CF76: Bra | CG76: ON_HAND | CH76: FALSE | CI76: MYSP1395621561 | CJ76: baf29512.44ac.450a.9d17.8233ead870e28BC4HsnQeW | CK76: 560068 | CL76: KA | CM76: 5 | CN76: 0 | CO76: 0 | CP76: 772.38 | CQ76: 0.5 | CR76: 0 | CS76: 0 | CT76: 0 | CU76: 0 | CW76: 0 | CX76: 07AALCG0172B1Z0 | CZ76: DL | DA76: 0 | DB76: 0 | DC76: 0 | DD76: 29AAECM9636P1ZJ | DE76: 27477 | EB76: PPMP | EL76: ON_HAND | EM76: 905 | EP76: 100066952474 | EQ76: 9fd41987-80ce-4d10-b354-cfee803d5aee | ES76: 11121681662
A77: 100046604276 | B77: 1.3283144e+20 | C77: 2026-04-17T19:57:35.000+05:30 | D77: 46130.447 | E77: I0727GE000003516 | F77: CVETBRAA103640774 | G77: reverse_in_transit | H77: 46134.479 | I77: 46134.687 | J77: 46147.593 | L77: return_refund | N77: INR | O77: 879 | P77: 0 | Q77: 879 | R77: 2099 | S77: 1126 | T77: Inter-State | U77: 5 | V77: 41.86 | W77: 0 | X77: 0 | Y77: 4.1857 | Z77: 0 | AA77: 0 | AB77: 0 | AC77: 13.02 | AD77: 114.446 | BZ77: Myntra Designs Pvt Ltd | CA77: 62121000 | CB77: Apparel | CD77: Chelvet | CE77: Women | CF77: Bra | CG77: ON_HAND | CH77: FALSE | CI77: MYSP1390285082 | CJ77: 6d3443fb.d463.481b.8f76.4f0c195baa0duRM5kMQCUg | CK77: 560103 | CL77: KA | CM77: 5 | CN77: 0 | CO77: 0 | CP77: 837.14 | CQ77: 0.5 | CR77: 0 | CS77: 0 | CT77: 0 | CU77: 0 | CW77: 0 | CX77: 07AALCG0172B1Z0 | CZ77: DL | DA77: 0 | DB77: 0 | DC77: 0 | DD77: 29AAECM9636P1ZJ | DE77: 27477 | EB77: PPMP | EL77: ON_HAND | EM77: 973 | EP77: 1000013704958 | EQ77: 6fb6bee9-71d8-40c6-9d6a-06dd4a2e0f70 | ES77: 11101333249 | ET77: DLS
A78: 100060121740 | B78: 1.3290271e+20 | C78: 2026-04-26T01:54:39.000+05:30 | D78: 46139.459 | E78: I0727GE000004702 | F78: CVETBRAA103722910 | G78: reverse_in_transit | H78: 46146.479 | I78: 46145.793 | J78: 46145.808 | L78: return_refund | N78: INR | O78: 525 | P78: 525 | Q78: 0 | R78: 1999 | S78: 1380 | T78: Inter-State | U78: 5 | V78: 25 | W78: 0 | X78: 0 | Y78: 2.5 | Z78: 0 | AA78: 0 | AB78: 0 | AC78: 8.65 | AD78: 45.413 | BZ78: Myntra Designs Pvt Ltd | CA78: 62121000 | CB78: Apparel | CD78: Chelvet | CE78: Women | CF78: Bra | CG78: ON_HAND | CH78: FALSE | CI78: MYSC1288551884 | CJ78: ef7f43f0.2b30.4450.96a5.8c4dc6e1adbdXthaCwm2WE | CK78: 781028 | CL78: AS | CM78: 5 | CN78: 0 | CO78: 0 | CP78: 500 | CQ78: 0.5 | CR78: 0 | CS78: 0 | CT78: 0 | CU78: 0 | CW78: 0 | CX78: 07AALCG0172B1Z0 | CZ78: DL | DA78: 0 | DB78: 0 | DC78: 0 | DD78: 29AAECM9636P1ZJ | DE78: 27477 | EB78: PPMP | EL78: ON_HAND | EM78: 619 | EP78: 100060121740 | EQ78: 247d4e15-1fd0-45c2-969d-577a3e1c9051 | ES78: 11114850844 | ET78: DLS
A79: 100065491647 | B79: 1.3293275e+20 | C79: 2026-04-29T13:21:25.000+05:30 | D79: 46141.592 | E79: I0927GE000000233 | F79: CVETBREF131490385 | G79: delivered | H79: 46145.479 | I79: 46144.797 | N79: INR | O79: 492 | P79: 0 | Q79: 492 | R79: 749 | S79: 163 | T79: Inter-State | U79: 5 | V79: 23.43 | W79: 0 | X79: 0 | Y79: 2.34285 | Z79: 0 | AA79: 0 | AB79: 0 | AC79: 8.26 | AD79: 40.639 | BZ79: Myntra Designs Pvt Ltd | CA79: 62121000 | CB79: Apparel | CD79: Chelvet | CE79: Women | CF79: Briefs | CG79: ON_HAND | CH79: FALSE | CI79: MYSP1395262478 | CJ79: 993155e1.e1be.467e.9764.a598995982a3cwM3sFiXVW | CK79: 342006 | CL79: RJ | CM79: 5 | CN79: 0 | CO79: 0 | CP79: 468.57 | CQ79: 0.5 | CR79: 0 | CS79: 0 | CT79: 0 | CU79: 0 | CW79: 0 | CX79: 09AALCG0172B1ZW | CZ79: UP | DA79: 0 | DB79: 0 | DC79: 0 | DD79: 29AAECM9636P1ZJ | DE79: 27477 | EB79: PPMP | EL79: ON_HAND | EM79: 586 | EP79: 100065491647 | EQ79: 8155549b-a145-474d-b7c1-843450a8dc55 | ES79: 11120220822
A80: 100038173100 | B80: 1.3279303e+20 | C80: 2026-04-13T09:16:01.000+05:30 | D80: 46125.464 | E80: I0727GE000002499 | F80: CVETBRAA104595890 | G80: delivered | H80: 46127.479 | I80: 46127.945 | N80: INR | O80: 625 | P80: 625 | Q80: 0 | R80: 1499 | S80: 780 | T80: Inter-State | U80: 5 | V80: 29.76 | W80: 0 | X80: 0 | Y80: 2.9762 | Z80: 0 | AA80: 0 | AB80: 0 | AC80: 12.05 | AD80: 75.312 | BZ80: Myntra Designs Pvt Ltd | CA80: 62121000 | CB80: Apparel | CD80: Chelvet | CE80: Women | CF80: Bra | CG80: ON_HAND | CH80: FALSE | CI80: MYSC1283573923 | CJ80: b15c9acf.0eac.4037.933d.1c90e0a933feM8gmrjGgBG | CK80: 282006 | CL80: UP | CM80: 5 | CN80: 0 | CO80: 0 | CP80: 595.24 | CQ80: 0.5 | CR80: 0 | CS80: 0 | CT80: 0 | CU80: 0 | CW80: 0 | CX80: 07AALCG0172B1Z0 | CZ80: DL | DA80: 0 | DB80: 0 | DC80: 0 | DD80: 29AAECM9636P1ZJ | DE80: 27477 | EB80: PPMP | EL80: ON_HAND | EM80: 719 | EP80: 100038173100 | EQ80: 345aef6b-f258-407c-a6a7-3d35220c3094 | ES80: 11092902055
A81: 100032672969 | B81: 1.3276918e+20 | C81: 2026-04-10T15:00:28.000+05:30 | D81: 46122.722 | E81: I0927GE000000079 | F81: CVETBRAA127431556 | G81: reverse_in_transit | H81: 46125.479 | I81: 46125.913 | J81: 46125.987 | L81: return_refund | N81: INR | O81: 1596 | P81: 1596 | Q81: 0 | R81: 2599 | S81: 832 | T81: Inter-State | U81: 5 | V81: 76 | W81: 0 | X81: 0 | Y81: 7.6 | Z81: 0 | AA81: 0 | AB81: 0 | AC81: 18.22 | AD81: 290.791 | BZ81: Myntra Designs Pvt Ltd | CA81: 62121000 | CB81: Apparel | CD81: Chelvet | CE81: Women | CF81: Bra | CG81: ON_HAND | CH81: FALSE | CI81: MYSC1282556151 | CJ81: 03fc398b.9f0c.4e85.98c0.f36d80d8e93dqal03IdeKq | CK81: 248013 | CL81: UT | CM81: 5 | CN81: 0 | CO81: 0 | CP81: 1520 | CQ81: 0.5 | CR81: 0 | CS81: 0 | CT81: 0 | CU81: 0 | CW81: 0 | CX81: 09AALCG0172B1ZW | CZ81: UP | DA81: 0 | DB81: 0 | DC81: 0 | DD81: 29AAECM9636P1ZJ | DE81: 27477 | EB81: PPMP | EL81: ON_HAND | EM81: 1767 | EP81: 100032672969 | EQ81: 1eeb64ca-f725-4bcb-80a1-683fdfe55712 | ES81: 11087401916 | ET81: DLS
A82: 100056974238 | B82: 1.3288734e+20 | C82: 2026-04-24T07:13:46.000+05:30 | D82: 46136.441 | E82: I0727GE000004411 | F82: CVETBRAA103722849 | G82: delivered | H82: 46140.479 | I82: 46140.722 | N82: INR | O82: 525 | P82: 0 | Q82: 525 | R82: 1999 | S82: 1380 | T82: Inter-State | U82: 5 | V82: 25 | W82: 0 | X82: 0 | Y82: 2.5 | Z82: 0 | AA82: 0 | AB82: 0 | AC82: 8.65 | AD82: 45.413 | BZ82: Myntra Designs Pvt Ltd | CA82: 62121000 | CB82: Apparel | CD82: Chelvet | CE82: Women | CF82: Bra | CG82: ON_HAND | CH82: FALSE | CI82: MYSP1392924618 | CJ82: f0c82891.9f9c.4a18.96b2.d26681bbdad80gLyhsFVcw | CK82: 800013 | CL82: BR | CM82: 5 | CN82: 0 | CO82: 0 | CP82: 500 | CQ82: 0.5 | CR82: 0 | CS82: 0 | CT82: 0 | CU82: 0 | CW82: 0 | CX82: 07AALCG0172B1Z0 | CZ82: DL | DA82: 0 | DB82: 0 | DC82: 0 | DD82: 29AAECM9636P1ZJ | DE82: 27477 | EB82: PPMP | EL82: ON_HAND | EM82: 619 | EP82: 100056974238 | EQ82: 5e4a728e-3a89-41aa-874b-97ce70405e9d | ES82: 11111703298
A83: 100014645005 | B83: 1.3269141e+20 | C83: 2026-04-01T14:59:13.000+05:30 | D83: 46113.683 | E83: I0927GE000000007 | F83: CVETBRAA127703248 | G83: reverse_in_transit | H83: 46120.479 | I83: 46118.811 | J83: 46119.047 | L83: return_refund | N83: INR | O83: 714 | P83: 0 | Q83: 713.99 | R83: 1499 | S83: 691 | T83: Inter-State | U83: 5 | V83: 34 | W83: 0 | X83: 0 | Y83: 3.4 | Z83: 0 | AA83: 0 | AB83: 0 | AC83: 15.89 | AD83: 113.455 | BZ83: Myntra Designs Pvt Ltd | CA83: 62121000 | CB83: Apparel | CD83: Chelvet | CE83: Women | CF83: Bra | CG83: ON_HAND | CH83: FALSE | CI83: MYSP1381735631 | CJ83: 0d4dff20.b483.4fe3.a957.4939f26b13a2mgQHH0TrnH | CK83: 560066 | CL83: KA | CM83: 5 | CN83: 0 | CO83: 0 | CP83: 680 | CQ83: 0.5 | CR83: 0 | CS83: 0 | CT83: 0 | CU83: 0 | CW83: 0 | CX83: 09AALCG0172B1ZW | CZ83: UP | DA83: 0 | DB83: 0 | DC83: 0 | DD83: 29AAECM9636P1ZJ | DE83: 27477 | EB83: PPMP | EL83: ON_HAND | EM83: 808.01 | EP83: 100014645005 | EQ83: ca4b3bb0-3e2b-4168-a298-447f4109d2dc | ES83: 11069373827 | ET83: DLS
A84: 100024851113 | B84: 1.3273457e+20 | C84: 2026-04-06T14:52:34.000+05:30 | D84: 46119.425 | E84: I0727GE000001358 | F84: CVETBRAA104553140 | G84: delivered | H84: 46124.479 | I84: 46125.95 | N84: INR | O84: 805 | P84: 805.01 | Q84: 0 | R84: 1699 | S84: 800 | T84: Inter-State | U84: 5 | V84: 38.33 | W84: 0 | X84: 0 | Y84: 3.83335 | Z84: 0 | AA84: 0 | AB84: 0 | AC84: 15.87 | AD84: 127.754 | BZ84: Myntra Designs Pvt Ltd | CA84: 62121000 | CB84: Apparel | CD84: Chelvet | CE84: Women | CF84: Bra | CG84: ON_HAND | CH84: FALSE | CI84: MYSC1281103201 | CJ84: 55a393c6.5147.44e4.9171.b3621321741cOM3e0Efd9C | CK84: 403101 | CL84: GA | CM84: 5 | CN84: 0 | CO84: 0 | CP84: 766.67 | CQ84: 0.5 | CR84: 0 | CS84: 0 | CT84: 0 | CU84: 0 | CW84: 0 | CX84: 07AALCG0172B1Z0 | CZ84: DL | DA84: 0 | DB84: 0 | DC84: 0 | DD84: 29AAECM9636P1ZJ | DE84: 27477 | EB84: PPMP | EL84: ON_HAND | EM84: 898.99 | EP84: 100024851113 | EQ84: abe2f730-820c-488f-8b9d-5d7542d22662 | ES84: 11079580015
A85: 100059947007 | B85: 1.3290187e+20 | C85: 2026-04-25T23:34:45.000+05:30 | D85: 46139.459 | E85: I0727GE000004703 | F85: CVETBRAA103717727 | G85: delivered | H85: 46143.479 | I85: 46143.802 | N85: INR | O85: 883 | P85: 883 | Q85: 0 | R85: 1849 | S85: 872 | T85: Inter-State | U85: 5 | V85: 42.05 | W85: 0 | X85: 0 | Y85: 4.20475 | Z85: 0 | AA85: 0 | AB85: 0 | AC85: 13.35 | AD85: 117.88 | BZ85: Myntra Designs Pvt Ltd | CA85: 62121000 | CB85: Apparel | CD85: Chelvet | CE85: Women | CF85: Bra | CG85: ON_HAND | CH85: FALSE | CI85: MYSC1288552581 | CJ85: 7b65cf16.d687.4e68.83b6.b396d118342euINybMcyhB | CK85: 560037 | CL85: KA | CM85: 5 | CN85: 0 | CO85: 0 | CP85: 840.95 | CQ85: 0.5 | CR85: 0 | CS85: 0 | CT85: 0 | CU85: 0 | CW85: 0 | CX85: 07AALCG0172B1Z0 | CZ85: DL | DA85: 0 | DB85: 0 | DC85: 0 | DD85: 29AAECM9636P1ZJ | DE85: 27477 | EB85: PPMP | EL85: ON_HAND | EM85: 977 | EP85: 100059947007 | EQ85: b922a59e-af80-47ec-9166-944eb66559b7 | ES85: 11114676110
A86: 100066892759 | B86: 1.3294087e+20 | C86: 2026-04-30T11:56:03.000+05:30 | D86: 46142.512 | E86: I0727GE000005292 | F86: CVETBRAA103718506 | G86: reverse_in_transit | H86: 46147.479 | L86: release_rto_refund | N86: INR | O86: 622 | P86: 0 | Q86: 622 | R86: 1749 | S86: 1033 | T86: Inter-State | U86: 5 | V86: 29.62 | W86: 0 | X86: 0 | Y86: 2.9619 | Z86: 0 | AA86: 0 | AB86: 0 | AC86: 11.79 | AD86: 73.334 | BZ86: Myntra Designs Pvt Ltd | CA86: 62121000 | CB86: Apparel | CD86: Chelvet | CE86: Women | CF86: Bra | CG86: ON_HAND | CH86: FALSE | CI86: MYSP1395604817 | CJ86: e744ce23.7a61.4a23.a793.ca6d75af5ad92oP7ychvqY | CK86: 400058 | CL86: MH | CM86: 5 | CN86: 0 | CO86: 0 | CP86: 592.38 | CQ86: 0.5 | CR86: 0 | CS86: 0 | CT86: 0 | CU86: 0 | CW86: 0 | CX86: 07AALCG0172B1Z0 | CZ86: DL | DA86: 0 | DB86: 0 | DC86: 0 | DD86: 29AAECM9636P1ZJ | DE86: 27477 | EB86: PPMP | EL86: ON_HAND | EM86: 716 | EP86: 100066892759 | EQ86: 3133215d-0303-42b3-8c21-5c74a3f969ff | ES86: 11121621946
A87: 100056466247 | B87: 1.3288355e+20 | C87: 2026-04-23T20:42:04.000+05:30 | D87: 46136.441 | E87: I0727GE000004413 | F87: CVETBRAA103646625 | G87: delivered | H87: 46139.75 | I87: 46139.741 | N87: INR | O87: 625 | P87: 0 | Q87: 625 | R87: 1499 | S87: 780 | T87: Inter-State | U87: 5 | V87: 29.76 | W87: 0 | X87: 0 | Y87: 2.9762 | Z87: 0 | AA87: 0 | AB87: 0 | AC87: 12.05 | AD87: 75.312 | BZ87: Myntra Designs Pvt Ltd | CA87: 62121000 | CB87: Apparel | CD87: Chelvet | CE87: Women | CF87: Bra | CG87: ON_HAND | CH87: FALSE | CI87: MYSP1392925084 | CJ87: 02952b6c.b274.49b4.bfc9.e90f480267ccop3YUWR7Un | CK87: 500011 | CL87: TG | CM87: 5 | CN87: 0 | CO87: 0 | CP87: 595.24 | CQ87: 0.5 | CR87: 0 | CS87: 0 | CT87: 0 | CU87: 0 | CW87: 0 | CX87: 07AALCG0172B1Z0 | CZ87: DL | DA87: 0 | DB87: 0 | DC87: 0 | DD87: 29AAECM9636P1ZJ | DE87: 27477 | EB87: PPMP | EL87: ON_HAND | EM87: 719 | EP87: 100056466247 | EQ87: d031178f-f4f1-4bdc-ac0b-f84144e5301a | ES87: 11111195306
A88: 100033534669 | B88: 1.3277217e+20 | C88: 2026-04-10T23:19:33.000+05:30 | D88: 46123.44 | E88: I0727GE000002322 | F88: CVETBRAA104553139 | G88: delivered | H88: 46127.479 | I88: 46127.966 | N88: INR | O88: 805 | P88: 0 | Q88: 805 | R88: 1699 | S88: 800 | T88: Inter-State | U88: 5 | V88: 38.33 | W88: 0 | X88: 0 | Y88: 3.83335 | Z88: 0 | AA88: 0 | AB88: 0 | AC88: 15.87 | AD88: 127.754 | BZ88: Myntra Designs Pvt Ltd | CA88: 62121000 | CB88: Apparel | CD88: Chelvet | CE88: Women | CF88: Bra | CG88: ON_HAND | CH88: FALSE | CI88: MYEP1114030350 | CJ88: cd2b2756.45ed.42fe.9002.8f36dfbc85538OZfgdRGf9 | CK88: 403527 | CL88: GA | CM88: 5 | CN88: 0 | CO88: 0 | CP88: 766.67 | CQ88: 0.5 | CR88: 0 | CS88: 0 | CT88: 0 | CU88: 0 | CW88: 0 | CX88: 07AALCG0172B1Z0 | CZ88: DL | DA88: 0 | DB88: 0 | DC88: 0 | DD88: 29AAECM9636P1ZJ | DE88: 27477 | EB88: PPMP | EL88: ON_HAND | EM88: 899 | EP88: 100033534669 | EQ88: 372e9de3-f8d2-49da-9a42-3cfd29988388 | ES88: 11088263616
A89: 100049037328 | B89: 1.3284225e+20 | C89: 2026-04-19T01:59:23.000+05:30 | D89: 46132.442 | E89: I0927GE000000157 | F89: CVETBRAA120951104 | G89: delivered | H89: 46136.479 | I89: 46134.966 | N89: INR | O89: 1146 | P89: 0 | Q89: 1146 | R89: 2540 | S89: 1223 | T89: Inter-State | U89: 5 | V89: 54.57 | W89: 0 | X89: 0 | Y89: 5.45715 | Z89: 0 | AA89: 0 | AB89: 0 | AC89: 23.6 | AD89: 270.456 | BZ89: Myntra Designs Pvt Ltd | CA89: 62121000 | CB89: Apparel | CD89: Chelvet | CE89: Women | CF89: Bra | CG89: ON_HAND | CH89: FALSE | CI89: MYSP1391187870 | CJ89: 95999d79.f499.4647.9d34.65a9d4224494uq9SUXmBbP | CK89: 380061 | CL89: GJ | CM89: 5 | CN89: 0 | CO89: 0 | CP89: 1091.43 | CQ89: 0.5 | CR89: 0 | CS89: 0 | CT89: 0 | CU89: 0 | CW89: 0 | CX89: 09AALCG0172B1ZW | CZ89: UP | DA89: 0 | DB89: 0 | DC89: 0 | DD89: 29AAECM9636P1ZJ | DE89: 27477 | EB89: PPMP | EL89: ON_HAND | EM89: 1317 | EP89: 100049037328 | EQ89: b2be5102-39dd-49fd-a5e6-da36ad58bbb7 | ES89: 11103766319
A90: 100065900775 | B90: 1.329346e+20 | C90: 2026-04-29T18:29:42.000+05:30 | D90: 46142.435 | E90: I0727GE000005233 | F90: CVETBRAA103722769 | G90: delivered | H90: 46147.479 | I90: 46147.019 | N90: INR | O90: 525 | P90: 0 | Q90: 525 | R90: 1999 | S90: 1380 | T90: Inter-State | U90: 5 | V90: 25 | W90: 0 | X90: 0 | Y90: 2.5 | Z90: 0 | AA90: 0 | AB90: 0 | AC90: 8.65 | AD90: 45.413 | BZ90: Myntra Designs Pvt Ltd | CA90: 62121000 | CB90: Apparel | CD90: Chelvet | CE90: Women | CF90: Bra | CG90: ON_HAND | CH90: FALSE | CI90: MYSP1395521764 | CJ90: 5e531aba.ac22.44d7.98a7.deb28de83a211JKZQ2l8my | CK90: 400053 | CL90: MH | CM90: 5 | CN90: 0 | CO90: 0 | CP90: 500 | CQ90: 0.5 | CR90: 0 | CS90: 0 | CT90: 0 | CU90: 0 | CW90: 0 | CX90: 07AALCG0172B1Z0 | CZ90: DL | DA90: 0 | DB90: 0 | DC90: 0 | DD90: 29AAECM9636P1ZJ | DE90: 27477 | EB90: PPMP | EL90: ON_HAND | EM90: 619 | EP90: 100065900775 | EQ90: 23466073-1945-4eaf-8923-8eef5241a72e | ES90: 11120629952
A91: 100016739033 | B91: 1.3270001e+20 | C91: 2026-04-02T14:52:04.000+05:30 | D91: 46114.623 | E91: I0927GE000000014 | F91: CVETBRAA127703230 | G91: reverse_in_transit | H91: 46119.479 | I91: 46119.813 | J91: 46122.076 | L91: return_refund | N91: INR | O91: 714 | P91: 0 | Q91: 714 | R91: 1499 | S91: 691 | T91: Inter-State | U91: 5 | V91: 34 | W91: 0 | X91: 0 | Y91: 3.4 | Z91: 0 | AA91: 0 | AB91: 0 | AC91: 15.89 | AD91: 113.455 | BZ91: Myntra Designs Pvt Ltd | CA91: 62121000 | CB91: Apparel | CD91: Chelvet | CE91: Women | CF91: Bra | CG91: ON_HAND | CH91: FALSE | CI91: MYSP1382222436 | CJ91: 86f14941.276e.43da.9d1e.4400e2ed8583LCt69nzCtk | CK91: 560068 | CL91: KA | CM91: 5 | CN91: 0 | CO91: 0 | CP91: 680 | CQ91: 0.5 | CR91: 0 | CS91: 0 | CT91: 0 | CU91: 0 | CW91: 0 | CX91: 09AALCG0172B1ZW | CZ91: UP | DA91: 0 | DB91: 0 | DC91: 0 | DD91: 29AAECM9636P1ZJ | DE91: 27477 | EB91: PPMP | EL91: ON_HAND | EM91: 808 | EP91: 100016739033 | EQ91: f51a9e45-3c09-4eb0-a5e8-9adb701fcddf | ES91: 11071467872 | ET91: DLS
A92: 100062098944 | B92: 1.3291408e+20 | C92: 2026-04-27T09:30:17.000+05:30 | D92: 46139.558 | E92: I0727GE000004876 | F92: CVETBRAA104595885 | G92: delivered | H92: 46144.479 | I92: 46143.775 | N92: INR | O92: 625 | P92: 0 | Q92: 624.99 | R92: 1499 | S92: 780 | T92: Inter-State | U92: 5 | V92: 29.76 | W92: 0 | X92: 0 | Y92: 2.9762 | Z92: 0 | AA92: 0 | AB92: 0 | AC92: 12.05 | AD92: 75.312 | BZ92: Myntra Designs Pvt Ltd | CA92: 62121000 | CB92: Apparel | CD92: Chelvet | CE92: Women | CF92: Bra | CG92: ON_HAND | CH92: FALSE | CI92: MYSP1394390734 | CJ92: 90c07133.382b.45ea.96e8.63a1892de4810HpFM8CVmf | CK92: 560034 | CL92: KA | CM92: 5 | CN92: 0 | CO92: 0 | CP92: 595.24 | CQ92: 0.5 | CR92: 0 | CS92: 0 | CT92: 0 | CU92: 0 | CW92: 0 | CX92: 07AALCG0172B1Z0 | CZ92: DL | DA92: 0 | DB92: 0 | DC92: 0 | DD92: 29AAECM9636P1ZJ | DE92: 27477 | EB92: PPMP | EL92: ON_HAND | EM92: 719.01 | EP92: 1000018121905 | EQ92: 3626c190-f207-4614-a06b-e62ed12ca6c5 | ES92: 11116828072
A93: 100046018088 | B93: 1.3282914e+20 | C93: 2026-04-17T13:34:25.000+05:30 | D93: 46129.612 | E93: I0927GE000000137 | F93: CVETLNGR130560805 | G93: reverse_in_transit | H93: 46135.979 | L93: release_rto_refund | N93: INR | O93: 2569 | P93: 0 | Q93: 2569 | R93: 3500 | S93: 701 | T93: Intra-State | U93: 5 | V93: 0 | W93: 61.17 | X93: 61.17 | Y93: 0 | Z93: 6.11665 | AA93: 6.11665 | AB93: 0 | AC93: 17.7 | AD93: 454.713 | BZ93: Myntra Designs Pvt Ltd | CA93: 62121000 | CB93: Apparel | CD93: Chelvet | CE93: Women | CF93: Lingerie Set | CG93: ON_HAND | CH93: FALSE | CI93: SF2967442965F | CJ93: c5bf405a.594d.4a93.8bbe.4cdb6a8dcd42P8AGvZB18t | CK93: 202137 | CL93: UP | CM93: 0 | CN93: 2.5 | CO93: 2.5 | CP93: 2446.66 | CQ93: 0 | CR93: 0.25 | CS93: 0.25 | CT93: 0 | CU93: 0 | CW93: 0 | CX93: 09AALCG0172B1ZW | CZ93: UP | DA93: 0 | DB93: 0 | DC93: 0 | DD93: 29AAECM9636P1ZJ | DE93: 27477 | EB93: PPMP | EL93: ON_HAND | EM93: 2799 | EP93: 100046018088 | EQ93: d9f55ee2-b982-4e7a-96b7-7680daa6453a | ES93: 11100747055
A94: 100054793280 | B94: 1.3287419e+20 | C94: 2026-04-22T18:41:44.000+05:30 | D94: 46135.436 | E94: I0927GE000000192 | F94: CVETBRAA127703241 | G94: delivered | H94: 46138.75 | I94: 46139.856 | N94: INR | O94: 751 | P94: 711.65027 | Q94: 39.349734 | R94: 1499 | S94: 654 | T94: Inter-State | U94: 5 | V94: 35.76 | W94: 0 | X94: 0 | Y94: 3.5762 | Z94: 0 | AA94: 0 | AB94: 0 | AC94: 20.06 | AD94: 150.651 | BZ94: Myntra Designs Pvt Ltd | CA94: 62121000 | CB94: Apparel | CD94: Chelvet | CE94: Women | CF94: Bra | CG94: ON_HAND | CH94: FALSE | CI94: MYSC1287178034 | CJ94: 4bc46628.8f42.4854.b750.9ed52c450abbDZQkGJreCt | CK94: 500004 | CL94: TG | CM94: 5 | CN94: 0 | CO94: 0 | CP94: 715.24 | CQ94: 0.5 | CR94: 0 | CS94: 0 | CT94: 0 | CU94: 0 | CW94: 0 | CX94: 09AALCG0172B1ZW | CZ94: UP | DA94: 0 | DB94: 0 | DC94: 0 | DD94: 29AAECM9636P1ZJ | DE94: 27477 | EB94: PPMP | EL94: ON_HAND | EM94: 845 | EP94: 100054793280 | EQ94: 8ca9b179-e8e8-43c7-bbd8-7c7b91e2d8eb | ES94: 11109522326
A95: 100034153082 | B95: 1.3277644e+20 | C95: 2026-04-11T11:10:21.000+05:30 | D95: 46123.559 | E95: I0727GE000002389 | F95: CVETBRAA104595888 | G95: reverse_in_transit | H95: 46125.479 | I95: 46124.713 | J95: 46124.769 | L95: return_refund | N95: INR | O95: 625 | P95: 0 | Q95: 625 | R95: 1499 | S95: 780 | T95: Inter-State | U95: 5 | V95: 29.76 | W95: 0 | X95: 0 | Y95: 2.9762 | Z95: 0 | AA95: 0 | AB95: 0 | AC95: 12.05 | AD95: 75.312 | BZ95: Myntra Designs Pvt Ltd | CA95: 62121000 | CB95: Apparel | CD95: Chelvet | CE95: Women | CF95: Bra | CG95: ON_HAND | CH95: FALSE | CI95: MYSP1386999955 | CJ95: 69f13196.38b9.43b8.a4c3.286b96684d81MbIXuJmbLV | CK95: 201305 | CL95: UP | CM95: 5 | CN95: 0 | CO95: 0 | CP95: 595.24 | CQ95: 0.5 | CR95: 0 | CS95: 0 | CT95: 0 | CU95: 0 | CW95: 0 | CX95: 07AALCG0172B1Z0 | CZ95: DL | DA95: 0 | DB95: 0 | DC95: 0 | DD95: 29AAECM9636P1ZJ | DE95: 27477 | EB95: PPMP | EL95: ON_HAND | EM95: 719 | EP95: 1000009791516 | EQ95: 748872af-7837-4870-8476-0f1081e92f8c | ES95: 11088882030 | ET95: DLS
A96: 100034948034 | B96: 1.3277903e+20 | C96: 2026-04-11T18:22:11.000+05:30 | D96: 46125.481 | E96: I0727GE000002614 | F96: CVETBRAA103725642 | G96: delivered | H96: 46129.479 | I96: 46129.811 | N96: INR | O96: 843 | P96: 0 | Q96: 843 | R96: 1749 | S96: 812 | T96: Inter-State | U96: 5 | V96: 40.14 | W96: 0 | X96: 0 | Y96: 4.0143 | Z96: 0 | AA96: 0 | AB96: 0 | AC96: 13.3 | AD96: 112.119 | BZ96: Myntra Designs Pvt Ltd | CA96: 62121000 | CB96: Apparel | CD96: Chelvet | CE96: Women | CF96: Bra | CG96: ON_HAND | CH96: FALSE | CI96: MYSP1388003581 | CJ96: 77be1195.2585.45fc.851d.946cd092f02bSghERR3Wp1 | CK96: 560092 | CL96: KA | CM96: 5 | CN96: 0 | CO96: 0 | CP96: 802.86 | CQ96: 0.5 | CR96: 0 | CS96: 0 | CT96: 0 | CU96: 0 | CW96: 0 | CX96: 07AALCG0172B1Z0 | CZ96: DL | DA96: 0 | DB96: 0 | DC96: 0 | DD96: 29AAECM9636P1ZJ | DE96: 27477 | EB96: PPMP | EL96: ON_HAND | EM96: 937 | EP96: 1000010959035 | EQ96: 689ea6f8-26ee-41eb-a935-8538fd42fffc | ES96: 11089676983
A97: 100065502609 | B97: 1.3293279e+20 | C97: 2026-04-29T13:29:14.000+05:30 | D97: 46142.436 | E97: I0727GE000005235 | F97: CVETBRAA104595890 | G97: delivered | H97: 46148.479 | I97: 46147.934 | N97: INR | O97: 625 | P97: 0 | Q97: 625 | R97: 1499 | S97: 780 | T97: Inter-State | U97: 5 | V97: 29.76 | W97: 0 | X97: 0 | Y97: 2.9762 | Z97: 0 | AA97: 0 | AB97: 0 | AC97: 12.05 | AD97: 75.312 | BZ97: Myntra Designs Pvt Ltd | CA97: 62121000 | CB97: Apparel | CD97: Chelvet | CE97: Women | CF97: Bra | CG97: ON_HAND | CH97: FALSE | CI97: MYSP1395522355 | CJ97: ebf3c983.a560.4a18.87c7.31389fbc5474AEBOeh1Ici | CK97: 700036 | CL97: WB | CM97: 5 | CN97: 0 | CO97: 0 | CP97: 595.24 | CQ97: 0.5 | CR97: 0 | CS97: 0 | CT97: 0 | CU97: 0 | CW97: 0 | CX97: 07AALCG0172B1Z0 | CZ97: DL | DA97: 0 | DB97: 0 | DC97: 0 | DD97: 29AAECM9636P1ZJ | DE97: 27477 | EB97: PPMP | EL97: ON_HAND | EM97: 719 | EP97: 100065502609 | EQ97: cd18453f-bbb6-4205-863e-afe069b18672 | ES97: 11120231784
A98: 100044414460 | B98: 1.3282146e+20 | C98: 2026-04-16T16:14:03.000+05:30 | D98: 46129.454 | E98: I0727GE000003357 | F98: CVETBRAA103722496 | G98: delivered | H98: 46132.479 | I98: 46131.966 | N98: INR | O98: 805 | P98: 805 | Q98: 0 | R98: 1699 | S98: 800 | T98: Inter-State | U98: 5 | V98: 38.33 | W98: 0 | X98: 0 | Y98: 3.83335 | Z98: 0 | AA98: 0 | AB98: 0 | AC98: 15.87 | AD98: 127.754 | BZ98: Myntra Designs Pvt Ltd | CA98: 62121000 | CB98: Apparel | CD98: Chelvet | CE98: Women | CF98: Bra | CG98: ON_HAND | CH98: FALSE | CI98: MYSC1285127071 | CJ98: 2a8f8b18.048e.4e26.adfa.9a496fb24cd7psje25TPKC | CK98: 380006 | CL98: GJ | CM98: 5 | CN98: 0 | CO98: 0 | CP98: 766.67 | CQ98: 0.5 | CR98: 0 | CS98: 0 | CT98: 0 | CU98: 0 | CW98: 0 | CX98: 07AALCG0172B1Z0 | CZ98: DL | DA98: 0 | DB98: 0 | DC98: 0 | DD98: 29AAECM9636P1ZJ | DE98: 27477 | EB98: PPMP | EL98: ON_HAND | EM98: 899 | EP98: 100044414460 | EQ98: 53506462-3338-4929-ae89-5b4a576eaa88 | ES98: 11099143426
A99: 100045517758 | B99: 1.3282689e+20 | C99: 2026-04-17T07:18:44.000+05:30 | D99: 46129.433 | E99: I0927GE000000128 | F99: CVETBRAA127713150 | G99: delivered | H99: 46136.479 | I99: 46135.957 | N99: INR | O99: 998 | P99: 0 | Q99: 998 | R99: 2999 | S99: 1830 | T99: Inter-State | U99: 5 | V99: 47.52 | W99: 0 | X99: 0 | Y99: 4.7524 | Z99: 0 | AA99: 0 | AB99: 0 | AC99: 14.2 | AD99: 141.716 | BZ99: Myntra Designs Pvt Ltd | CA99: 62121000 | CB99: Apparel | CD99: Chelvet | CE99: Women | CF99: Bra | CG99: ON_HAND | CH99: FALSE | CI99: MYSP1389820419 | CJ99: e538c5fb.9995.4993.b7ca.d179fcaac3afTyNKq862Nb | CK99: 782435 | CL99: AS | CM99: 5 | CN99: 0 | CO99: 0 | CP99: 950.48 | CQ99: 0.5 | CR99: 0 | CS99: 0 | CT99: 0 | CU99: 0 | CW99: 0 | CX99: 09AALCG0172B1ZW | CZ99: UP | DA99: 0 | DB99: 0 | DC99: 0 | DD99: 29AAECM9636P1ZJ | DE99: 27477 | EB99: PPMP | EL99: ON_HAND | EM99: 1169 | EP99: 100045517758 | EQ99: 591261a1-ae54-41ca-9e6d-8bedb0b2b1dd | ES99: 11100246725
A100: 100049979980 | B100: 1.3284757e+20 | C100: 2026-04-19T16:46:02.000+05:30 | D100: 46132.438 | E100: I0927GE000000152 | F100: CVETBRAA127703228 | G100: reverse_in_transit | H100: 46133.75 | I100: 46133.864 | J100: 46134.177 | L100: return_refund | N100: INR | O100: 751 | P100: 0 | Q100: 751 | R100: 1499 | S100: 654 | T100: Inter-State | U100: 5 | V100: 35.76 | W100: 0 | X100: 0 | Y100: 3.5762 | Z100: 0 | AA100: 0 | AB100: 0 | AC100: 20.06 | AD100: 150.651 | BZ100: Myntra Designs Pvt Ltd | CA100: 62121000 | CB100: Apparel | CD100: Chelvet | CE100: Women | CF100: Bra | CG100: ON_HAND | CH100: FALSE | CI100: MYSP1391178154 | CJ100: 356193d0.fffe.424f.aa18.5dde6f3fba235BQDfwxaiq | CK100: 122002 | CL100: HR | CM100: 5 | CN100: 0 | CO100: 0 | CP100: 715.24 | CQ100: 0.5 | CR100: 0 | CS100: 0 | CT100: 0 | CU100: 0 | CW100: 0 | CX100: 09AALCG0172B1ZW | CZ100: UP | DA100: 0 | DB100: 0 | DC100: 0 | DD100: 29AAECM9636P1ZJ | DE100: 27477 | EB100: PPMP | EL100: ON_HAND | EM100: 845 | EP100: 100049979980 | EQ100: c792b5f1-80a2-4e94-a3c2-c8f71c2572d9 | ES100: 11104708988 | ET100: DLS
...

Sheet Table
A1: Brand | B1: Channel Name | C1: Total Order Count | D1: Delivered Count | E1: RTO Count | F1: Total Order | G1: Delivered | H1: RTO
A2: Chelvet | B2: Myntra | C2: 448 | D2: 262 | E2: 187 | F2: 410226 | G2: 227165 | H2: 183061
A3: Chelvet | B3: Nykaa | C3: 225 | D3: 142 | E3: 57 | F3: 421880 | G3: 267848 | H3: 101239
A4: Chelvet | B4: Shopify | C4: 327 | D4: 272 | E4: 55 | F4: 489379 | G4: 409522 | H4: 79857
A5: Chelvet | B5: Tatacliq | C5: 7 | D5: 5 | E5: 2 | F5: 5154 | G5: 3678 | H5: 1476
A6: Chelvet | B6: Flipkart | C6: 3 | D6: 2 | E6: 1 | F6: 4245 | G6: 930 | H6: 3315

Sheet flipkart 
A1: qty | B1: Category | C1: Shipping Method | D1: Item SKU Code | E1: Channel Product Id | F1: Item Type Name | G1: Item Type Color | H1: Item Type Size | I1: Item Type Brand | J1: Channel Name | K1: SKU Require Customization | L1: Gift Wrap | M1: Gift Message | N1: HSN Code | O1: MRP | P1: Total Price | Q1: Selling Price | R1: Cost Price | S1: Prepaid Amount | T1: Subtotal | U1: Discount | V1: GST Tax Type Code | W1: CGST | X1: IGST | Y1: SGST | Z1: UTGST | AA1: CESS | AB1: CGST Rate | AC1: IGST Rate | AD1: SGST Rate | AE1: UTGST Rate | AF1: CESS Rate | AG1: TCS Amount | AH1: Tax % | AI1: Tax Value | AJ1: Voucher Code | AK1: Shipping Charges | AL1: Shipping Method Charges | AM1: COD Service Charges | AN1: Gift Wrap Charges | AO1: Packet Number | AP1: Order Date as dd/mm/yyyy hh:MM:ss | AQ1: Sale Order Code | AR1: On Hold | AS1: Sale Order Status | AT1: Priority | AU1: Currency | AV1: Currency Conversion Rate | AW1: Sale Order Item Status | AX1: Cancellation Reason | AY1: Shipping provider | AZ1: Shipping Courier | BA1: Shipping Arranged By | BB1: Shipping Package Code | BC1: Shipping Package Creation Date | BD1: Shipping Package Status Code | BE1: Shipping Package Type | BF1: Length(mm) | BG1: Width(mm) | BH1: Height(mm) | BI1: Delivery Time | BJ1: Tracking Number | BK1: Dispatch Date | BL1: Facility | BM1: Return Date | BN1: Return Reason | BO1: Return Remarks | BP1: Created | BQ1: Updated | BR1: Combination Identifier | BS1: Combination Description | BT1: Transfer Price | BU1: Item Code | BV1: IMEI | BW1: Weight | BX1: GSTIN | BY1: Customer GSTIN | BZ1: TIN | CA1: Payment Instrument | CB1: Fulfillment TAT | CC1: Adjustment In Selling Price | CD1: Adjustment In Discount | CE1: Store Credit | CF1: IRN | CG1: Acknowledgement Number | CH1: Bundle SKU Code Number | CI1: SKU Name | CJ1: Batch Code | CK1: Vendor Batch Number | CL1: Seller SKU Code | CM1: Item Type EAN | CN1: Shipping Courier Status | CO1: Shipping Tracking Status | CP1: Item Seal Id | CQ1: Parent Sale Order Code | CR1: Item Tag | CS1: Shipment Tag | CT1: Channel Shipping | CU1: Item Details
A2: 1 | B2: Nightwear | C2: STD | D2: RB-RED-CHV021-M | E2: LSTNDNHGA74YHPPFS3DYWGEWR | F2: Night Wear Robe | G2: RED | H2: M | I2: Chelvet | J2: FLIPKART noida | K2: FALSE | L2: FALSE | N2: 6208 | O2: 6899 | P2: 3315 | Q2: 3315 | R2: 1524 | S2: 0 | T2: 2809.32 | U2: 0 | V2: 5_18_slab | W2: 0 | X2: 505.68 | Y2: 0 | Z2: 0 | AA2: 0 | AB2: 0 | AC2: 18 | AD2: 0 | AE2: 0 | AF2: 0 | AG2: 0 | AK2: 0 | AL2: 0 | AM2: 0 | AN2: 0 | AO2: 1 | AP2: 46127.876 | AQ2: 5c0e93d7-89d9-4bec-a100-408996660945 | AR2: FALSE | AS2: COMPLETE | AT2: 0 | AU2: INR | AV2: 1 | AW2: DISPATCHED | AY2: E-Kart Logistics | BA2: Channel | BB2: GOTC-N-00990 | BC2: 46127.885 | BD2: RETURN_EXPECTED | BE2: DEFAULT | BF2: 200 | BG2: 60 | BH2: 10 | BJ2: FMPC5993399490 | BK2: 46128.445 | BL2: GotchaNoida | BP2: 46127.883 | BQ2: 46128.445 | BU2: 1316 | BW2: 400 | BX2: 09AALCG0172B1ZW | CB2: 46128.5 | CC2: 0 | CD2: 0 | CE2: 0 | CI2: Night Wear Robe | CL2: RB-RED-CHV021-M | CN2: COURIER_RETURN-DELIVERED | CO2: RTO_DELIVERED_TO_SELLER | CT2: TRUE
A3: 1 | B3: Bra | C3: STD | D3: BRA-CH01-ROSE-34C | E3: LSTBRAHBKDXYX2GAHGHYWGIFJ | F3: Women Full Coverage Lightly Padded Bra Seamless & Non-Wired | G3: ROSE | H3: 34C | I3: Chelvet | J3: FLIPKART CHHAWLA | K3: FALSE | L3: FALSE | N3: 62121000 | O3: 1299 | P3: 610 | Q3: 610 | R3: 207 | S3: 0 | T3: 580.95 | U3: 0 | V3: 5_18_slab | W3: 0 | X3: 29.05 | Y3: 0 | Z3: 0 | AA3: 0 | AB3: 0 | AC3: 5 | AD3: 0 | AE3: 0 | AF3: 0 | AG3: 0 | AK3: 0 | AL3: 0 | AM3: 0 | AN3: 0 | AO3: 1 | AP3: 46118.352 | AQ3: 3a3daf41-7e95-418e-a7d6-825ccbfadec8 | AR3: FALSE | AS3: CANCELLED | AT3: 0 | AU3: INR | AV3: 1 | AW3: CANCELLED | AY3: E-Kart Logistics | BA3: Channel | BB3: GOTC12279 | BC3: 46118.356 | BD3: SHIPPED | BE3: DEFAULT | BF3: 180 | BG3: 170 | BH3: 60 | BJ3: FMPC5957195346 | BK3: 46118.543 | BL3: Gotcha Chhawla | BN3: SIZE_FIT_ISSUES | BP3: 46118.355 | BQ3: 46130.618 | BU3: 7 | BW3: 200 | CB3: 46118.542 | CC3: 0 | CD3: 0 | CE3: 0 | CI3: Women Full Coverage Lightly Padded Bra Seamless & Non-Wired | CL3: BRA-CH01-ROSE-34C | CN3: SHIPPED | CO3: STATUS_NOT_DEFINED | CT3: TRUE
A4: 1 | B4: Bra | C4: STD | D4: BRA-CH28-PRT2-36D | E4: LSTBRAHCFFSZFFE37HUPJWWJK | F4: Women Full Coverage Lightly Padded Bra Seamless & Non Wired | G4: BLUE | H4: 36D | I4: Chelvet | J4: FLIPKART CHHAWLA | K4: FALSE | L4: FALSE | N4: 62121000 | O4: 1299 | P4: 429 | Q4: 429 | R4: 207 | S4: 0 | T4: 442.57 | U4: 34 | V4: 5_18_slab | W4: 0 | X4: 20.43 | Y4: 0 | Z4: 0 | AA4: 0 | AB4: 0 | AC4: 5 | AD4: 0 | AE4: 0 | AF4: 0 | AG4: 0 | AK4: 0 | AL4: 0 | AM4: 0 | AN4: 0 | AO4: 1 | AP4: 46135.697 | AQ4: e3e43846-1949-48d0-89f6-286868e65c68 | AR4: FALSE | AS4: CANCELLED | AT4: 0 | AU4: INR | AV4: 1 | AW4: CANCELLED | AY4: E-Kart Logistics | BA4: Channel | BB4: GOTC15666 | BC4: 46135.704 | BD4: DELIVERED | BE4: DEFAULT | BF4: 180 | BG4: 170 | BH4: 60 | BI4: 46137.319 | BJ4: FMPP3943222663 | BK4: 46136.43 | BL4: Gotcha Chhawla | BN4: SIZE_FIT_ISSUES | BP4: 46135.703 | BQ4: 46148.762 | BU4: GOT038455 | BW4: 200 | CB4: 46136.542 | CC4: 0 | CD4: 0 | CE4: 0 | CI4: Women Full Coverage Lightly Padded Bra Seamless & Non Wired | CL4: BRA-CH28-PRT2-36D | CN4: DELIVERED | CO4: STATUS_NOT_DEFINED | CT4: TRUE
A5: 1 | B5: Bra | C5: STD | D5: BRA-CH07-LTGR-36D | E5: LSTBRAHBTF5S4SSVCNPTBINIU | F5: Women Bra Full Coverage Lightly Padded | G5: LT GREEN | H5: 36D | I5: Chelvet | J5: FLIPKART CHHAWLA | K5: FALSE | L5: FALSE | N5: 62121000 | O5: 1299 | P5: 508 | Q5: 508 | R5: 207 | S5: 0 | T5: 530.81 | U5: 47 | V5: 5_18_slab | W5: 0 | X5: 24.19 | Y5: 0 | Z5: 0 | AA5: 0 | AB5: 0 | AC5: 5 | AD5: 0 | AE5: 0 | AF5: 0 | AG5: 0 | AK5: 0 | AL5: 0 | AM5: 0 | AN5: 0 | AO5: 1 | AP5: 46136.96 | AQ5: bc3db6f3-53a9-431c-9e5d-20f447aaffbf | AR5: FALSE | AS5: COMPLETE | AT5: 0 | AU5: INR | AV5: 1 | AW5: DELIVERED | AY5: E-Kart Logistics | BA5: Channel | BB5: GOTC15867 | BC5: 46136.966 | BD5: DELIVERED | BE5: DEFAULT | BF5: 180 | BG5: 170 | BH5: 60 | BI5: 46137.981 | BJ5: FMPP3946435543 | BK5: 46137.454 | BL5: Gotcha Chhawla | BP5: 46136.966 | BQ5: 46139.51 | BU5: GOT065628 | BW5: 200 | CB5: 46137.542 | CC5: 0 | CD5: 0 | CE5: 0 | CI5: Women Bra Full Coverage Lightly Padded | CL5: BRA-CH07-LTGR-36D | CN5: DELIVERED | CO5: STATUS_NOT_DEFINED | CT5: TRUE
A6: 1 | B6: Bra | C6: STD | D6: BRA-CH28-PRT2-34B | E6: LSTBRAHCFFS7G2DWYFFJI6AHM | F6: Women Full Coverage Lightly Padded Bra Seamless & Non Wired | G6: BLUE | H6: 34B | I6: Chelvet | J6: FLIPKART CHHAWLA | K6: FALSE | L6: FALSE | N6: 62121000 | O6: 1299 | P6: 422 | Q6: 422 | R6: 207 | S6: 0 | T6: 464.9 | U6: 63 | V6: 5_18_slab | W6: 0 | X6: 20.1 | Y6: 0 | Z6: 0 | AA6: 0 | AB6: 0 | AC6: 5 | AD6: 0 | AE6: 0 | AF6: 0 | AG6: 0 | AK6: 0 | AL6: 0 | AM6: 0 | AN6: 0 | AO6: 1 | AP6: 46138.852 | AQ6: 72fdc996-3f22-4dbd-a323-d49d26fb066e | AR6: FALSE | AS6: COMPLETE | AT6: 0 | AU6: INR | AV6: 1 | AW6: DELIVERED | AY6: E-Kart Logistics | BA6: Channel | BB6: GOTC16164 | BC6: 46138.857 | BD6: DELIVERED | BE6: DEFAULT | BF6: 180 | BG6: 170 | BH6: 60 | BI6: 46139.931 | BJ6: FMPP3950887700 | BK6: 46139.49 | BL6: Gotcha Chhawla | BP6: 46138.856 | BQ6: 46141.688 | BU6: GOT038698 | BW6: 200 | CB6: 46139.542 | CC6: 0 | CD6: 0 | CE6: 0 | CI6: Women Full Coverage Lightly Padded Bra Seamless & Non Wired | CL6: BRA-CH28-PRT2-34B | CN6: DELIVERED | CO6: STATUS_NOT_DEFINED | CT6: TRUE

Sheet tatacliq
A1: qty | B1: Category | C1: Shipping Method | D1: Item SKU Code | E1: Channel Product Id | F1: Item Type Name | G1: Item Type Color | H1: Item Type Size | I1: Item Type Brand | J1: Channel Name | K1: SKU Require Customization | L1: Gift Wrap | M1: Gift Message | N1: HSN Code | O1: MRP | P1: Total Price | Q1: Selling Price | R1: Cost Price | S1: Prepaid Amount | T1: Subtotal | U1: Discount | V1: GST Tax Type Code | W1: CGST | X1: IGST | Y1: SGST | Z1: UTGST | AA1: CESS | AB1: CGST Rate | AC1: IGST Rate | AD1: SGST Rate | AE1: UTGST Rate | AF1: CESS Rate | AG1: TCS Amount | AH1: Tax % | AI1: Tax Value | AJ1: Voucher Code | AK1: Shipping Charges | AL1: Shipping Method Charges | AM1: COD Service Charges | AN1: Gift Wrap Charges | AO1: Packet Number | AP1: Order Date as dd/mm/yyyy hh:MM:ss | AQ1: Sale Order Code | AR1: On Hold | AS1: Sale Order Status | AT1: Priority | AU1: Currency | AV1: Currency Conversion Rate | AW1: Sale Order Item Status | AX1: Cancellation Reason | AY1: Shipping provider | AZ1: Shipping Courier | BA1: Shipping Arranged By | BB1: Shipping Package Code | BC1: Shipping Package Creation Date | BD1: Shipping Package Status Code | BE1: Shipping Package Type | BF1: Length(mm) | BG1: Width(mm) | BH1: Height(mm) | BI1: Delivery Time | BJ1: Tracking Number | BK1: Dispatch Date | BL1: Facility | BM1: Return Date | BN1: Return Reason | BO1: Return Remarks | BP1: Created | BQ1: Updated | BR1: Combination Identifier | BS1: Combination Description | BT1: Transfer Price | BU1: Item Code | BV1: IMEI | BW1: Weight | BX1: GSTIN | BY1: Customer GSTIN | BZ1: TIN | CA1: Payment Instrument | CB1: Fulfillment TAT | CC1: Adjustment In Selling Price | CD1: Adjustment In Discount | CE1: Store Credit | CF1: IRN | CG1: Acknowledgement Number | CH1: Bundle SKU Code Number | CI1: SKU Name | CJ1: Batch Code | CK1: Vendor Batch Number | CL1: Seller SKU Code | CM1: Item Type EAN | CN1: Shipping Courier Status | CO1: Shipping Tracking Status | CP1: Item Seal Id | CQ1: Parent Sale Order Code | CR1: Item Tag | CS1: Shipment Tag | CT1: Channel Shipping | CU1: Item Details
A2: 1 | B2: Bra | C2: STD | D2: BRA-CH12-MGRN-34C | E2: BRA-CH12-MGRN-34C|BRA-CH12-MGRN-34C | F2: Padded Push Up Bra | G2: M GREEN | H2: 34C | I2: Chelvet | J2: TATACLIQ_chhawla | K2: FALSE | L2: FALSE | N2: 62121000 | O2: 1299 | P2: 722.8 | Q2: 708.3 | R2: 207 | S2: 0 | U2: 78.7 | V2: 5_18_slab | AK2: 14.5 | AL2: 0 | AM2: 0 | AN2: 0 | AO2: 1000 | AP2: 46122.735 | AQ2: 260410_044_285215 | AR2: FALSE | AS2: CANCELLED | AT2: 0 | AU2: INR | AV2: 1 | AW2: CANCELLED | AX2: cancelled on panel | BA2: Channel | BL2: Gotcha Chhawla | BP2: 46122.738 | BQ2: 46124.78 | CB2: 46125.042 | CI2: Padded Push Up Bra | CL2: BRA-CH12-MGRN-34C | CT2: TRUE
A3: 1 | B3: Bra | C3: STD | D3: BRA-CH12-COPK-34D | E3: BRA-CH12-COPK-34D|BRA-CH12-COPK-34D | F3: Padded Push Up Bra | G3: COOL PINK | H3: 34D | I3: Chelvet | J3: TATACLIQ_chhawla | K3: FALSE | L3: FALSE | N3: 62121000 | O3: 1299 | P3: 801.5 | Q3: 787 | R3: 207 | S3: 0 | T3: 749.52 | U3: 0 | V3: 5_18_slab | W3: 0 | X3: 38.17 | Y3: 0 | Z3: 0 | AA3: 0 | AB3: 0 | AC3: 5 | AD3: 0 | AE3: 0 | AF3: 0 | AG3: 0 | AK3: 14.5 | AL3: 0 | AM3: 0 | AN3: 0 | AO3: 1000 | AP3: 46125.383 | AQ3: 260413_044_321555 | AR3: FALSE | AS3: COMPLETE | AT3: 0 | AU3: INR | AV3: 1 | AW3: DISPATCHED | AY3: XC-AIR | BA3: Channel | BB3: GOTC13868 | BC3: 46125.392 | BD3: DISPATCHED | BE3: DEFAULT | BF3: 180 | BG3: 170 | BH3: 60 | BJ3: 14136900000000 | BK3: 46126.418 | BL3: Gotcha Chhawla | BN3: Return expected on panel | BP3: 46125.389 | BQ3: 46127.549 | BU3: 44664 | BW3: 200 | CB3: 46126.042 | CC3: 0 | CD3: 0 | CE3: 0 | CI3: Padded Push Up Bra | CL3: BRA-CH12-COPK-34D | CT3: TRUE
A4: 1 | B4: Bra | C4: STD | D4: BRA-CH14-NABL-36B | E4: BRA-CH14-NABL-36B|BRA-CH14-NABL-36B | F4: Full Coverage Lightly Padded Bra | G4: NAVY BLUE | H4: 36B | I4: Chelvet | J4: TATACLIQ_chhawla | K4: FALSE | L4: FALSE | N4: 62121000 | O4: 1299 | P4: 786.66 | Q4: 777 | R4: 207 | S4: 0 | T4: 740 | U4: 0 | V4: 5_18_slab | W4: 0 | X4: 37.46 | Y4: 0 | Z4: 0 | AA4: 0 | AB4: 0 | AC4: 5 | AD4: 0 | AE4: 0 | AF4: 0 | AG4: 0 | AK4: 9.66 | AL4: 0 | AM4: 0 | AN4: 0 | AO4: 1000 | AP4: 46125.949 | AQ4: 260413_044_330730 | AR4: FALSE | AS4: COMPLETE | AT4: 0 | AU4: INR | AV4: 1 | AW4: DELIVERED | AY4: XC-AIR | BA4: Channel | BB4: GOTC13978 | BC4: 46125.954 | BD4: DELIVERED | BE4: DEFAULT | BF4: 180 | BG4: 170 | BH4: 60 | BI4: 46130.68 | BJ4: 14136900000000 | BK4: 46126.772 | BL4: Gotcha Chhawla | BN4: Return expected on panel | BP4: 46125.953 | BQ4: 46131.724 | BU4: 41571 | BW4: 200 | CB4: 46127.042 | CC4: 0 | CD4: 0 | CE4: 0 | CI4: Full Coverage Lightly Padded Bra | CL4: BRA-CH14-NABL-36B | CN4: DELIVERED | CO4: STATUS_NOT_DEFINED | CT4: TRUE
A5: 1 | B5: Bra | C5: STD | D5: BRA-CH06-RUST-38B | E5: BRA-CH06-RUST-38B|BRA-CH06-RUST-38B | F5: Chic Lightly Padded T-Shirt Bra-Seamless & Non Wired | G5: RUST | H5: 38B | I5: Chelvet | J5: TATACLIQ_chhawla | K5: FALSE | L5: FALSE | N5: 62121000 | O5: 1299 | P5: 696.03 | Q5: 691.2 | R5: 207 | S5: 0 | T5: 735.09 | U5: 76.8 | V5: 5_18_slab | W5: 0 | X5: 33.14 | Y5: 0 | Z5: 0 | AA5: 0 | AB5: 0 | AC5: 5 | AD5: 0 | AE5: 0 | AF5: 0 | AG5: 0 | AK5: 4.83 | AL5: 0 | AM5: 0 | AN5: 0 | AO5: 1000 | AP5: 46126.939 | AQ5: 260414_044_343663 | AR5: FALSE | AS5: COMPLETE | AT5: 0 | AU5: INR | AV5: 1 | AW5: DELIVERED | AY5: XC-AIR | BA5: Channel | BB5: GOTC14169 | BC5: 46126.947 | BD5: DELIVERED | BE5: DEFAULT | BF5: 180 | BG5: 170 | BH5: 60 | BI5: 46130.68 | BJ5: 14136900000000 | BK5: 46128.376 | BL5: Gotcha Chhawla | BP5: 46126.945 | BQ5: 46130.68 | BU5: GOT041704 | BW5: 200 | CB5: 46128.042 | CC5: 0 | CD5: 0 | CE5: 0 | CI5: Chic Lightly Padded T-Shirt Bra-Seamless & Non Wired | CL5: BRA-CH06-RUST-38B | CN5: DELIVERED | CO5: STATUS_NOT_DEFINED | CT5: TRUE
